[{"page_content":"Tool: expense_list\nDescription: دریافت لیست تمام هزینه‌های پروژه جاری\n\nاین متد لیست هزینه‌های مرتبط با پروژه فعال را برمی‌گرداند.\nنتایج به صورت صفحه‌بندی شده و قابل مرتب‌سازی هستند.\n\nQuery Parameters:\n    - page: شماره صفحه (پیش‌فرض: 1)\n    - page_size: تعداد رکورد در هر صفحه (پیش‌فرض: 10)\n    - ordering: فیلد مرتب‌سازی با پیشوند \"-\" برای نزولی (پیش‌فرض: -created_at)\n\nReturns:\n    Response با ساختار paginated شامل results, count, next, previous\n\nمثال:\n    GET /api/v1/Expense/?page=1&page_size=20&ordering=-amount\n\nنکات:\n    - فقط هزینه‌های پروژه جاری برگردانده می‌شود\n    - نیاز به احراز هویت دارد\n\nمثال‌های استفاده:\n- GET /api/v1/Expense/?page=1&page_size=20&ordering=-amount\n\nنکات مهم:\n- - فقط هزینه‌های پروژه جاری برگردانده می‌شود\n- - نیاز به احراز هویت دارد\n\nAPI Endpoint: GET /api/v1/Expense/\nOperation ID: Expense_list\nدسته‌بندی: Expense","metadata":{"tool_name":"expense_list","category":"Expense","method":"GET","path":"/api/v1/Expense/","operation_id":"Expense_list","tags":["Expense"],"has_auth":true,"parameters":[],"response_codes":["200: array"]}},{"page_content":"Tool: expense_create\nDescription: ایجاد هزینه جدید برای پروژه جاری\n\nاین متد هزینه جدید را برای پروژه فعال ثبت می‌کند.\nپروژه به صورت خودکار از session کاربر تعیین می‌شود.\n\nRequest Body:\n    - period (الزامی): شناسه دوره متعلق به پروژه جاری\n    - expense_type (الزامی): نوع هزینه (project_manager, facilities_manager, procurement, warehouse, construction_contractor, other)\n    - amount (الزامی): مبلغ هزینه به تومان (به صورت string)\n    - description (اختیاری): توضیحات تکمیلی\n\nReturns:\n    Response با اطلاعات هزینه ایجاد شده (status 201)\n\nمثال:\n    POST /api/v1/Expense/\n    {\n        \"period\": 1,\n        \"expense_type\": \"project_manager\",\n        \"amount\": \"5000000\",\n        \"description\": \"حقوق مدیر پروژه برای ماه دسامبر\"\n    }\n\nنکات:\n    - جزئیات فیلدها در serializer descriptions موجود است\n    - پروژه به صورت خودکار از session تنظیم می‌شود\n    - نیاز به احراز هویت و دسترسی APISecurityPermission دارد\n\nپارامترها:\n- project (int, optional): شناسه پروژه. اگر مشخص نشود، از پروژه جاری session استفاده می‌شود.\n- expense_type (str): نوع هزینه. مقادیر معتبر: project_manager (مدیر پروژه), facilities_manager (سرپرست کارگاه), procurement (کارپرداز), warehouse (انباردار), construction_contractor (پیمان ساختمان), other (سایر). (الزامی)\n\n* `project_manager` - مدیر پروژه\n* `facilities_manager` - سرپرست کارگاه\n* `procurement` - کارپرداز\n* `warehouse` - انباردار\n* `construction_contractor` - پیمان ساختمان\n* `other` - سایر [required]\n- amount (str): مبلغ هزینه به تومان. باید مقدار مثبت باشد. برای جلوگیری از مشکلات دقت، به صورت string ارسال شود. (الزامی) [required]\n- description (str, optional): توضیحات تکمیلی درباره هزینه. حداکثر 500 کاراکتر. (اختیاری)\n- period (int): شناسه دوره‌ای که هزینه برای آن ثبت می‌شود. دوره باید متعلق به پروژه جاری باشد. (الزامی) [required]\n\nمثال‌های استفاده:\n- POST /api/v1/Expense/\n- {\n- \"period\": 1,\n- \"expense_type\": \"project_manager\",\n- \"amount\": \"5000000\",\n\nنکات مهم:\n- - جزئیات فیلدها در serializer descriptions موجود است\n- - پروژه به صورت خودکار از session تنظیم می‌شود\n- - نیاز به احراز هویت و دسترسی APISecurityPermission دارد\n\nAPI Endpoint: POST /api/v1/Expense/\nOperation ID: Expense_create\nدسته‌بندی: Expense","metadata":{"tool_name":"expense_create","category":"Expense","method":"POST","path":"/api/v1/Expense/","operation_id":"Expense_create","tags":["Expense"],"has_auth":true,"parameters":[{"name":"project","type":"integer","required":false,"description":"شناسه پروژه. اگر مشخص نشود، از پروژه جاری session استفاده می‌شود."},{"name":"expense_type","type":"string","required":true,"description":"نوع هزینه. مقادیر معتبر: project_manager (مدیر پروژه), facilities_manager (سرپرست کارگاه), procurement (کارپرداز), warehouse (انباردار), construction_contractor (پیمان ساختمان), other (سایر). (الزامی)\n\n* `project_manager` - مدیر پروژه\n* `facilities_manager` - سرپرست کارگاه\n* `procurement` - کارپرداز\n* `warehouse` - انباردار\n* `construction_contractor` - پیمان ساختمان\n* `other` - سایر"},{"name":"amount","type":"string","required":true,"description":"مبلغ هزینه به تومان. باید مقدار مثبت باشد. برای جلوگیری از مشکلات دقت، به صورت string ارسال شود. (الزامی)"},{"name":"description","type":"string","required":false,"description":"توضیحات تکمیلی درباره هزینه. حداکثر 500 کاراکتر. (اختیاری)"},{"name":"period","type":"integer","required":true,"description":"شناسه دوره‌ای که هزینه برای آن ثبت می‌شود. دوره باید متعلق به پروژه جاری باشد. (الزامی)"}],"response_codes":["201: Expense"]}},{"page_content":"Tool: expense_retrieve\nDescription: دریافت جزئیات یک هزینه خاص\n\nاین متد اطلاعات کامل هزینه با شناسه مشخص شده را برمی‌گرداند.\n\nURL Parameters:\n    - pk: شناسه یکتای هزینه\n\nReturns:\n    Response با اطلاعات کامل هزینه شامل period_data و period_weight\n\nمثال:\n    GET /api/v1/Expense/1/\n\nنکات:\n    - فقط هزینه‌های پروژه جاری قابل دسترسی هستند\n    - در صورت عدم دسترسی، خطای 403 برگردانده می‌شود\n    - نیاز به احراز هویت دارد\n\nپارامترها:\n- id (int): یک مقداد عدد یکتا که این هزینه را شناسایی میکند. [required]\n\nمثال‌های استفاده:\n- GET /api/v1/Expense/1/\n\nنکات مهم:\n- - فقط هزینه‌های پروژه جاری قابل دسترسی هستند\n- - در صورت عدم دسترسی، خطای 403 برگردانده می‌شود\n- - نیاز به احراز هویت دارد\n\nAPI Endpoint: GET /api/v1/Expense/{id}/\nOperation ID: Expense_retrieve\nدسته‌بندی: Expense","metadata":{"tool_name":"expense_retrieve","category":"Expense","method":"GET","path":"/api/v1/Expense/{id}/","operation_id":"Expense_retrieve","tags":["Expense"],"has_auth":true,"parameters":[{"name":"id","type":"integer","required":true,"description":"یک مقداد عدد یکتا که این هزینه را شناسایی میکند."}],"response_codes":["200: Expense"]}},{"page_content":"Tool: expense_update\nDescription: به‌روزرسانی کامل هزینه\n\nاین متد امکان تغییر همه فیلدهای یک هزینه را فراهم می‌کند.\nتمام فیلدهای قابل ویرایش باید ارسال شوند.\n\nURL Parameters:\n    - pk: شناسه یکتای هزینه\n\nRequest Body:\n    - تمام فیلدهای قابل ویرایش (period, expense_type, amount, description)\n\nReturns:\n    Response با اطلاعات به‌روزرسانی شده هزینه (status 200)\n\nمثال:\n    PUT /api/v1/Expense/1/\n    {\n        \"period\": 1,\n        \"expense_type\": \"project_manager\",\n        \"amount\": \"6000000\",\n        \"description\": \"حقوق مدیر پروژه - به‌روزرسانی شده\"\n    }\n\nنکات:\n    - همه فیلدها باید ارسال شوند (به جز project که خودکار تنظیم می‌شود)\n    - برای به‌روزرسانی جزئی از PATCH استفاده کنید\n    - جزئیات فیلدها در serializer descriptions موجود است\n    - نیاز به احراز هویت دارد\n\nپارامترها:\n- id (int): یک مقداد عدد یکتا که این هزینه را شناسایی میکند. [required]\n- project (int, optional): شناسه پروژه. اگر مشخص نشود، از پروژه جاری session استفاده می‌شود.\n- expense_type (str): نوع هزینه. مقادیر معتبر: project_manager (مدیر پروژه), facilities_manager (سرپرست کارگاه), procurement (کارپرداز), warehouse (انباردار), construction_contractor (پیمان ساختمان), other (سایر). (الزامی)\n\n* `project_manager` - مدیر پروژه\n* `facilities_manager` - سرپرست کارگاه\n* `procurement` - کارپرداز\n* `warehouse` - انباردار\n* `construction_contractor` - پیمان ساختمان\n* `other` - سایر [required]\n- amount (str): مبلغ هزینه به تومان. باید مقدار مثبت باشد. برای جلوگیری از مشکلات دقت، به صورت string ارسال شود. (الزامی) [required]\n- description (str, optional): توضیحات تکمیلی درباره هزینه. حداکثر 500 کاراکتر. (اختیاری)\n- period (int): شناسه دوره‌ای که هزینه برای آن ثبت می‌شود. دوره باید متعلق به پروژه جاری باشد. (الزامی) [required]\n\nمثال‌های استفاده:\n- PUT /api/v1/Expense/1/\n- {\n- \"period\": 1,\n- \"expense_type\": \"project_manager\",\n- \"amount\": \"6000000\",\n\nنکات مهم:\n- - همه فیلدها باید ارسال شوند (به جز project که خودکار تنظیم می‌شود)\n- - برای به‌روزرسانی جزئی از PATCH استفاده کنید\n- - جزئیات فیلدها در serializer descriptions موجود است\n- - نیاز به احراز هویت دارد\n\nAPI Endpoint: PUT /api/v1/Expense/{id}/\nOperation ID: Expense_update\nدسته‌بندی: Expense","metadata":{"tool_name":"expense_update","category":"Expense","method":"PUT","path":"/api/v1/Expense/{id}/","operation_id":"Expense_update","tags":["Expense"],"has_auth":true,"parameters":[{"name":"id","type":"integer","required":true,"description":"یک مقداد عدد یکتا که این هزینه را شناسایی میکند."},{"name":"project","type":"integer","required":false,"description":"شناسه پروژه. اگر مشخص نشود، از پروژه جاری session استفاده می‌شود."},{"name":"expense_type","type":"string","required":true,"description":"نوع هزینه. مقادیر معتبر: project_manager (مدیر پروژه), facilities_manager (سرپرست کارگاه), procurement (کارپرداز), warehouse (انباردار), construction_contractor (پیمان ساختمان), other (سایر). (الزامی)\n\n* `project_manager` - مدیر پروژه\n* `facilities_manager` - سرپرست کارگاه\n* `procurement` - کارپرداز\n* `warehouse` - انباردار\n* `construction_contractor` - پیمان ساختمان\n* `other` - سایر"},{"name":"amount","type":"string","required":true,"description":"مبلغ هزینه به تومان. باید مقدار مثبت باشد. برای جلوگیری از مشکلات دقت، به صورت string ارسال شود. (الزامی)"},{"name":"description","type":"string","required":false,"description":"توضیحات تکمیلی درباره هزینه. حداکثر 500 کاراکتر. (اختیاری)"},{"name":"period","type":"integer","required":true,"description":"شناسه دوره‌ای که هزینه برای آن ثبت می‌شود. دوره باید متعلق به پروژه جاری باشد. (الزامی)"}],"response_codes":["200: Expense"]}},{"page_content":"Tool: expense_partial_update\nDescription: به‌روزرسانی جزئی هزینه\n\nاین متد امکان تغییر بخشی از فیلدهای هزینه را فراهم می‌کند.\nفقط فیلدهای ارسال شده تغییر می‌کنند.\n\nURL Parameters:\n    - pk: شناسه یکتای هزینه\n\nRequest Body:\n    - فیلدهای انتخابی برای به‌روزرسانی (period, expense_type, amount, description)\n\nReturns:\n    Response با اطلاعات به‌روزرسانی شده هزینه (status 200)\n\nمثال:\n    PATCH /api/v1/Expense/1/\n    {\n        \"amount\": \"7000000\"\n    }\n\nنکات:\n    - فقط فیلدهای ارسال شده تغییر می‌کنند\n    - فیلدهای ارسال نشده حفظ می‌شوند\n    - انعطاف بیشتری نسبت به PUT دارد\n    - جزئیات فیلدها در serializer descriptions موجود است\n    - نیاز به احراز هویت دارد\n\nپارامترها:\n- id (int): یک مقداد عدد یکتا که این هزینه را شناسایی میکند. [required]\n- project (int, optional): شناسه پروژه. اگر مشخص نشود، از پروژه جاری session استفاده می‌شود.\n- expense_type (str, optional): نوع هزینه. مقادیر معتبر: project_manager (مدیر پروژه), facilities_manager (سرپرست کارگاه), procurement (کارپرداز), warehouse (انباردار), construction_contractor (پیمان ساختمان), other (سایر). (الزامی)\n\n* `project_manager` - مدیر پروژه\n* `facilities_manager` - سرپرست کارگاه\n* `procurement` - کارپرداز\n* `warehouse` - انباردار\n* `construction_contractor` - پیمان ساختمان\n* `other` - سایر\n- amount (str, optional): مبلغ هزینه به تومان. باید مقدار مثبت باشد. برای جلوگیری از مشکلات دقت، به صورت string ارسال شود. (الزامی)\n- description (str, optional): توضیحات تکمیلی درباره هزینه. حداکثر 500 کاراکتر. (اختیاری)\n- period (int, optional): شناسه دوره‌ای که هزینه برای آن ثبت می‌شود. دوره باید متعلق به پروژه جاری باشد. (الزامی)\n\nمثال‌های استفاده:\n- PATCH /api/v1/Expense/1/\n- {\n- \"amount\": \"7000000\"\n- }\n\nنکات مهم:\n- - فقط فیلدهای ارسال شده تغییر می‌کنند\n- - فیلدهای ارسال نشده حفظ می‌شوند\n- - انعطاف بیشتری نسبت به PUT دارد\n- - جزئیات فیلدها در serializer descriptions موجود است\n- - نیاز به احراز هویت دارد\n\nAPI Endpoint: PATCH /api/v1/Expense/{id}/\nOperation ID: Expense_partial_update\nدسته‌بندی: Expense","metadata":{"tool_name":"expense_partial_update","category":"Expense","method":"PATCH","path":"/api/v1/Expense/{id}/","operation_id":"Expense_partial_update","tags":["Expense"],"has_auth":true,"parameters":[{"name":"id","type":"integer","required":true,"description":"یک مقداد عدد یکتا که این هزینه را شناسایی میکند."},{"name":"project","type":"integer","required":false,"description":"شناسه پروژه. اگر مشخص نشود، از پروژه جاری session استفاده می‌شود."},{"name":"expense_type","type":"string","required":false,"description":"نوع هزینه. مقادیر معتبر: project_manager (مدیر پروژه), facilities_manager (سرپرست کارگاه), procurement (کارپرداز), warehouse (انباردار), construction_contractor (پیمان ساختمان), other (سایر). (الزامی)\n\n* `project_manager` - مدیر پروژه\n* `facilities_manager` - سرپرست کارگاه\n* `procurement` - کارپرداز\n* `warehouse` - انباردار\n* `construction_contractor` - پیمان ساختمان\n* `other` - سایر"},{"name":"amount","type":"string","required":false,"description":"مبلغ هزینه به تومان. باید مقدار مثبت باشد. برای جلوگیری از مشکلات دقت، به صورت string ارسال شود. (الزامی)"},{"name":"description","type":"string","required":false,"description":"توضیحات تکمیلی درباره هزینه. حداکثر 500 کاراکتر. (اختیاری)"},{"name":"period","type":"integer","required":false,"description":"شناسه دوره‌ای که هزینه برای آن ثبت می‌شود. دوره باید متعلق به پروژه جاری باشد. (الزامی)"}],"response_codes":["200: Expense"]}},{"page_content":"Tool: expense_destroy\nDescription: حذف هزینه\n\nاین متد هزینه را به‌طور کامل و برگشت‌ناپذیری حذف می‌کند.\n\nURL Parameters:\n    - pk: شناسه یکتای هزینه\n\nReturns:\n    Response خالی با status 204 No Content در صورت موفقیت\n\nمثال:\n    DELETE /api/v1/Expense/1/\n\nنکات:\n    - حذف برگشت‌ناپذیر است\n    - فقط هزینه‌های پروژه جاری قابل حذف هستند\n    - نیاز به احراز هویت و دسترسی APISecurityPermission دارد\n    - در صورت وجود وابستگی، ممکن است حذف ناموفق باشد\n\nپارامترها:\n- id (int): یک مقداد عدد یکتا که این هزینه را شناسایی میکند. [required]\n\nمثال‌های استفاده:\n- DELETE /api/v1/Expense/1/\n\nنکات مهم:\n- - حذف برگشت‌ناپذیر است\n- - فقط هزینه‌های پروژه جاری قابل حذف هستند\n- - نیاز به احراز هویت و دسترسی APISecurityPermission دارد\n- - در صورت وجود وابستگی، ممکن است حذف ناموفق باشد\n\nAPI Endpoint: DELETE /api/v1/Expense/{id}/\nOperation ID: Expense_destroy\nدسته‌بندی: Expense","metadata":{"tool_name":"expense_destroy","category":"Expense","method":"DELETE","path":"/api/v1/Expense/{id}/","operation_id":"Expense_destroy","tags":["Expense"],"has_auth":true,"parameters":[{"name":"id","type":"integer","required":true,"description":"یک مقداد عدد یکتا که این هزینه را شناسایی میکند."}],"response_codes":[]}},{"page_content":"Tool: expense_dashboard_data_retrieve\nDescription: دریافت داده‌های لیست هزینه‌ها\n\nاین endpoint داده‌های کامل داشبورد هزینه‌ها را بر اساس دوره‌ها و انواع هزینه\nبرمی‌گرداند. شامل:\n- لیست تمام دوره‌ها با هزینه‌های هر نوع\n- مجموع تجمعی هزینه‌ها\n- مجموع هر ستون (هر نوع هزینه)\n- مجموع کل همه هزینه‌ها\n\nReturns:\n    Response: شامل:\n        - periods: لیست دوره‌ها با هزینه‌های هر نوع\n        - expense_types: انواع هزینه‌ها\n        - column_totals: مجموع هر نوع هزینه در تمام دوره‌ها\n        - grand_total: مجموع کل همه هزینه‌ها\n\nنکات مهم:\n- فقط هزینه‌های پروژه جاری را برمی‌گرداند\n- اگر پروژه جاری وجود نداشته باشد، خطای 400 برمی‌گرداند\n- داده‌ها بر اساس دوره مرتب می‌شوند\n\nمثال‌های استفاده:\n- expense_dashboard_data_retrieve()\n\nنکات مهم:\n- - فقط هزینه‌های پروژه جاری را برمی‌گرداند\n- - اگر پروژه جاری وجود نداشته باشد، خطای 400 برمی‌گرداند\n- - داده‌ها بر اساس دوره مرتب می‌شوند\n\nAPI Endpoint: GET /api/v1/Expense/dashboard_data/\nOperation ID: Expense_dashboard_data_retrieve\nدسته‌بندی: Expense","metadata":{"tool_name":"expense_dashboard_data_retrieve","category":"Expense","method":"GET","path":"/api/v1/Expense/dashboard_data/","operation_id":"Expense_dashboard_data_retrieve","tags":["Expense"],"has_auth":true,"parameters":[],"response_codes":["200: Expense"]}},{"page_content":"Tool: expense_get_expense_details_retrieve\nDescription: دریافت جزئیات هزینه برای ویرایش\n\nمثال‌های استفاده:\n- expense_get_expense_details_retrieve()\n\nنکات مهم:\n- نیاز به احراز هویت دارد\n\nAPI Endpoint: GET /api/v1/Expense/get_expense_details/\nOperation ID: Expense_get_expense_details_retrieve\nدسته‌بندی: Expense","metadata":{"tool_name":"expense_get_expense_details_retrieve","category":"Expense","method":"GET","path":"/api/v1/Expense/get_expense_details/","operation_id":"Expense_get_expense_details_retrieve","tags":["Expense"],"has_auth":true,"parameters":[],"response_codes":["200: Expense"]}},{"page_content":"Tool: expense_total_expenses_retrieve\nDescription: دریافت مجموع کل هزینه‌های پروژه\n\nمثال‌های استفاده:\n- expense_total_expenses_retrieve()\n\nنکات مهم:\n- نیاز به احراز هویت دارد\n\nAPI Endpoint: GET /api/v1/Expense/total_expenses/\nOperation ID: Expense_total_expenses_retrieve\nدسته‌بندی: Expense","metadata":{"tool_name":"expense_total_expenses_retrieve","category":"Expense","method":"GET","path":"/api/v1/Expense/total_expenses/","operation_id":"Expense_total_expenses_retrieve","tags":["Expense"],"has_auth":true,"parameters":[],"response_codes":["200: Expense"]}},{"page_content":"Tool: expense_update_expense_create\nDescription: به‌روزرسانی یا ایجاد هزینه برای یک دوره و نوع خاص\n\nاین endpoint امکان به‌روزرسانی یا ایجاد هزینه برای یک دوره و نوع خاص را فراهم می‌کند.\nاگر هزینه وجود داشته باشد، به‌روزرسانی می‌شود؛ در غیر این صورت ایجاد می‌شود.\n\nParameters:\n    period_id (int): شناسه دوره\n    expense_type (str): نوع هزینه (project_manager, facilities_manager, ...)\n    amount (float/str): مبلغ هزینه\n    description (str, optional): توضیحات هزینه\n\nReturns:\n    Response: شامل:\n        - success: وضعیت موفقیت\n        - message: پیام پاسخ\n        - data: شامل expense_id, amount, description, created\n\nنکات مهم:\n- هزینه بر اساس پروژه جاری (active project) از session شناسایی می‌شود\n- اگر هزینه وجود داشته باشد، به‌روزرسانی می‌شود؛ در غیر این صورت ایجاد می‌شود\n- مبلغ باید به صورت string ارسال شود تا از مشکلات precision جلوگیری شود\n- نیاز به احراز هویت دارد (IsAuthenticated)\n\nپارامترها:\n- project (int, optional): شناسه پروژه. اگر مشخص نشود، از پروژه جاری session استفاده می‌شود.\n- expense_type (str): نوع هزینه. مقادیر معتبر: project_manager (مدیر پروژه), facilities_manager (سرپرست کارگاه), procurement (کارپرداز), warehouse (انباردار), construction_contractor (پیمان ساختمان), other (سایر). (الزامی)\n\n* `project_manager` - مدیر پروژه\n* `facilities_manager` - سرپرست کارگاه\n* `procurement` - کارپرداز\n* `warehouse` - انباردار\n* `construction_contractor` - پیمان ساختمان\n* `other` - سایر [required]\n- amount (str): مبلغ هزینه به تومان. باید مقدار مثبت باشد. برای جلوگیری از مشکلات دقت، به صورت string ارسال شود. (الزامی) [required]\n- description (str, optional): توضیحات تکمیلی درباره هزینه. حداکثر 500 کاراکتر. (اختیاری)\n- period (int): شناسه دوره‌ای که هزینه برای آن ثبت می‌شود. دوره باید متعلق به پروژه جاری باشد. (الزامی) [required]\n\nمثال‌های استفاده:\n- expense_update_expense_create(project=1, expense_type='value', amount='value', description='value', period=1)\n\nنکات مهم:\n- - هزینه بر اساس پروژه جاری (active project) از session شناسایی می‌شود\n- - اگر هزینه وجود داشته باشد، به‌روزرسانی می‌شود؛ در غیر این صورت ایجاد می‌شود\n- - مبلغ باید به صورت string ارسال شود تا از مشکلات precision جلوگیری شود\n- - نیاز به احراز هویت دارد (IsAuthenticated)\n\nAPI Endpoint: POST /api/v1/Expense/update_expense/\nOperation ID: Expense_update_expense_create\nدسته‌بندی: Expense","metadata":{"tool_name":"expense_update_expense_create","category":"Expense","method":"POST","path":"/api/v1/Expense/update_expense/","operation_id":"Expense_update_expense_create","tags":["Expense"],"has_auth":true,"parameters":[{"name":"project","type":"integer","required":false,"description":"شناسه پروژه. اگر مشخص نشود، از پروژه جاری session استفاده می‌شود."},{"name":"expense_type","type":"string","required":true,"description":"نوع هزینه. مقادیر معتبر: project_manager (مدیر پروژه), facilities_manager (سرپرست کارگاه), procurement (کارپرداز), warehouse (انباردار), construction_contractor (پیمان ساختمان), other (سایر). (الزامی)\n\n* `project_manager` - مدیر پروژه\n* `facilities_manager` - سرپرست کارگاه\n* `procurement` - کارپرداز\n* `warehouse` - انباردار\n* `construction_contractor` - پیمان ساختمان\n* `other` - سایر"},{"name":"amount","type":"string","required":true,"description":"مبلغ هزینه به تومان. باید مقدار مثبت باشد. برای جلوگیری از مشکلات دقت، به صورت string ارسال شود. (الزامی)"},{"name":"description","type":"string","required":false,"description":"توضیحات تکمیلی درباره هزینه. حداکثر 500 کاراکتر. (اختیاری)"},{"name":"period","type":"integer","required":true,"description":"شناسه دوره‌ای که هزینه برای آن ثبت می‌شود. دوره باید متعلق به پروژه جاری باشد. (الزامی)"}],"response_codes":["200: Expense"]}},{"page_content":"Tool: expense_with_periods_retrieve\nDescription: دریافت هزینه‌ها با اطلاعات دوره‌ها برای محاسبه دوره متوسط ساخت\n\nمثال‌های استفاده:\n- expense_with_periods_retrieve()\n\nنکات مهم:\n- نیاز به احراز هویت دارد\n\nAPI Endpoint: GET /api/v1/Expense/with_periods/\nOperation ID: Expense_with_periods_retrieve\nدسته‌بندی: Expense","metadata":{"tool_name":"expense_with_periods_retrieve","category":"Expense","method":"GET","path":"/api/v1/Expense/with_periods/","operation_id":"Expense_with_periods_retrieve","tags":["Expense"],"has_auth":true,"parameters":[],"response_codes":["200: Expense"]}},{"page_content":"Tool: interestrate_list\nDescription: دریافت لیست تمام نرخ‌های سود پروژه جاری\n\nاین متد لیست نرخ‌های سود مرتبط با پروژه فعال را برمی‌گرداند.\nنتایج به صورت صفحه‌بندی شده و قابل مرتب‌سازی هستند.\n\nQuery Parameters:\n    - page: شماره صفحه (پیش‌فرض: 1)\n    - page_size: تعداد رکورد در هر صفحه (پیش‌فرض: 10)\n    - ordering: فیلد مرتب‌سازی\n\nReturns:\n    Response با ساختار paginated شامل results, count, next, previous\n\nمثال:\n    GET /api/v1/InterestRate/?page=1\n\nنکات:\n    - فقط نرخ‌های سود پروژه جاری برگردانده می‌شود\n    - نیاز به احراز هویت دارد\n\nمثال‌های استفاده:\n- GET /api/v1/InterestRate/?page=1\n\nنکات مهم:\n- - فقط نرخ‌های سود پروژه جاری برگردانده می‌شود\n- - نیاز به احراز هویت دارد\n\nAPI Endpoint: GET /api/v1/InterestRate/\nOperation ID: InterestRate_list\nدسته‌بندی: InterestRate","metadata":{"tool_name":"interestrate_list","category":"InterestRate","method":"GET","path":"/api/v1/InterestRate/","operation_id":"InterestRate_list","tags":["InterestRate"],"has_auth":true,"parameters":[],"response_codes":["200: array"]}},{"page_content":"Tool: interestrate_create\nDescription: ایجاد نرخ سود جدید برای پروژه جاری\n\nاین متد نرخ سود جدید را برای پروژه فعال ثبت می‌کند.\nپروژه به صورت خودکار از session کاربر تعیین می‌شود.\n\nRequest Body:\n    - rate (الزامی): نرخ سود روزانه (به صورت string)\n    - effective_date (الزامی): تاریخ اعمال شمسی (YYYY-MM-DD)\n    - description (اختیاری): توضیحات\n    - is_active (اختیاری): فعال/غیرفعال (پیش‌فرض: True)\n\nReturns:\n    Response با اطلاعات نرخ سود ایجاد شده (status 201)\n\nمثال:\n    POST /api/v1/InterestRate/\n    {\n        \"rate\": \"0.000481925679775\",\n        \"effective_date\": \"1403-01-01\",\n        \"description\": \"نرخ سود جدید از ابتدای سال 1403\",\n        \"is_active\": true\n    }\n\nنکات:\n    - جزئیات فیلدها در serializer descriptions موجود است\n    - پروژه به صورت خودکار از session تنظیم می‌شود\n    - تاریخ میلادی به صورت خودکار محاسبه می‌شود\n    - نیاز به احراز هویت و دسترسی APISecurityPermission دارد\n\nپارامترها:\n- project (int, optional): شناسه پروژه. اگر مشخص نشود، از پروژه جاری session استفاده می‌شود.\n- rate (str): نرخ سود روزانه (به صورت اعشاری، مثال: 0.000481925679775). برای جلوگیری از مشکلات دقت، به صورت string ارسال شود. (الزامی) [required]\n- effective_date (str): تاریخ اعمال نرخ سود به شمسی به فرمت YYYY-MM-DD (مثال: 1403-01-01). (الزامی) [required]\n- description (str, optional): توضیحات درباره تغییر نرخ سود. (اختیاری)\n- is_active (bool, optional): آیا این نرخ در حال حاضر فعال است؟ (پیش‌فرض: True)\n\nمثال‌های استفاده:\n- POST /api/v1/InterestRate/\n- {\n- \"rate\": \"0.000481925679775\",\n- \"effective_date\": \"1403-01-01\",\n- \"description\": \"نرخ سود جدید از ابتدای سال 1403\",\n\nنکات مهم:\n- - جزئیات فیلدها در serializer descriptions موجود است\n- - پروژه به صورت خودکار از session تنظیم می‌شود\n- - تاریخ میلادی به صورت خودکار محاسبه می‌شود\n- - نیاز به احراز هویت و دسترسی APISecurityPermission دارد\n\nAPI Endpoint: POST /api/v1/InterestRate/\nOperation ID: InterestRate_create\nدسته‌بندی: InterestRate","metadata":{"tool_name":"interestrate_create","category":"InterestRate","method":"POST","path":"/api/v1/InterestRate/","operation_id":"InterestRate_create","tags":["InterestRate"],"has_auth":true,"parameters":[{"name":"project","type":"integer","required":false,"description":"شناسه پروژه. اگر مشخص نشود، از پروژه جاری session استفاده می‌شود."},{"name":"rate","type":"string","required":true,"description":"نرخ سود روزانه (به صورت اعشاری، مثال: 0.000481925679775). برای جلوگیری از مشکلات دقت، به صورت string ارسال شود. (الزامی)"},{"name":"effective_date","type":"string","required":true,"description":"تاریخ اعمال نرخ سود به شمسی به فرمت YYYY-MM-DD (مثال: 1403-01-01). (الزامی)"},{"name":"description","type":"string","required":false,"description":"توضیحات درباره تغییر نرخ سود. (اختیاری)"},{"name":"is_active","type":"boolean","required":false,"description":"آیا این نرخ در حال حاضر فعال است؟ (پیش‌فرض: True)"}],"response_codes":["201: InterestRate"]}},{"page_content":"Tool: interestrate_retrieve\nDescription: دریافت جزئیات یک نرخ سود خاص\n\nاین متد اطلاعات کامل نرخ سود با شناسه مشخص شده را برمی‌گرداند.\n\nURL Parameters:\n    - pk: شناسه یکتای نرخ سود\n\nReturns:\n    Response با اطلاعات کامل نرخ سود\n\nمثال:\n    GET /api/v1/InterestRate/1/\n\nنکات:\n    - فقط نرخ‌های سود پروژه جاری قابل دسترسی هستند\n    - در صورت عدم دسترسی، خطای 403 برگردانده می‌شود\n    - نیاز به احراز هویت دارد\n\nپارامترها:\n- id (int): یک مقداد عدد یکتا که این نرخ سود را شناسایی میکند. [required]\n\nمثال‌های استفاده:\n- GET /api/v1/InterestRate/1/\n\nنکات مهم:\n- - فقط نرخ‌های سود پروژه جاری قابل دسترسی هستند\n- - در صورت عدم دسترسی، خطای 403 برگردانده می‌شود\n- - نیاز به احراز هویت دارد\n\nAPI Endpoint: GET /api/v1/InterestRate/{id}/\nOperation ID: InterestRate_retrieve\nدسته‌بندی: InterestRate","metadata":{"tool_name":"interestrate_retrieve","category":"InterestRate","method":"GET","path":"/api/v1/InterestRate/{id}/","operation_id":"InterestRate_retrieve","tags":["InterestRate"],"has_auth":true,"parameters":[{"name":"id","type":"integer","required":true,"description":"یک مقداد عدد یکتا که این نرخ سود را شناسایی میکند."}],"response_codes":["200: InterestRate"]}},{"page_content":"Tool: interestrate_update\nDescription: به‌روزرسانی کامل نرخ سود\n\nاین متد امکان تغییر همه فیلدهای یک نرخ سود را فراهم می‌کند.\nتمام فیلدهای قابل ویرایش باید ارسال شوند.\n\nURL Parameters:\n    - pk: شناسه یکتای نرخ سود\n\nRequest Body:\n    - تمام فیلدهای قابل ویرایش\n\nReturns:\n    Response با اطلاعات به‌روزرسانی شده نرخ سود (status 200)\n\nمثال:\n    PUT /api/v1/InterestRate/1/\n    {\n        \"rate\": \"0.000500000000000\",\n        \"effective_date\": \"1403-07-01\",\n        \"is_active\": true\n    }\n\nنکات:\n    - همه فیلدها باید ارسال شوند\n    - برای به‌روزرسانی جزئی از PATCH استفاده کنید\n    - جزئیات فیلدها در serializer descriptions موجود است\n    - نیاز به احراز هویت دارد\n\nپارامترها:\n- id (int): یک مقداد عدد یکتا که این نرخ سود را شناسایی میکند. [required]\n- project (int, optional): شناسه پروژه. اگر مشخص نشود، از پروژه جاری session استفاده می‌شود.\n- rate (str): نرخ سود روزانه (به صورت اعشاری، مثال: 0.000481925679775). برای جلوگیری از مشکلات دقت، به صورت string ارسال شود. (الزامی) [required]\n- effective_date (str): تاریخ اعمال نرخ سود به شمسی به فرمت YYYY-MM-DD (مثال: 1403-01-01). (الزامی) [required]\n- description (str, optional): توضیحات درباره تغییر نرخ سود. (اختیاری)\n- is_active (bool, optional): آیا این نرخ در حال حاضر فعال است؟ (پیش‌فرض: True)\n\nمثال‌های استفاده:\n- PUT /api/v1/InterestRate/1/\n- {\n- \"rate\": \"0.000500000000000\",\n- \"effective_date\": \"1403-07-01\",\n- \"is_active\": true\n\nنکات مهم:\n- - همه فیلدها باید ارسال شوند\n- - برای به‌روزرسانی جزئی از PATCH استفاده کنید\n- - جزئیات فیلدها در serializer descriptions موجود است\n- - نیاز به احراز هویت دارد\n\nAPI Endpoint: PUT /api/v1/InterestRate/{id}/\nOperation ID: InterestRate_update\nدسته‌بندی: InterestRate","metadata":{"tool_name":"interestrate_update","category":"InterestRate","method":"PUT","path":"/api/v1/InterestRate/{id}/","operation_id":"InterestRate_update","tags":["InterestRate"],"has_auth":true,"parameters":[{"name":"id","type":"integer","required":true,"description":"یک مقداد عدد یکتا که این نرخ سود را شناسایی میکند."},{"name":"project","type":"integer","required":false,"description":"شناسه پروژه. اگر مشخص نشود، از پروژه جاری session استفاده می‌شود."},{"name":"rate","type":"string","required":true,"description":"نرخ سود روزانه (به صورت اعشاری، مثال: 0.000481925679775). برای جلوگیری از مشکلات دقت، به صورت string ارسال شود. (الزامی)"},{"name":"effective_date","type":"string","required":true,"description":"تاریخ اعمال نرخ سود به شمسی به فرمت YYYY-MM-DD (مثال: 1403-01-01). (الزامی)"},{"name":"description","type":"string","required":false,"description":"توضیحات درباره تغییر نرخ سود. (اختیاری)"},{"name":"is_active","type":"boolean","required":false,"description":"آیا این نرخ در حال حاضر فعال است؟ (پیش‌فرض: True)"}],"response_codes":["200: InterestRate"]}},{"page_content":"Tool: interestrate_partial_update\nDescription: به‌روزرسانی جزئی نرخ سود\n\nاین متد امکان تغییر بخشی از فیلدهای نرخ سود را فراهم می‌کند.\nفقط فیلدهای ارسال شده تغییر می‌کنند.\n\nURL Parameters:\n    - pk: شناسه یکتای نرخ سود\n\nRequest Body:\n    - فیلدهای انتخابی برای به‌روزرسانی\n\nReturns:\n    Response با اطلاعات به‌روزرسانی شده نرخ سود (status 200)\n\nمثال:\n    PATCH /api/v1/InterestRate/1/\n    {\n        \"is_active\": false\n    }\n\nنکات:\n    - فقط فیلدهای ارسال شده تغییر می‌کنند\n    - فیلدهای ارسال نشده حفظ می‌شوند\n    - انعطاف بیشتری نسبت به PUT دارد\n    - جزئیات فیلدها در serializer descriptions موجود است\n    - نیاز به احراز هویت دارد\n\nپارامترها:\n- id (int): یک مقداد عدد یکتا که این نرخ سود را شناسایی میکند. [required]\n- project (int, optional): شناسه پروژه. اگر مشخص نشود، از پروژه جاری session استفاده می‌شود.\n- rate (str, optional): نرخ سود روزانه (به صورت اعشاری، مثال: 0.000481925679775). برای جلوگیری از مشکلات دقت، به صورت string ارسال شود. (الزامی)\n- effective_date (str, optional): تاریخ اعمال نرخ سود به شمسی به فرمت YYYY-MM-DD (مثال: 1403-01-01). (الزامی)\n- description (str, optional): توضیحات درباره تغییر نرخ سود. (اختیاری)\n- is_active (bool, optional): آیا این نرخ در حال حاضر فعال است؟ (پیش‌فرض: True)\n\nمثال‌های استفاده:\n- PATCH /api/v1/InterestRate/1/\n- {\n- \"is_active\": false\n- }\n\nنکات مهم:\n- - فقط فیلدهای ارسال شده تغییر می‌کنند\n- - فیلدهای ارسال نشده حفظ می‌شوند\n- - انعطاف بیشتری نسبت به PUT دارد\n- - جزئیات فیلدها در serializer descriptions موجود است\n- - نیاز به احراز هویت دارد\n\nAPI Endpoint: PATCH /api/v1/InterestRate/{id}/\nOperation ID: InterestRate_partial_update\nدسته‌بندی: InterestRate","metadata":{"tool_name":"interestrate_partial_update","category":"InterestRate","method":"PATCH","path":"/api/v1/InterestRate/{id}/","operation_id":"InterestRate_partial_update","tags":["InterestRate"],"has_auth":true,"parameters":[{"name":"id","type":"integer","required":true,"description":"یک مقداد عدد یکتا که این نرخ سود را شناسایی میکند."},{"name":"project","type":"integer","required":false,"description":"شناسه پروژه. اگر مشخص نشود، از پروژه جاری session استفاده می‌شود."},{"name":"rate","type":"string","required":false,"description":"نرخ سود روزانه (به صورت اعشاری، مثال: 0.000481925679775). برای جلوگیری از مشکلات دقت، به صورت string ارسال شود. (الزامی)"},{"name":"effective_date","type":"string","required":false,"description":"تاریخ اعمال نرخ سود به شمسی به فرمت YYYY-MM-DD (مثال: 1403-01-01). (الزامی)"},{"name":"description","type":"string","required":false,"description":"توضیحات درباره تغییر نرخ سود. (اختیاری)"},{"name":"is_active","type":"boolean","required":false,"description":"آیا این نرخ در حال حاضر فعال است؟ (پیش‌فرض: True)"}],"response_codes":["200: InterestRate"]}},{"page_content":"Tool: interestrate_destroy\nDescription: حذف نرخ سود\n\nاین متد نرخ سود را به‌طور کامل و برگشت‌ناپذیری حذف می‌کند.\n\nURL Parameters:\n    - pk: شناسه یکتای نرخ سود\n\nReturns:\n    Response خالی با status 204 No Content در صورت موفقیت\n\nمثال:\n    DELETE /api/v1/InterestRate/1/\n\nنکات:\n    - حذف برگشت‌ناپذیر است\n    - فقط نرخ‌های سود پروژه جاری قابل حذف هستند\n    - نیاز به احراز هویت و دسترسی APISecurityPermission دارد\n    - در صورت وجود وابستگی (تراکنش‌ها)، ممکن است حذف ناموفق باشد\n\nپارامترها:\n- id (int): یک مقداد عدد یکتا که این نرخ سود را شناسایی میکند. [required]\n\nمثال‌های استفاده:\n- DELETE /api/v1/InterestRate/1/\n\nنکات مهم:\n- - حذف برگشت‌ناپذیر است\n- - فقط نرخ‌های سود پروژه جاری قابل حذف هستند\n- - نیاز به احراز هویت و دسترسی APISecurityPermission دارد\n- - در صورت وجود وابستگی (تراکنش‌ها)، ممکن است حذف ناموفق باشد\n\nAPI Endpoint: DELETE /api/v1/InterestRate/{id}/\nOperation ID: InterestRate_destroy\nدسته‌بندی: InterestRate","metadata":{"tool_name":"interestrate_destroy","category":"InterestRate","method":"DELETE","path":"/api/v1/InterestRate/{id}/","operation_id":"InterestRate_destroy","tags":["InterestRate"],"has_auth":true,"parameters":[{"name":"id","type":"integer","required":true,"description":"یک مقداد عدد یکتا که این نرخ سود را شناسایی میکند."}],"response_codes":[]}},{"page_content":"Tool: interestrate_current_retrieve\nDescription: دریافت نرخ سود فعال فعلی برای پروژه فعال\n\nمثال‌های استفاده:\n- interestrate_current_retrieve()\n\nنکات مهم:\n- نیاز به احراز هویت دارد\n\nAPI Endpoint: GET /api/v1/InterestRate/current/\nOperation ID: InterestRate_current_retrieve\nدسته‌بندی: InterestRate","metadata":{"tool_name":"interestrate_current_retrieve","category":"InterestRate","method":"GET","path":"/api/v1/InterestRate/current/","operation_id":"InterestRate_current_retrieve","tags":["InterestRate"],"has_auth":true,"parameters":[],"response_codes":["200: InterestRate"]}},{"page_content":"Tool: investor_list\nDescription: دریافت لیست تمام سرمایه‌گذاران پروژه جاری\n\nاین متد لیست سرمایه‌گذاران مرتبط با پروژه فعال را برمی‌گرداند.\nنتایج به صورت صفحه‌بندی شده و قابل مرتب‌سازی هستند.\n\nQuery Parameters:\n    - page: شماره صفحه (پیش‌فرض: 1)\n    - page_size: تعداد رکورد در هر صفحه (پیش‌فرض: 10)\n    - ordering: فیلد مرتب‌سازی با پیشوند \"-\" برای نزولی\n\nReturns:\n    Response با ساختار paginated شامل results, count, next, previous\n\nمثال:\n    GET /api/v1/Investor/?page=1&page_size=20\n\nنکات:\n    - فقط سرمایه‌گذاران پروژه جاری برگردانده می‌شود\n    - نیاز به احراز هویت دارد\n\nمثال‌های استفاده:\n- GET /api/v1/Investor/?page=1&page_size=20\n\nنکات مهم:\n- - فقط سرمایه‌گذاران پروژه جاری برگردانده می‌شود\n- - نیاز به احراز هویت دارد\n\nAPI Endpoint: GET /api/v1/Investor/\nOperation ID: Investor_list\nدسته‌بندی: Investor","metadata":{"tool_name":"investor_list","category":"Investor","method":"GET","path":"/api/v1/Investor/","operation_id":"Investor_list","tags":["Investor"],"has_auth":true,"parameters":[],"response_codes":["200: array"]}},{"page_content":"Tool: investor_create\nDescription: ایجاد سرمایه‌گذار جدید برای پروژه جاری\n\nاین متد سرمایه‌گذار جدید را برای پروژه فعال ثبت می‌کند.\nپروژه به صورت خودکار از session کاربر تعیین می‌شود.\n\nRequest Body:\n    - first_name (الزامی): نام سرمایه‌گذار\n    - last_name (الزامی): نام خانوادگی سرمایه‌گذار\n    - phone (الزامی): شماره تماس\n    - email (اختیاری): آدرس ایمیل\n    - participation_type (اختیاری): نوع مشارکت (owner, investor)\n    - contract_date_shamsi (اختیاری): تاریخ قرارداد شمسی\n    - description (اختیاری): توضیحات\n\nReturns:\n    Response با اطلاعات سرمایه‌گذار ایجاد شده (status 201)\n\nمثال:\n    POST /api/v1/Investor/\n    {\n        \"first_name\": \"علی\",\n        \"last_name\": \"احمدی\",\n        \"phone\": \"09123456789\",\n        \"email\": \"ali@example.com\",\n        \"participation_type\": \"owner\",\n        \"description\": \"مالک واحد 101\"\n    }\n\nنکات:\n    - جزئیات فیلدها در serializer descriptions موجود است\n    - پروژه به صورت خودکار از session تنظیم می‌شود\n    - نیاز به احراز هویت و دسترسی APISecurityPermission دارد\n\nپارامترها:\n- project (int, optional): شناسه پروژه. اگر مشخص نشود، از پروژه جاری session استفاده می‌شود.\n- first_name (str): نام سرمایه‌گذار. (الزامی) [required]\n- last_name (str): نام خانوادگی سرمایه‌گذار. (الزامی) [required]\n- phone (str): شماره تماس سرمایه‌گذار. (الزامی) [required]\n- email (str, optional): آدرس ایمیل سرمایه‌گذار. (اختیاری) (ایمیل)\n- participation_type (str, optional): نوع مشارکت. مقادیر معتبر: owner (مالک), investor (سرمایه‌گذار). (پیش‌فرض: owner)\n\n* `owner` - مالک\n* `investor` - سرمایه‌گذار\n- contract_date_shamsi (str, optional): تاریخ قرارداد به شمسی. (اختیاری) (فرمت: YYYY-MM-DD)\n- description (str, optional): توضیحات تکمیلی درباره سرمایه‌گذار. (اختیاری)\n\nمثال‌های استفاده:\n- POST /api/v1/Investor/\n- {\n- \"first_name\": \"علی\",\n- \"last_name\": \"احمدی\",\n- \"phone\": \"09123456789\",\n\nنکات مهم:\n- - جزئیات فیلدها در serializer descriptions موجود است\n- - پروژه به صورت خودکار از session تنظیم می‌شود\n- - نیاز به احراز هویت و دسترسی APISecurityPermission دارد\n\nAPI Endpoint: POST /api/v1/Investor/\nOperation ID: Investor_create\nدسته‌بندی: Investor","metadata":{"tool_name":"investor_create","category":"Investor","method":"POST","path":"/api/v1/Investor/","operation_id":"Investor_create","tags":["Investor"],"has_auth":true,"parameters":[{"name":"project","type":"integer","required":false,"description":"شناسه پروژه. اگر مشخص نشود، از پروژه جاری session استفاده می‌شود."},{"name":"first_name","type":"string","required":true,"description":"نام سرمایه‌گذار. (الزامی)"},{"name":"last_name","type":"string","required":true,"description":"نام خانوادگی سرمایه‌گذار. (الزامی)"},{"name":"phone","type":"string","required":true,"description":"شماره تماس سرمایه‌گذار. (الزامی)"},{"name":"email","type":"string","required":false,"description":"آدرس ایمیل سرمایه‌گذار. (اختیاری)"},{"name":"participation_type","type":"string","required":false,"description":"نوع مشارکت. مقادیر معتبر: owner (مالک), investor (سرمایه‌گذار). (پیش‌فرض: owner)\n\n* `owner` - مالک\n* `investor` - سرمایه‌گذار"},{"name":"contract_date_shamsi","type":"string","required":false,"description":"تاریخ قرارداد به شمسی. (اختیاری)"},{"name":"description","type":"string","required":false,"description":"توضیحات تکمیلی درباره سرمایه‌گذار. (اختیاری)"}],"response_codes":["201: Investor"]}},{"page_content":"Tool: investor_retrieve\nDescription: دریافت جزئیات یک سرمایه‌گذار خاص\n\nاین متد اطلاعات کامل سرمایه‌گذار با شناسه مشخص شده را برمی‌گرداند.\n\nURL Parameters:\n    - pk: شناسه یکتای سرمایه‌گذار\n\nReturns:\n    Response با اطلاعات کامل سرمایه‌گذار شامل units\n\nمثال:\n    GET /api/v1/Investor/1/\n\nنکات:\n    - فقط سرمایه‌گذاران پروژه جاری قابل دسترسی هستند\n    - در صورت عدم دسترسی، خطای 403 برگردانده می‌شود\n    - نیاز به احراز هویت دارد\n\nپارامترها:\n- id (int): یک مقداد عدد یکتا که این سرمایه‌گذار را شناسایی میکند. [required]\n\nمثال‌های استفاده:\n- GET /api/v1/Investor/1/\n\nنکات مهم:\n- - فقط سرمایه‌گذاران پروژه جاری قابل دسترسی هستند\n- - در صورت عدم دسترسی، خطای 403 برگردانده می‌شود\n- - نیاز به احراز هویت دارد\n\nAPI Endpoint: GET /api/v1/Investor/{id}/\nOperation ID: Investor_retrieve\nدسته‌بندی: Investor","metadata":{"tool_name":"investor_retrieve","category":"Investor","method":"GET","path":"/api/v1/Investor/{id}/","operation_id":"Investor_retrieve","tags":["Investor"],"has_auth":true,"parameters":[{"name":"id","type":"integer","required":true,"description":"یک مقداد عدد یکتا که این سرمایه‌گذار را شناسایی میکند."}],"response_codes":["200: Investor"]}},{"page_content":"Tool: investor_update\nDescription: به‌روزرسانی کامل سرمایه‌گذار\n\nاین متد امکان تغییر همه فیلدهای یک سرمایه‌گذار را فراهم می‌کند.\nتمام فیلدهای قابل ویرایش باید ارسال شوند.\n\nURL Parameters:\n    - pk: شناسه یکتای سرمایه‌گذار\n\nRequest Body:\n    - تمام فیلدهای قابل ویرایش\n\nReturns:\n    Response با اطلاعات به‌روزرسانی شده سرمایه‌گذار (status 200)\n\nمثال:\n    PUT /api/v1/Investor/1/\n    {\n        \"first_name\": \"علی\",\n        \"last_name\": \"احمدی\",\n        \"phone\": \"09123456789\",\n        \"participation_type\": \"owner\"\n    }\n\nنکات:\n    - همه فیلدها باید ارسال شوند\n    - برای به‌روزرسانی جزئی از PATCH استفاده کنید\n    - جزئیات فیلدها در serializer descriptions موجود است\n    - نیاز به احراز هویت دارد\n\nپارامترها:\n- id (int): یک مقداد عدد یکتا که این سرمایه‌گذار را شناسایی میکند. [required]\n- project (int, optional): شناسه پروژه. اگر مشخص نشود، از پروژه جاری session استفاده می‌شود.\n- first_name (str): نام سرمایه‌گذار. (الزامی) [required]\n- last_name (str): نام خانوادگی سرمایه‌گذار. (الزامی) [required]\n- phone (str): شماره تماس سرمایه‌گذار. (الزامی) [required]\n- email (str, optional): آدرس ایمیل سرمایه‌گذار. (اختیاری) (ایمیل)\n- participation_type (str, optional): نوع مشارکت. مقادیر معتبر: owner (مالک), investor (سرمایه‌گذار). (پیش‌فرض: owner)\n\n* `owner` - مالک\n* `investor` - سرمایه‌گذار\n- contract_date_shamsi (str, optional): تاریخ قرارداد به شمسی. (اختیاری) (فرمت: YYYY-MM-DD)\n- description (str, optional): توضیحات تکمیلی درباره سرمایه‌گذار. (اختیاری)\n\nمثال‌های استفاده:\n- PUT /api/v1/Investor/1/\n- {\n- \"first_name\": \"علی\",\n- \"last_name\": \"احمدی\",\n- \"phone\": \"09123456789\",\n\nنکات مهم:\n- - همه فیلدها باید ارسال شوند\n- - برای به‌روزرسانی جزئی از PATCH استفاده کنید\n- - جزئیات فیلدها در serializer descriptions موجود است\n- - نیاز به احراز هویت دارد\n\nAPI Endpoint: PUT /api/v1/Investor/{id}/\nOperation ID: Investor_update\nدسته‌بندی: Investor","metadata":{"tool_name":"investor_update","category":"Investor","method":"PUT","path":"/api/v1/Investor/{id}/","operation_id":"Investor_update","tags":["Investor"],"has_auth":true,"parameters":[{"name":"id","type":"integer","required":true,"description":"یک مقداد عدد یکتا که این سرمایه‌گذار را شناسایی میکند."},{"name":"project","type":"integer","required":false,"description":"شناسه پروژه. اگر مشخص نشود، از پروژه جاری session استفاده می‌شود."},{"name":"first_name","type":"string","required":true,"description":"نام سرمایه‌گذار. (الزامی)"},{"name":"last_name","type":"string","required":true,"description":"نام خانوادگی سرمایه‌گذار. (الزامی)"},{"name":"phone","type":"string","required":true,"description":"شماره تماس سرمایه‌گذار. (الزامی)"},{"name":"email","type":"string","required":false,"description":"آدرس ایمیل سرمایه‌گذار. (اختیاری)"},{"name":"participation_type","type":"string","required":false,"description":"نوع مشارکت. مقادیر معتبر: owner (مالک), investor (سرمایه‌گذار). (پیش‌فرض: owner)\n\n* `owner` - مالک\n* `investor` - سرمایه‌گذار"},{"name":"contract_date_shamsi","type":"string","required":false,"description":"تاریخ قرارداد به شمسی. (اختیاری)"},{"name":"description","type":"string","required":false,"description":"توضیحات تکمیلی درباره سرمایه‌گذار. (اختیاری)"}],"response_codes":["200: Investor"]}},{"page_content":"Tool: investor_partial_update\nDescription: به‌روزرسانی جزئی سرمایه‌گذار\n\nاین متد امکان تغییر بخشی از فیلدهای سرمایه‌گذار را فراهم می‌کند.\nفقط فیلدهای ارسال شده تغییر می‌کنند.\n\nURL Parameters:\n    - pk: شناسه یکتای سرمایه‌گذار\n\nRequest Body:\n    - فیلدهای انتخابی برای به‌روزرسانی\n\nReturns:\n    Response با اطلاعات به‌روزرسانی شده سرمایه‌گذار (status 200)\n\nمثال:\n    PATCH /api/v1/Investor/1/\n    {\n        \"phone\": \"09123456789\"\n    }\n\nنکات:\n    - فقط فیلدهای ارسال شده تغییر می‌کنند\n    - فیلدهای ارسال نشده حفظ می‌شوند\n    - انعطاف بیشتری نسبت به PUT دارد\n    - جزئیات فیلدها در serializer descriptions موجود است\n    - نیاز به احراز هویت دارد\n\nپارامترها:\n- id (int): یک مقداد عدد یکتا که این سرمایه‌گذار را شناسایی میکند. [required]\n- project (int, optional): شناسه پروژه. اگر مشخص نشود، از پروژه جاری session استفاده می‌شود.\n- first_name (str, optional): نام سرمایه‌گذار. (الزامی)\n- last_name (str, optional): نام خانوادگی سرمایه‌گذار. (الزامی)\n- phone (str, optional): شماره تماس سرمایه‌گذار. (الزامی)\n- email (str, optional): آدرس ایمیل سرمایه‌گذار. (اختیاری) (ایمیل)\n- participation_type (str, optional): نوع مشارکت. مقادیر معتبر: owner (مالک), investor (سرمایه‌گذار). (پیش‌فرض: owner)\n\n* `owner` - مالک\n* `investor` - سرمایه‌گذار\n- contract_date_shamsi (str, optional): تاریخ قرارداد به شمسی. (اختیاری) (فرمت: YYYY-MM-DD)\n- description (str, optional): توضیحات تکمیلی درباره سرمایه‌گذار. (اختیاری)\n\nمثال‌های استفاده:\n- PATCH /api/v1/Investor/1/\n- {\n- \"phone\": \"09123456789\"\n- }\n\nنکات مهم:\n- - فقط فیلدهای ارسال شده تغییر می‌کنند\n- - فیلدهای ارسال نشده حفظ می‌شوند\n- - انعطاف بیشتری نسبت به PUT دارد\n- - جزئیات فیلدها در serializer descriptions موجود است\n- - نیاز به احراز هویت دارد\n\nAPI Endpoint: PATCH /api/v1/Investor/{id}/\nOperation ID: Investor_partial_update\nدسته‌بندی: Investor","metadata":{"tool_name":"investor_partial_update","category":"Investor","method":"PATCH","path":"/api/v1/Investor/{id}/","operation_id":"Investor_partial_update","tags":["Investor"],"has_auth":true,"parameters":[{"name":"id","type":"integer","required":true,"description":"یک مقداد عدد یکتا که این سرمایه‌گذار را شناسایی میکند."},{"name":"project","type":"integer","required":false,"description":"شناسه پروژه. اگر مشخص نشود، از پروژه جاری session استفاده می‌شود."},{"name":"first_name","type":"string","required":false,"description":"نام سرمایه‌گذار. (الزامی)"},{"name":"last_name","type":"string","required":false,"description":"نام خانوادگی سرمایه‌گذار. (الزامی)"},{"name":"phone","type":"string","required":false,"description":"شماره تماس سرمایه‌گذار. (الزامی)"},{"name":"email","type":"string","required":false,"description":"آدرس ایمیل سرمایه‌گذار. (اختیاری)"},{"name":"participation_type","type":"string","required":false,"description":"نوع مشارکت. مقادیر معتبر: owner (مالک), investor (سرمایه‌گذار). (پیش‌فرض: owner)\n\n* `owner` - مالک\n* `investor` - سرمایه‌گذار"},{"name":"contract_date_shamsi","type":"string","required":false,"description":"تاریخ قرارداد به شمسی. (اختیاری)"},{"name":"description","type":"string","required":false,"description":"توضیحات تکمیلی درباره سرمایه‌گذار. (اختیاری)"}],"response_codes":["200: Investor"]}},{"page_content":"Tool: investor_destroy\nDescription: حذف سرمایه‌گذار\n\nاین متد سرمایه‌گذار را به‌طور کامل و برگشت‌ناپذیری حذف می‌کند.\n\nURL Parameters:\n    - pk: شناسه یکتای سرمایه‌گذار\n\nReturns:\n    Response خالی با status 204 No Content در صورت موفقیت\n\nمثال:\n    DELETE /api/v1/Investor/1/\n\nنکات:\n    - حذف برگشت‌ناپذیر است\n    - فقط سرمایه‌گذاران پروژه جاری قابل حذف هستند\n    - نیاز به احراز هویت و دسترسی APISecurityPermission دارد\n    - در صورت وجود وابستگی، ممکن است حذف ناموفق باشد\n\nپارامترها:\n- id (int): یک مقداد عدد یکتا که این سرمایه‌گذار را شناسایی میکند. [required]\n\nمثال‌های استفاده:\n- DELETE /api/v1/Investor/1/\n\nنکات مهم:\n- - حذف برگشت‌ناپذیر است\n- - فقط سرمایه‌گذاران پروژه جاری قابل حذف هستند\n- - نیاز به احراز هویت و دسترسی APISecurityPermission دارد\n- - در صورت وجود وابستگی، ممکن است حذف ناموفق باشد\n\nAPI Endpoint: DELETE /api/v1/Investor/{id}/\nOperation ID: Investor_destroy\nدسته‌بندی: Investor","metadata":{"tool_name":"investor_destroy","category":"Investor","method":"DELETE","path":"/api/v1/Investor/{id}/","operation_id":"Investor_destroy","tags":["Investor"],"has_auth":true,"parameters":[{"name":"id","type":"integer","required":true,"description":"یک مقداد عدد یکتا که این سرمایه‌گذار را شناسایی میکند."}],"response_codes":[]}},{"page_content":"Tool: investor_detailed_statistics_retrieve\nDescription: دریافت آمار تفصیلی سرمایه‌گذار\n\nاین endpoint آمار کامل و تفصیلی برای یک سرمایه‌گذار خاص را محاسبه و برمی‌گرداند.\nشامل اطلاعات مالی، سرمایه، سود، نسبت‌ها و سایر متریک‌های مرتبط.\n\nParameters:\n    pk (int): شناسه سرمایه‌گذار\n    project_id (int, optional): شناسه پروژه (از query parameter یا پروژه جاری)\n\nReturns:\n    Response: شامل آمار تفصیلی سرمایه‌گذار\n\nمثال Response:\n{\n    \"total_investment\": 50000000,\n    \"total_profit\": 15000000,\n    \"grand_total\": 115000000,\n    \"ownership_percentage\": 25.5,\n    \"unit_cost\": 5000000\n}\n\nنکات مهم:\n- اگر سرمایه‌گذار یافت نشود، خطای 404 برمی‌گرداند\n- محاسبات بر اساس پروژه جاری یا project_id ارسالی انجام می‌شود\n- تمام مبالغ به تومان هستند\n\nپارامترها:\n- id (int): یک مقداد عدد یکتا که این سرمایه‌گذار را شناسایی میکند. [required]\n\nمثال‌های استفاده:\n- {\n- \"total_investment\": 50000000,\n- \"total_profit\": 15000000,\n- \"grand_total\": 115000000,\n- \"ownership_percentage\": 25.5,\n\nنکات مهم:\n- - اگر سرمایه‌گذار یافت نشود، خطای 404 برمی‌گرداند\n- - محاسبات بر اساس پروژه جاری یا project_id ارسالی انجام می‌شود\n- - تمام مبالغ به تومان هستند\n\nAPI Endpoint: GET /api/v1/Investor/{id}/detailed_statistics/\nOperation ID: Investor_detailed_statistics_retrieve\nدسته‌بندی: Investor","metadata":{"tool_name":"investor_detailed_statistics_retrieve","category":"Investor","method":"GET","path":"/api/v1/Investor/{id}/detailed_statistics/","operation_id":"Investor_detailed_statistics_retrieve","tags":["Investor"],"has_auth":true,"parameters":[{"name":"id","type":"integer","required":true,"description":"یک مقداد عدد یکتا که این سرمایه‌گذار را شناسایی میکند."}],"response_codes":["200: Investor"]}},{"page_content":"Tool: investor_cumulative_capital_and_unit_cost_chart_retrieve\nDescription: دریافت داده‌های نمودار ترند سرمایه موجود و هزینه واحد برای سرمایه‌گذار\n\nاین endpoint داده‌های لازم برای نمودار ترند را محاسبه می‌کند:\n- سرمایه موجود تجمعی به میلیون تومان\n- هزینه واحد به میلیون تومان برای هر دوره\n\nپارامترها:\n- id (int): یک مقداد عدد یکتا که این سرمایه‌گذار را شناسایی میکند. [required]\n\nمثال‌های استفاده:\n- investor_cumulative_capital_and_unit_cost_chart_retrieve(id=1)\n\nنکات مهم:\n- نیاز به احراز هویت دارد\n\nAPI Endpoint: GET /api/v1/Investor/{id}/investor_cumulative_capital_and_unit_cost_chart/\nOperation ID: Investor_investor_cumulative_capital_and_unit_cost_chart_retrieve\nدسته‌بندی: Investor","metadata":{"tool_name":"investor_cumulative_capital_and_unit_cost_chart_retrieve","category":"Investor","method":"GET","path":"/api/v1/Investor/{id}/investor_cumulative_capital_and_unit_cost_chart/","operation_id":"Investor_investor_cumulative_capital_and_unit_cost_chart_retrieve","tags":["Investor"],"has_auth":true,"parameters":[{"name":"id","type":"integer","required":true,"description":"یک مقداد عدد یکتا که این سرمایه‌گذار را شناسایی میکند."}],"response_codes":["200: Investor"]}},{"page_content":"Tool: investor_ownership_retrieve\nDescription: دریافت مالکیت سرمایه‌گذار به متر مربع\n\nمحاسبه: (آورده + سود) / قیمت هر متر مربع واحد انتخابی\n\nپارامترها:\n- id (int): یک مقداد عدد یکتا که این سرمایه‌گذار را شناسایی میکند. [required]\n\nمثال‌های استفاده:\n- investor_ownership_retrieve(id=1)\n\nنکات مهم:\n- نیاز به احراز هویت دارد\n\nAPI Endpoint: GET /api/v1/Investor/{id}/ownership/\nOperation ID: Investor_ownership_retrieve\nدسته‌بندی: Investor","metadata":{"tool_name":"investor_ownership_retrieve","category":"Investor","method":"GET","path":"/api/v1/Investor/{id}/ownership/","operation_id":"Investor_ownership_retrieve","tags":["Investor"],"has_auth":true,"parameters":[{"name":"id","type":"integer","required":true,"description":"یک مقداد عدد یکتا که این سرمایه‌گذار را شناسایی میکند."}],"response_codes":["200: Investor"]}},{"page_content":"Tool: investor_ratios_retrieve\nDescription: دریافت نسبت‌های سرمایه‌گذار\n\nپارامترها:\n- id (int): یک مقداد عدد یکتا که این سرمایه‌گذار را شناسایی میکند. [required]\n\nمثال‌های استفاده:\n- investor_ratios_retrieve(id=1)\n\nنکات مهم:\n- نیاز به احراز هویت دارد\n\nAPI Endpoint: GET /api/v1/Investor/{id}/ratios/\nOperation ID: Investor_ratios_retrieve\nدسته‌بندی: Investor","metadata":{"tool_name":"investor_ratios_retrieve","category":"Investor","method":"GET","path":"/api/v1/Investor/{id}/ratios/","operation_id":"Investor_ratios_retrieve","tags":["Investor"],"has_auth":true,"parameters":[{"name":"id","type":"integer","required":true,"description":"یک مقداد عدد یکتا که این سرمایه‌گذار را شناسایی میکند."}],"response_codes":["200: Investor"]}},{"page_content":"Tool: investor_all_investors_summary_retrieve\nDescription: دریافت خلاصه آمار تمام سرمایه‌گذاران\n\nاین endpoint از سرویس محاسباتی InvestorCalculations استفاده می‌کند\nتا آمار کامل شامل نسبت‌های سرمایه، سود و شاخص نفع را ارائه دهد.\n\nمثال‌های استفاده:\n- investor_all_investors_summary_retrieve()\n\nنکات مهم:\n- نیاز به احراز هویت دارد\n\nAPI Endpoint: GET /api/v1/Investor/all_investors_summary/\nOperation ID: Investor_all_investors_summary_retrieve\nدسته‌بندی: Investor","metadata":{"tool_name":"investor_all_investors_summary_retrieve","category":"Investor","method":"GET","path":"/api/v1/Investor/all_investors_summary/","operation_id":"Investor_all_investors_summary_retrieve","tags":["Investor"],"has_auth":true,"parameters":[],"response_codes":["200: Investor"]}},{"page_content":"Tool: investor_participation_stats_retrieve\nDescription: دریافت آمار مشارکت کنندگان بر اساس نوع (مالک و سرمایه گذار)\n\nمثال‌های استفاده:\n- investor_participation_stats_retrieve()\n\nنکات مهم:\n- نیاز به احراز هویت دارد\n\nAPI Endpoint: GET /api/v1/Investor/participation_stats/\nOperation ID: Investor_participation_stats_retrieve\nدسته‌بندی: Investor","metadata":{"tool_name":"investor_participation_stats_retrieve","category":"Investor","method":"GET","path":"/api/v1/Investor/participation_stats/","operation_id":"Investor_participation_stats_retrieve","tags":["Investor"],"has_auth":true,"parameters":[],"response_codes":["200: Investor"]}},{"page_content":"Tool: investor_summary_retrieve\nDescription: خلاصه مالی تمام سرمایه‌گذاران پروژه\n\nاین endpoint خلاصه مالی تمام سرمایه‌گذاران پروژه جاری را محاسبه و برمی‌گرداند.\n\nخروجی شامل:\n- شناسه و نام هر سرمایه‌گذار\n- نوع مشارکت (مالک یا سرمایه‌گذار)\n- مجموع آورده‌ها\n- مجموع برداشت‌ها\n- سرمایه خالص\n- مجموع سود\n- مجموع کل (سرمایه + سود)\n\nسناریوهای استفاده:\n- نمایش لیست خلاصه تمام سرمایه‌گذاران\n- مقایسه عملکرد سرمایه‌گذاران\n- تهیه گزارش‌های مدیریتی\n- نمایش داشبورد سرمایه‌گذاران\n\nمثال استفاده:\nGET /api/v1/Investor/summary/\n\nمثال خروجی:\n[\n    {\n        \"investor_id\": 1,\n        \"name\": \"علی احمدی\",\n        \"participation_type\": \"owner\",\n        \"total_deposits\": 100000000,\n        \"total_withdrawals\": 0,\n        \"net_principal\": 100000000,\n        \"total_profit\": 15000000,\n        \"grand_total\": 115000000\n    },\n    {\n        \"investor_id\": 2,\n        \"name\": \"محمد رضایی\",\n        \"participation_type\": \"investor\",\n        \"total_deposits\": 50000000,\n        \"total_withdrawals\": 10000000,\n        \"net_principal\": 40000000,\n        \"total_profit\": 7500000,\n        \"grand_total\": 47500000\n    }\n]\n\nنکات مهم:\n- نتایج بر اساس سرمایه خالص (net_principal) به صورت نزولی مرتب می‌شوند\n- فقط سرمایه‌گذاران پروژه جاری را شامل می‌شود\n- اگر پروژه جاری وجود نداشته باشد، تمام سرمایه‌گذاران را برمی‌گرداند\n- تمام مبالغ به تومان هستند\n\nسناریوهای استفاده:\n- - نمایش لیست خلاصه تمام سرمایه‌گذاران\n- - مقایسه عملکرد سرمایه‌گذاران\n- - تهیه گزارش‌های مدیریتی\n- - نمایش داشبورد سرمایه‌گذاران\n\nمثال‌های استفاده:\n- GET /api/v1/Investor/summary/\n- [\n- {\n- \"investor_id\": 1,\n- \"name\": \"علی احمدی\",\n\nنکات مهم:\n- - نتایج بر اساس سرمایه خالص (net_principal) به صورت نزولی مرتب می‌شوند\n- - فقط سرمایه‌گذاران پروژه جاری را شامل می‌شود\n- - اگر پروژه جاری وجود نداشته باشد، تمام سرمایه‌گذاران را برمی‌گرداند\n- - تمام مبالغ به تومان هستند\n\nAPI Endpoint: GET /api/v1/Investor/summary/\nOperation ID: Investor_summary_retrieve\nدسته‌بندی: Investor","metadata":{"tool_name":"investor_summary_retrieve","category":"Investor","method":"GET","path":"/api/v1/Investor/summary/","operation_id":"Investor_summary_retrieve","tags":["Investor"],"has_auth":true,"parameters":[],"response_codes":["200: Investor"]}},{"page_content":"Tool: investor_summary_ssot_retrieve\nDescription: خلاصه مالی تمام سرمایه‌گذاران با مرجع واحد (بدون SQL خام)\n\nمثال‌های استفاده:\n- investor_summary_ssot_retrieve()\n\nنکات مهم:\n- نیاز به احراز هویت دارد\n\nAPI Endpoint: GET /api/v1/Investor/summary_ssot/\nOperation ID: Investor_summary_ssot_retrieve\nدسته‌بندی: Investor","metadata":{"tool_name":"investor_summary_ssot_retrieve","category":"Investor","method":"GET","path":"/api/v1/Investor/summary_ssot/","operation_id":"Investor_summary_ssot_retrieve","tags":["Investor"],"has_auth":true,"parameters":[],"response_codes":["200: Investor"]}},{"page_content":"Tool: period_list\nDescription: دریافت لیست تمام دوره‌های پروژه جاری\n\nاین متد لیست دوره‌های مرتبط با پروژه فعال را برمی‌گرداند.\nنتایج به صورت مرتب شده بر اساس سال و ماه (نزولی) هستند.\n\nQuery Parameters:\n    - page: شماره صفحه (پیش‌فرض: 1)\n    - page_size: تعداد رکورد در هر صفحه (پیش‌فرض: 10)\n    - ordering: فیلد مرتب‌سازی\n\nReturns:\n    Response با ساختار paginated شامل results, count, next, previous\n\nمثال:\n    GET /api/v1/Period/?page=1&page_size=12\n\nنکات:\n    - فقط دوره‌های پروژه جاری برگردانده می‌شود\n    - دوره‌ها به صورت نزولی (جدیدترین اول) مرتب می‌شوند\n    - نیاز به احراز هویت دارد\n\nمثال‌های استفاده:\n- GET /api/v1/Period/?page=1&page_size=12\n\nنکات مهم:\n- - فقط دوره‌های پروژه جاری برگردانده می‌شود\n- - دوره‌ها به صورت نزولی (جدیدترین اول) مرتب می‌شوند\n- - نیاز به احراز هویت دارد\n\nAPI Endpoint: GET /api/v1/Period/\nOperation ID: Period_list\nدسته‌بندی: Period","metadata":{"tool_name":"period_list","category":"Period","method":"GET","path":"/api/v1/Period/","operation_id":"Period_list","tags":["Period"],"has_auth":true,"parameters":[],"response_codes":["200: array"]}},{"page_content":"Tool: period_create\nDescription: ایجاد دوره جدید برای پروژه جاری\n\nاین متد دوره جدید را برای پروژه فعال ثبت می‌کند.\nپروژه به صورت خودکار از session کاربر تعیین می‌شود.\n\nRequest Body:\n    - label (الزامی): عنوان دوره\n    - year (الزامی): سال شمسی\n    - month_number (الزامی): شماره ماه (1-12)\n    - month_name (الزامی): نام ماه\n    - weight (الزامی): وزن دوره\n    - start_date_shamsi (الزامی): تاریخ شروع شمسی\n    - end_date_shamsi (الزامی): تاریخ پایان شمسی\n    - start_date_gregorian (الزامی): تاریخ شروع میلادی\n    - end_date_gregorian (الزامی): تاریخ پایان میلادی\n\nReturns:\n    Response با اطلاعات دوره ایجاد شده (status 201)\n\nمثال:\n    POST /api/v1/Period/\n    {\n        \"label\": \"مهر 1403\",\n        \"year\": 1403,\n        \"month_number\": 7,\n        \"month_name\": \"مهر\",\n        \"weight\": 1,\n        \"start_date_shamsi\": \"1403-07-01\",\n        \"end_date_shamsi\": \"1403-07-29\",\n        \"start_date_gregorian\": \"2024-09-22\",\n        \"end_date_gregorian\": \"2024-10-20\"\n    }\n\nنکات:\n    - جزئیات فیلدها در serializer descriptions موجود است\n    - پروژه به صورت خودکار از session تنظیم می‌شود\n    - هر ترکیب (project, year, month_number) باید یکتا باشد\n    - نیاز به احراز هویت و دسترسی APISecurityPermission دارد\n\nپارامترها:\n- label (str): عنوان دوره (مثال: \"مهر 1403\"). (الزامی) [required]\n- year (int): سال شمسی دوره (مثال: 1403). (الزامی) [required]\n- month_number (int): شماره ماه شمسی (1 تا 12). (الزامی) [required]\n- month_name (str): نام ماه شمسی (مثال: \"مهر\"). (الزامی) [required]\n- weight (int): وزن دوره برای محاسبات مالی. هرچه بیشتر باشد، تأثیر بیشتری در محاسبات دارد. (الزامی) [required]\n- start_date_shamsi (str): تاریخ شروع دوره به شمسی. (الزامی) (فرمت: YYYY-MM-DD) [required]\n- end_date_shamsi (str): تاریخ پایان دوره به شمسی. (الزامی) (فرمت: YYYY-MM-DD) [required]\n- start_date_gregorian (str): تاریخ شروع دوره به میلادی. (الزامی) (فرمت: YYYY-MM-DD) [required]\n- end_date_gregorian (str): تاریخ پایان دوره به میلادی. (الزامی) (فرمت: YYYY-MM-DD) [required]\n- project (int, optional): شناسه پروژه. اگر مشخص نشود، از پروژه جاری session استفاده می‌شود.\n\nمثال‌های استفاده:\n- POST /api/v1/Period/\n- {\n- \"label\": \"مهر 1403\",\n- \"year\": 1403,\n- \"month_number\": 7,\n\nنکات مهم:\n- - جزئیات فیلدها در serializer descriptions موجود است\n- - پروژه به صورت خودکار از session تنظیم می‌شود\n- - هر ترکیب (project, year, month_number) باید یکتا باشد\n- - نیاز به احراز هویت و دسترسی APISecurityPermission دارد\n\nAPI Endpoint: POST /api/v1/Period/\nOperation ID: Period_create\nدسته‌بندی: Period","metadata":{"tool_name":"period_create","category":"Period","method":"POST","path":"/api/v1/Period/","operation_id":"Period_create","tags":["Period"],"has_auth":true,"parameters":[{"name":"label","type":"string","required":true,"description":"عنوان دوره (مثال: \"مهر 1403\"). (الزامی)"},{"name":"year","type":"integer","required":true,"description":"سال شمسی دوره (مثال: 1403). (الزامی)"},{"name":"month_number","type":"integer","required":true,"description":"شماره ماه شمسی (1 تا 12). (الزامی)"},{"name":"month_name","type":"string","required":true,"description":"نام ماه شمسی (مثال: \"مهر\"). (الزامی)"},{"name":"weight","type":"integer","required":true,"description":"وزن دوره برای محاسبات مالی. هرچه بیشتر باشد، تأثیر بیشتری در محاسبات دارد. (الزامی)"},{"name":"start_date_shamsi","type":"string","required":true,"description":"تاریخ شروع دوره به شمسی. (الزامی)"},{"name":"end_date_shamsi","type":"string","required":true,"description":"تاریخ پایان دوره به شمسی. (الزامی)"},{"name":"start_date_gregorian","type":"string","required":true,"description":"تاریخ شروع دوره به میلادی. (الزامی)"},{"name":"end_date_gregorian","type":"string","required":true,"description":"تاریخ پایان دوره به میلادی. (الزامی)"},{"name":"project","type":"integer","required":false,"description":"شناسه پروژه. اگر مشخص نشود، از پروژه جاری session استفاده می‌شود."}],"response_codes":["201: Period"]}},{"page_content":"Tool: period_retrieve\nDescription: دریافت جزئیات یک دوره خاص\n\nاین متد اطلاعات کامل دوره با شناسه مشخص شده را برمی‌گرداند.\n\nURL Parameters:\n    - pk: شناسه یکتای دوره\n\nReturns:\n    Response با اطلاعات کامل دوره\n\nمثال:\n    GET /api/v1/Period/1/\n\nنکات:\n    - فقط دوره‌های پروژه جاری قابل دسترسی هستند\n    - در صورت عدم دسترسی، خطای 403 برگردانده می‌شود\n    - نیاز به احراز هویت دارد\n\nپارامترها:\n- id (int): یک مقداد عدد یکتا که این دوره را شناسایی میکند. [required]\n\nمثال‌های استفاده:\n- GET /api/v1/Period/1/\n\nنکات مهم:\n- - فقط دوره‌های پروژه جاری قابل دسترسی هستند\n- - در صورت عدم دسترسی، خطای 403 برگردانده می‌شود\n- - نیاز به احراز هویت دارد\n\nAPI Endpoint: GET /api/v1/Period/{id}/\nOperation ID: Period_retrieve\nدسته‌بندی: Period","metadata":{"tool_name":"period_retrieve","category":"Period","method":"GET","path":"/api/v1/Period/{id}/","operation_id":"Period_retrieve","tags":["Period"],"has_auth":true,"parameters":[{"name":"id","type":"integer","required":true,"description":"یک مقداد عدد یکتا که این دوره را شناسایی میکند."}],"response_codes":["200: Period"]}},{"page_content":"Tool: period_update\nDescription: به‌روزرسانی کامل دوره\n\nاین متد امکان تغییر همه فیلدهای یک دوره را فراهم می‌کند.\nتمام فیلدهای قابل ویرایش باید ارسال شوند.\n\nURL Parameters:\n    - pk: شناسه یکتای دوره\n\nRequest Body:\n    - تمام فیلدهای قابل ویرایش\n\nReturns:\n    Response با اطلاعات به‌روزرسانی شده دوره (status 200)\n\nمثال:\n    PUT /api/v1/Period/1/\n    {\n        \"label\": \"مهر 1403\",\n        \"year\": 1403,\n        \"month_number\": 7,\n        \"weight\": 2\n    }\n\nنکات:\n    - همه فیلدها باید ارسال شوند\n    - برای به‌روزرسانی جزئی از PATCH استفاده کنید\n    - جزئیات فیلدها در serializer descriptions موجود است\n    - نیاز به احراز هویت دارد\n\nپارامترها:\n- id (int): یک مقداد عدد یکتا که این دوره را شناسایی میکند. [required]\n- label (str): عنوان دوره (مثال: \"مهر 1403\"). (الزامی) [required]\n- year (int): سال شمسی دوره (مثال: 1403). (الزامی) [required]\n- month_number (int): شماره ماه شمسی (1 تا 12). (الزامی) [required]\n- month_name (str): نام ماه شمسی (مثال: \"مهر\"). (الزامی) [required]\n- weight (int): وزن دوره برای محاسبات مالی. هرچه بیشتر باشد، تأثیر بیشتری در محاسبات دارد. (الزامی) [required]\n- start_date_shamsi (str): تاریخ شروع دوره به شمسی. (الزامی) (فرمت: YYYY-MM-DD) [required]\n- end_date_shamsi (str): تاریخ پایان دوره به شمسی. (الزامی) (فرمت: YYYY-MM-DD) [required]\n- start_date_gregorian (str): تاریخ شروع دوره به میلادی. (الزامی) (فرمت: YYYY-MM-DD) [required]\n- end_date_gregorian (str): تاریخ پایان دوره به میلادی. (الزامی) (فرمت: YYYY-MM-DD) [required]\n- project (int, optional): شناسه پروژه. اگر مشخص نشود، از پروژه جاری session استفاده می‌شود.\n\nمثال‌های استفاده:\n- PUT /api/v1/Period/1/\n- {\n- \"label\": \"مهر 1403\",\n- \"year\": 1403,\n- \"month_number\": 7,\n\nنکات مهم:\n- - همه فیلدها باید ارسال شوند\n- - برای به‌روزرسانی جزئی از PATCH استفاده کنید\n- - جزئیات فیلدها در serializer descriptions موجود است\n- - نیاز به احراز هویت دارد\n\nAPI Endpoint: PUT /api/v1/Period/{id}/\nOperation ID: Period_update\nدسته‌بندی: Period","metadata":{"tool_name":"period_update","category":"Period","method":"PUT","path":"/api/v1/Period/{id}/","operation_id":"Period_update","tags":["Period"],"has_auth":true,"parameters":[{"name":"id","type":"integer","required":true,"description":"یک مقداد عدد یکتا که این دوره را شناسایی میکند."},{"name":"label","type":"string","required":true,"description":"عنوان دوره (مثال: \"مهر 1403\"). (الزامی)"},{"name":"year","type":"integer","required":true,"description":"سال شمسی دوره (مثال: 1403). (الزامی)"},{"name":"month_number","type":"integer","required":true,"description":"شماره ماه شمسی (1 تا 12). (الزامی)"},{"name":"month_name","type":"string","required":true,"description":"نام ماه شمسی (مثال: \"مهر\"). (الزامی)"},{"name":"weight","type":"integer","required":true,"description":"وزن دوره برای محاسبات مالی. هرچه بیشتر باشد، تأثیر بیشتری در محاسبات دارد. (الزامی)"},{"name":"start_date_shamsi","type":"string","required":true,"description":"تاریخ شروع دوره به شمسی. (الزامی)"},{"name":"end_date_shamsi","type":"string","required":true,"description":"تاریخ پایان دوره به شمسی. (الزامی)"},{"name":"start_date_gregorian","type":"string","required":true,"description":"تاریخ شروع دوره به میلادی. (الزامی)"},{"name":"end_date_gregorian","type":"string","required":true,"description":"تاریخ پایان دوره به میلادی. (الزامی)"},{"name":"project","type":"integer","required":false,"description":"شناسه پروژه. اگر مشخص نشود، از پروژه جاری session استفاده می‌شود."}],"response_codes":["200: Period"]}},{"page_content":"Tool: period_partial_update\nDescription: به‌روزرسانی جزئی دوره\n\nاین متد امکان تغییر بخشی از فیلدهای دوره را فراهم می‌کند.\nفقط فیلدهای ارسال شده تغییر می‌کنند.\n\nURL Parameters:\n    - pk: شناسه یکتای دوره\n\nRequest Body:\n    - فیلدهای انتخابی برای به‌روزرسانی\n\nReturns:\n    Response با اطلاعات به‌روزرسانی شده دوره (status 200)\n\nمثال:\n    PATCH /api/v1/Period/1/\n    {\n        \"weight\": 2\n    }\n\nنکات:\n    - فقط فیلدهای ارسال شده تغییر می‌کنند\n    - فیلدهای ارسال نشده حفظ می‌شوند\n    - انعطاف بیشتری نسبت به PUT دارد\n    - جزئیات فیلدها در serializer descriptions موجود است\n    - نیاز به احراز هویت دارد\n\nپارامترها:\n- id (int): یک مقداد عدد یکتا که این دوره را شناسایی میکند. [required]\n- label (str, optional): عنوان دوره (مثال: \"مهر 1403\"). (الزامی)\n- year (int, optional): سال شمسی دوره (مثال: 1403). (الزامی)\n- month_number (int, optional): شماره ماه شمسی (1 تا 12). (الزامی)\n- month_name (str, optional): نام ماه شمسی (مثال: \"مهر\"). (الزامی)\n- weight (int, optional): وزن دوره برای محاسبات مالی. هرچه بیشتر باشد، تأثیر بیشتری در محاسبات دارد. (الزامی)\n- start_date_shamsi (str, optional): تاریخ شروع دوره به شمسی. (الزامی) (فرمت: YYYY-MM-DD)\n- end_date_shamsi (str, optional): تاریخ پایان دوره به شمسی. (الزامی) (فرمت: YYYY-MM-DD)\n- start_date_gregorian (str, optional): تاریخ شروع دوره به میلادی. (الزامی) (فرمت: YYYY-MM-DD)\n- end_date_gregorian (str, optional): تاریخ پایان دوره به میلادی. (الزامی) (فرمت: YYYY-MM-DD)\n- project (int, optional): شناسه پروژه. اگر مشخص نشود، از پروژه جاری session استفاده می‌شود.\n\nمثال‌های استفاده:\n- PATCH /api/v1/Period/1/\n- {\n- \"weight\": 2\n- }\n\nنکات مهم:\n- - فقط فیلدهای ارسال شده تغییر می‌کنند\n- - فیلدهای ارسال نشده حفظ می‌شوند\n- - انعطاف بیشتری نسبت به PUT دارد\n- - جزئیات فیلدها در serializer descriptions موجود است\n- - نیاز به احراز هویت دارد\n\nAPI Endpoint: PATCH /api/v1/Period/{id}/\nOperation ID: Period_partial_update\nدسته‌بندی: Period","metadata":{"tool_name":"period_partial_update","category":"Period","method":"PATCH","path":"/api/v1/Period/{id}/","operation_id":"Period_partial_update","tags":["Period"],"has_auth":true,"parameters":[{"name":"id","type":"integer","required":true,"description":"یک مقداد عدد یکتا که این دوره را شناسایی میکند."},{"name":"label","type":"string","required":false,"description":"عنوان دوره (مثال: \"مهر 1403\"). (الزامی)"},{"name":"year","type":"integer","required":false,"description":"سال شمسی دوره (مثال: 1403). (الزامی)"},{"name":"month_number","type":"integer","required":false,"description":"شماره ماه شمسی (1 تا 12). (الزامی)"},{"name":"month_name","type":"string","required":false,"description":"نام ماه شمسی (مثال: \"مهر\"). (الزامی)"},{"name":"weight","type":"integer","required":false,"description":"وزن دوره برای محاسبات مالی. هرچه بیشتر باشد، تأثیر بیشتری در محاسبات دارد. (الزامی)"},{"name":"start_date_shamsi","type":"string","required":false,"description":"تاریخ شروع دوره به شمسی. (الزامی)"},{"name":"end_date_shamsi","type":"string","required":false,"description":"تاریخ پایان دوره به شمسی. (الزامی)"},{"name":"start_date_gregorian","type":"string","required":false,"description":"تاریخ شروع دوره به میلادی. (الزامی)"},{"name":"end_date_gregorian","type":"string","required":false,"description":"تاریخ پایان دوره به میلادی. (الزامی)"},{"name":"project","type":"integer","required":false,"description":"شناسه پروژه. اگر مشخص نشود، از پروژه جاری session استفاده می‌شود."}],"response_codes":["200: Period"]}},{"page_content":"Tool: period_destroy\nDescription: حذف دوره\n\nاین متد دوره را به‌طور کامل و برگشت‌ناپذیری حذف می‌کند.\n\nURL Parameters:\n    - pk: شناسه یکتای دوره\n\nReturns:\n    Response خالی با status 204 No Content در صورت موفقیت\n\nمثال:\n    DELETE /api/v1/Period/1/\n\nنکات:\n    - حذف برگشت‌ناپذیر است\n    - فقط دوره‌های پروژه جاری قابل حذف هستند\n    - نیاز به احراز هویت و دسترسی APISecurityPermission دارد\n    - در صورت وجود وابستگی (هزینه‌ها، تراکنش‌ها)، ممکن است حذف ناموفق باشد\n\nپارامترها:\n- id (int): یک مقداد عدد یکتا که این دوره را شناسایی میکند. [required]\n\nمثال‌های استفاده:\n- DELETE /api/v1/Period/1/\n\nنکات مهم:\n- - حذف برگشت‌ناپذیر است\n- - فقط دوره‌های پروژه جاری قابل حذف هستند\n- - نیاز به احراز هویت و دسترسی APISecurityPermission دارد\n- - در صورت وجود وابستگی (هزینه‌ها، تراکنش‌ها)، ممکن است حذف ناموفق باشد\n\nAPI Endpoint: DELETE /api/v1/Period/{id}/\nOperation ID: Period_destroy\nدسته‌بندی: Period","metadata":{"tool_name":"period_destroy","category":"Period","method":"DELETE","path":"/api/v1/Period/{id}/","operation_id":"Period_destroy","tags":["Period"],"has_auth":true,"parameters":[{"name":"id","type":"integer","required":true,"description":"یک مقداد عدد یکتا که این دوره را شناسایی میکند."}],"response_codes":[]}},{"page_content":"Tool: period_chart_data_retrieve\nDescription: دریافت داده‌های دوره‌ای برای نمودارها (سرمایه، هزینه، فروش، مانده صندوق)\n\nمثال‌های استفاده:\n- period_chart_data_retrieve()\n\nنکات مهم:\n- نیاز به احراز هویت دارد\n\nAPI Endpoint: GET /api/v1/Period/chart_data/\nOperation ID: Period_chart_data_retrieve\nدسته‌بندی: Period","metadata":{"tool_name":"period_chart_data_retrieve","category":"Period","method":"GET","path":"/api/v1/Period/chart_data/","operation_id":"Period_chart_data_retrieve","tags":["Period"],"has_auth":true,"parameters":[],"response_codes":["200: Period"]}},{"page_content":"Tool: period_summary_retrieve\nDescription: دریافت خلاصه کامل دوره‌ای شامل تمام فاکتورها و مقادیر تجمعی\n\nاین endpoint خلاصه کامل تمام دوره‌های پروژه را با تمام اطلاعات مالی\nشامل آورده‌ها، برداشت‌ها، سرمایه خالص، سود، هزینه‌ها و فروش‌ها برمی‌گرداند.\n\nReturns:\n    Response: شامل:\n        - data: لیست خلاصه هر دوره\n        - totals: مجموع‌های کلی\n        - current: خلاصه دوره جاری\n\nنکات مهم:\n- فقط دوره‌های پروژه جاری را شامل می‌شود\n- اگر پروژه جاری وجود نداشته باشد، خطای 400 برمی‌گرداند\n- دوره‌ها به ترتیب زمانی مرتب می‌شوند\n- تمام مبالغ به تومان هستند\n\nمثال‌های استفاده:\n- period_summary_retrieve()\n\nنکات مهم:\n- - فقط دوره‌های پروژه جاری را شامل می‌شود\n- - اگر پروژه جاری وجود نداشته باشد، خطای 400 برمی‌گرداند\n- - دوره‌ها به ترتیب زمانی مرتب می‌شوند\n- - تمام مبالغ به تومان هستند\n\nAPI Endpoint: GET /api/v1/Period/period_summary/\nOperation ID: Period_period_summary_retrieve\nدسته‌بندی: Period","metadata":{"tool_name":"period_summary_retrieve","category":"Period","method":"GET","path":"/api/v1/Period/period_summary/","operation_id":"Period_period_summary_retrieve","tags":["Period"],"has_auth":true,"parameters":[],"response_codes":["200: Period"]}},{"page_content":"Tool: pettycashtransaction_list\nDescription: دریافت لیست تمام تراکنش‌های تنخواه پروژه جاری\n\nاین متد لیست تراکنش‌های تنخواه مرتبط با پروژه فعال را برمی‌گرداند.\nنتایج به صورت صفحه‌بندی شده و قابل مرتب‌سازی هستند.\n\nQuery Parameters:\n    - page: شماره صفحه (پیش‌فرض: 1)\n    - page_size: تعداد رکورد در هر صفحه (پیش‌فرض: 10)\n    - ordering: فیلد مرتب‌سازی\n\nReturns:\n    Response با ساختار paginated شامل results, count, next, previous\n\nمثال:\n    GET /api/v1/PettyCashTransaction/?page=1&page_size=20\n\nنکات:\n    - فقط تراکنش‌های تنخواه پروژه جاری برگردانده می‌شود\n    - نیاز به احراز هویت دارد\n\nمثال‌های استفاده:\n- GET /api/v1/PettyCashTransaction/?page=1&page_size=20\n\nنکات مهم:\n- - فقط تراکنش‌های تنخواه پروژه جاری برگردانده می‌شود\n- - نیاز به احراز هویت دارد\n\nAPI Endpoint: GET /api/v1/PettyCashTransaction/\nOperation ID: PettyCashTransaction_list\nدسته‌بندی: PettyCashTransaction","metadata":{"tool_name":"pettycashtransaction_list","category":"PettyCashTransaction","method":"GET","path":"/api/v1/PettyCashTransaction/","operation_id":"PettyCashTransaction_list","tags":["PettyCashTransaction"],"has_auth":true,"parameters":[],"response_codes":["200: array"]}},{"page_content":"Tool: pettycashtransaction_create\nDescription: ایجاد تراکنش تنخواه جدید برای پروژه جاری\n\nاین متد تراکنش تنخواه جدید را برای پروژه فعال ثبت می‌کند.\nپروژه به صورت خودکار از session کاربر تعیین می‌شود.\n\nRequest Body:\n    - expense_type (الزامی): عامل اجرایی (project_manager, facilities_manager, procurement, warehouse, construction_contractor, other)\n    - transaction_type (الزامی): نوع تراکنش (receipt, return)\n    - amount (الزامی): مبلغ تراکنش (به صورت string)\n    - date_shamsi_input (اختیاری): تاریخ شمسی (YYYY-MM-DD)\n    - description (اختیاری): توضیحات\n    - receipt_number (اختیاری): شماره فیش/رسید\n\nReturns:\n    Response با اطلاعات تراکنش تنخواه ایجاد شده (status 201)\n\nمثال:\n    POST /api/v1/PettyCashTransaction/\n    {\n        \"expense_type\": \"project_manager\",\n        \"transaction_type\": \"receipt\",\n        \"amount\": \"10000000\",\n        \"date_shamsi_input\": \"1403-07-15\",\n        \"description\": \"دریافت تنخواه برای خرید مواد اولیه\",\n        \"receipt_number\": \"F-12345\"\n    }\n\nنکات:\n    - جزئیات فیلدها در serializer descriptions موجود است\n    - پروژه به صورت خودکار از session تنظیم می‌شود\n    - تاریخ میلادی به صورت خودکار محاسبه می‌شود\n    - نیاز به احراز هویت و دسترسی APISecurityPermission دارد\n\nپارامترها:\n- expense_type (str): عامل اجرایی (نوع هزینه). مقادیر معتبر: project_manager (مدیر پروژه), facilities_manager (سرپرست کارگاه), procurement (کارپرداز), warehouse (انباردار), construction_contractor (پیمان ساختمان), other (سایر). (الزامی)\n\n* `project_manager` - مدیر پروژه\n* `facilities_manager` - سرپرست کارگاه\n* `procurement` - کارپرداز\n* `warehouse` - انباردار\n* `construction_contractor` - پیمان ساختمان\n* `other` - سایر [required]\n- transaction_type (str): نوع تراکنش. مقادیر معتبر: receipt (دریافت تنخواه از صندوق به عامل اجرایی), return (عودت تنخواه از عامل اجرایی به صندوق). (الزامی)\n\n* `receipt` - دریافت تنخواه\n* `return` - عودت تنخواه [required]\n- amount (str): مبلغ تراکنش به تومان (همیشه مثبت ذخیره می‌شود). برای جلوگیری از مشکلات دقت، به صورت string ارسال شود. (الزامی) [required]\n- description (str, optional): توضیحات تکمیلی درباره تراکنش تنخواه. (اختیاری)\n- receipt_number (str, optional): شماره فیش یا رسید تراکنش. (اختیاری)\n- date_shamsi_input (str, optional): تاریخ شمسی به فرمت YYYY-MM-DD برای دریافت از frontend. (اختیاری)\n\nمثال‌های استفاده:\n- POST /api/v1/PettyCashTransaction/\n- {\n- \"expense_type\": \"project_manager\",\n- \"transaction_type\": \"receipt\",\n- \"amount\": \"10000000\",\n\nنکات مهم:\n- - جزئیات فیلدها در serializer descriptions موجود است\n- - پروژه به صورت خودکار از session تنظیم می‌شود\n- - تاریخ میلادی به صورت خودکار محاسبه می‌شود\n- - نیاز به احراز هویت و دسترسی APISecurityPermission دارد\n\nAPI Endpoint: POST /api/v1/PettyCashTransaction/\nOperation ID: PettyCashTransaction_create\nدسته‌بندی: PettyCashTransaction","metadata":{"tool_name":"pettycashtransaction_create","category":"PettyCashTransaction","method":"POST","path":"/api/v1/PettyCashTransaction/","operation_id":"PettyCashTransaction_create","tags":["PettyCashTransaction"],"has_auth":true,"parameters":[{"name":"expense_type","type":"string","required":true,"description":"عامل اجرایی (نوع هزینه). مقادیر معتبر: project_manager (مدیر پروژه), facilities_manager (سرپرست کارگاه), procurement (کارپرداز), warehouse (انباردار), construction_contractor (پیمان ساختمان), other (سایر). (الزامی)\n\n* `project_manager` - مدیر پروژه\n* `facilities_manager` - سرپرست کارگاه\n* `procurement` - کارپرداز\n* `warehouse` - انباردار\n* `construction_contractor` - پیمان ساختمان\n* `other` - سایر"},{"name":"transaction_type","type":"string","required":true,"description":"نوع تراکنش. مقادیر معتبر: receipt (دریافت تنخواه از صندوق به عامل اجرایی), return (عودت تنخواه از عامل اجرایی به صندوق). (الزامی)\n\n* `receipt` - دریافت تنخواه\n* `return` - عودت تنخواه"},{"name":"amount","type":"string","required":true,"description":"مبلغ تراکنش به تومان (همیشه مثبت ذخیره می‌شود). برای جلوگیری از مشکلات دقت، به صورت string ارسال شود. (الزامی)"},{"name":"description","type":"string","required":false,"description":"توضیحات تکمیلی درباره تراکنش تنخواه. (اختیاری)"},{"name":"receipt_number","type":"string","required":false,"description":"شماره فیش یا رسید تراکنش. (اختیاری)"},{"name":"date_shamsi_input","type":"string","required":false,"description":"تاریخ شمسی به فرمت YYYY-MM-DD برای دریافت از frontend. (اختیاری)"}],"response_codes":["201: PettyCashTransaction"]}},{"page_content":"Tool: pettycashtransaction_retrieve\nDescription: دریافت جزئیات یک تراکنش تنخواه خاص\n\nاین متد اطلاعات کامل تراکنش تنخواه با شناسه مشخص شده را برمی‌گرداند.\n\nURL Parameters:\n    - pk: شناسه یکتای تراکنش تنخواه\n\nReturns:\n    Response با اطلاعات کامل تراکنش تنخواه شامل signed_amount\n\nمثال:\n    GET /api/v1/PettyCashTransaction/1/\n\nنکات:\n    - فقط تراکنش‌های تنخواه پروژه جاری قابل دسترسی هستند\n    - در صورت عدم دسترسی، خطای 403 برگردانده می‌شود\n    - نیاز به احراز هویت دارد\n\nپارامترها:\n- id (int): یک مقداد عدد یکتا که این تراکنش تنخواه را شناسایی میکند. [required]\n\nمثال‌های استفاده:\n- GET /api/v1/PettyCashTransaction/1/\n\nنکات مهم:\n- - فقط تراکنش‌های تنخواه پروژه جاری قابل دسترسی هستند\n- - در صورت عدم دسترسی، خطای 403 برگردانده می‌شود\n- - نیاز به احراز هویت دارد\n\nAPI Endpoint: GET /api/v1/PettyCashTransaction/{id}/\nOperation ID: PettyCashTransaction_retrieve\nدسته‌بندی: PettyCashTransaction","metadata":{"tool_name":"pettycashtransaction_retrieve","category":"PettyCashTransaction","method":"GET","path":"/api/v1/PettyCashTransaction/{id}/","operation_id":"PettyCashTransaction_retrieve","tags":["PettyCashTransaction"],"has_auth":true,"parameters":[{"name":"id","type":"integer","required":true,"description":"یک مقداد عدد یکتا که این تراکنش تنخواه را شناسایی میکند."}],"response_codes":["200: PettyCashTransaction"]}},{"page_content":"Tool: pettycashtransaction_update\nDescription: به‌روزرسانی کامل تراکنش تنخواه\n\nاین متد امکان تغییر همه فیلدهای یک تراکنش تنخواه را فراهم می‌کند.\nتمام فیلدهای قابل ویرایش باید ارسال شوند.\n\nURL Parameters:\n    - pk: شناسه یکتای تراکنش تنخواه\n\nRequest Body:\n    - تمام فیلدهای قابل ویرایش\n\nReturns:\n    Response با اطلاعات به‌روزرسانی شده تراکنش تنخواه (status 200)\n\nمثال:\n    PUT /api/v1/PettyCashTransaction/1/\n    {\n        \"expense_type\": \"project_manager\",\n        \"transaction_type\": \"receipt\",\n        \"amount\": \"12000000\",\n        \"description\": \"به‌روزرسانی شده\"\n    }\n\nنکات:\n    - همه فیلدها باید ارسال شوند\n    - برای به‌روزرسانی جزئی از PATCH استفاده کنید\n    - جزئیات فیلدها در serializer descriptions موجود است\n    - نیاز به احراز هویت دارد\n\nپارامترها:\n- id (int): یک مقداد عدد یکتا که این تراکنش تنخواه را شناسایی میکند. [required]\n- expense_type (str): عامل اجرایی (نوع هزینه). مقادیر معتبر: project_manager (مدیر پروژه), facilities_manager (سرپرست کارگاه), procurement (کارپرداز), warehouse (انباردار), construction_contractor (پیمان ساختمان), other (سایر). (الزامی)\n\n* `project_manager` - مدیر پروژه\n* `facilities_manager` - سرپرست کارگاه\n* `procurement` - کارپرداز\n* `warehouse` - انباردار\n* `construction_contractor` - پیمان ساختمان\n* `other` - سایر [required]\n- transaction_type (str): نوع تراکنش. مقادیر معتبر: receipt (دریافت تنخواه از صندوق به عامل اجرایی), return (عودت تنخواه از عامل اجرایی به صندوق). (الزامی)\n\n* `receipt` - دریافت تنخواه\n* `return` - عودت تنخواه [required]\n- amount (str): مبلغ تراکنش به تومان (همیشه مثبت ذخیره می‌شود). برای جلوگیری از مشکلات دقت، به صورت string ارسال شود. (الزامی) [required]\n- description (str, optional): توضیحات تکمیلی درباره تراکنش تنخواه. (اختیاری)\n- receipt_number (str, optional): شماره فیش یا رسید تراکنش. (اختیاری)\n- date_shamsi_input (str, optional): تاریخ شمسی به فرمت YYYY-MM-DD برای دریافت از frontend. (اختیاری)\n\nمثال‌های استفاده:\n- PUT /api/v1/PettyCashTransaction/1/\n- {\n- \"expense_type\": \"project_manager\",\n- \"transaction_type\": \"receipt\",\n- \"amount\": \"12000000\",\n\nنکات مهم:\n- - همه فیلدها باید ارسال شوند\n- - برای به‌روزرسانی جزئی از PATCH استفاده کنید\n- - جزئیات فیلدها در serializer descriptions موجود است\n- - نیاز به احراز هویت دارد\n\nAPI Endpoint: PUT /api/v1/PettyCashTransaction/{id}/\nOperation ID: PettyCashTransaction_update\nدسته‌بندی: PettyCashTransaction","metadata":{"tool_name":"pettycashtransaction_update","category":"PettyCashTransaction","method":"PUT","path":"/api/v1/PettyCashTransaction/{id}/","operation_id":"PettyCashTransaction_update","tags":["PettyCashTransaction"],"has_auth":true,"parameters":[{"name":"id","type":"integer","required":true,"description":"یک مقداد عدد یکتا که این تراکنش تنخواه را شناسایی میکند."},{"name":"expense_type","type":"string","required":true,"description":"عامل اجرایی (نوع هزینه). مقادیر معتبر: project_manager (مدیر پروژه), facilities_manager (سرپرست کارگاه), procurement (کارپرداز), warehouse (انباردار), construction_contractor (پیمان ساختمان), other (سایر). (الزامی)\n\n* `project_manager` - مدیر پروژه\n* `facilities_manager` - سرپرست کارگاه\n* `procurement` - کارپرداز\n* `warehouse` - انباردار\n* `construction_contractor` - پیمان ساختمان\n* `other` - سایر"},{"name":"transaction_type","type":"string","required":true,"description":"نوع تراکنش. مقادیر معتبر: receipt (دریافت تنخواه از صندوق به عامل اجرایی), return (عودت تنخواه از عامل اجرایی به صندوق). (الزامی)\n\n* `receipt` - دریافت تنخواه\n* `return` - عودت تنخواه"},{"name":"amount","type":"string","required":true,"description":"مبلغ تراکنش به تومان (همیشه مثبت ذخیره می‌شود). برای جلوگیری از مشکلات دقت، به صورت string ارسال شود. (الزامی)"},{"name":"description","type":"string","required":false,"description":"توضیحات تکمیلی درباره تراکنش تنخواه. (اختیاری)"},{"name":"receipt_number","type":"string","required":false,"description":"شماره فیش یا رسید تراکنش. (اختیاری)"},{"name":"date_shamsi_input","type":"string","required":false,"description":"تاریخ شمسی به فرمت YYYY-MM-DD برای دریافت از frontend. (اختیاری)"}],"response_codes":["200: PettyCashTransaction"]}},{"page_content":"Tool: pettycashtransaction_partial_update\nDescription: به‌روزرسانی جزئی تراکنش تنخواه\n\nاین متد امکان تغییر بخشی از فیلدهای تراکنش تنخواه را فراهم می‌کند.\nفقط فیلدهای ارسال شده تغییر می‌کنند.\n\nURL Parameters:\n    - pk: شناسه یکتای تراکنش تنخواه\n\nRequest Body:\n    - فیلدهای انتخابی برای به‌روزرسانی\n\nReturns:\n    Response با اطلاعات به‌روزرسانی شده تراکنش تنخواه (status 200)\n\nمثال:\n    PATCH /api/v1/PettyCashTransaction/1/\n    {\n        \"amount\": \"12000000\"\n    }\n\nنکات:\n    - فقط فیلدهای ارسال شده تغییر می‌کنند\n    - فیلدهای ارسال نشده حفظ می‌شوند\n    - انعطاف بیشتری نسبت به PUT دارد\n    - جزئیات فیلدها در serializer descriptions موجود است\n    - نیاز به احراز هویت دارد\n\nپارامترها:\n- id (int): یک مقداد عدد یکتا که این تراکنش تنخواه را شناسایی میکند. [required]\n- expense_type (str, optional): عامل اجرایی (نوع هزینه). مقادیر معتبر: project_manager (مدیر پروژه), facilities_manager (سرپرست کارگاه), procurement (کارپرداز), warehouse (انباردار), construction_contractor (پیمان ساختمان), other (سایر). (الزامی)\n\n* `project_manager` - مدیر پروژه\n* `facilities_manager` - سرپرست کارگاه\n* `procurement` - کارپرداز\n* `warehouse` - انباردار\n* `construction_contractor` - پیمان ساختمان\n* `other` - سایر\n- transaction_type (str, optional): نوع تراکنش. مقادیر معتبر: receipt (دریافت تنخواه از صندوق به عامل اجرایی), return (عودت تنخواه از عامل اجرایی به صندوق). (الزامی)\n\n* `receipt` - دریافت تنخواه\n* `return` - عودت تنخواه\n- amount (str, optional): مبلغ تراکنش به تومان (همیشه مثبت ذخیره می‌شود). برای جلوگیری از مشکلات دقت، به صورت string ارسال شود. (الزامی)\n- description (str, optional): توضیحات تکمیلی درباره تراکنش تنخواه. (اختیاری)\n- receipt_number (str, optional): شماره فیش یا رسید تراکنش. (اختیاری)\n- date_shamsi_input (str, optional): تاریخ شمسی به فرمت YYYY-MM-DD برای دریافت از frontend. (اختیاری)\n\nمثال‌های استفاده:\n- PATCH /api/v1/PettyCashTransaction/1/\n- {\n- \"amount\": \"12000000\"\n- }\n\nنکات مهم:\n- - فقط فیلدهای ارسال شده تغییر می‌کنند\n- - فیلدهای ارسال نشده حفظ می‌شوند\n- - انعطاف بیشتری نسبت به PUT دارد\n- - جزئیات فیلدها در serializer descriptions موجود است\n- - نیاز به احراز هویت دارد\n\nAPI Endpoint: PATCH /api/v1/PettyCashTransaction/{id}/\nOperation ID: PettyCashTransaction_partial_update\nدسته‌بندی: PettyCashTransaction","metadata":{"tool_name":"pettycashtransaction_partial_update","category":"PettyCashTransaction","method":"PATCH","path":"/api/v1/PettyCashTransaction/{id}/","operation_id":"PettyCashTransaction_partial_update","tags":["PettyCashTransaction"],"has_auth":true,"parameters":[{"name":"id","type":"integer","required":true,"description":"یک مقداد عدد یکتا که این تراکنش تنخواه را شناسایی میکند."},{"name":"expense_type","type":"string","required":false,"description":"عامل اجرایی (نوع هزینه). مقادیر معتبر: project_manager (مدیر پروژه), facilities_manager (سرپرست کارگاه), procurement (کارپرداز), warehouse (انباردار), construction_contractor (پیمان ساختمان), other (سایر). (الزامی)\n\n* `project_manager` - مدیر پروژه\n* `facilities_manager` - سرپرست کارگاه\n* `procurement` - کارپرداز\n* `warehouse` - انباردار\n* `construction_contractor` - پیمان ساختمان\n* `other` - سایر"},{"name":"transaction_type","type":"string","required":false,"description":"نوع تراکنش. مقادیر معتبر: receipt (دریافت تنخواه از صندوق به عامل اجرایی), return (عودت تنخواه از عامل اجرایی به صندوق). (الزامی)\n\n* `receipt` - دریافت تنخواه\n* `return` - عودت تنخواه"},{"name":"amount","type":"string","required":false,"description":"مبلغ تراکنش به تومان (همیشه مثبت ذخیره می‌شود). برای جلوگیری از مشکلات دقت، به صورت string ارسال شود. (الزامی)"},{"name":"description","type":"string","required":false,"description":"توضیحات تکمیلی درباره تراکنش تنخواه. (اختیاری)"},{"name":"receipt_number","type":"string","required":false,"description":"شماره فیش یا رسید تراکنش. (اختیاری)"},{"name":"date_shamsi_input","type":"string","required":false,"description":"تاریخ شمسی به فرمت YYYY-MM-DD برای دریافت از frontend. (اختیاری)"}],"response_codes":["200: PettyCashTransaction"]}},{"page_content":"Tool: pettycashtransaction_destroy\nDescription: حذف تراکنش تنخواه\n\nاین متد تراکنش تنخواه را به‌طور کامل و برگشت‌ناپذیری حذف می‌کند.\n\nURL Parameters:\n    - pk: شناسه یکتای تراکنش تنخواه\n\nReturns:\n    Response خالی با status 204 No Content در صورت موفقیت\n\nمثال:\n    DELETE /api/v1/PettyCashTransaction/1/\n\nنکات:\n    - حذف برگشت‌ناپذیر است\n    - فقط تراکنش‌های تنخواه پروژه جاری قابل حذف هستند\n    - نیاز به احراز هویت و دسترسی APISecurityPermission دارد\n\nپارامترها:\n- id (int): یک مقداد عدد یکتا که این تراکنش تنخواه را شناسایی میکند. [required]\n\nمثال‌های استفاده:\n- DELETE /api/v1/PettyCashTransaction/1/\n\nنکات مهم:\n- - حذف برگشت‌ناپذیر است\n- - فقط تراکنش‌های تنخواه پروژه جاری قابل حذف هستند\n- - نیاز به احراز هویت و دسترسی APISecurityPermission دارد\n\nAPI Endpoint: DELETE /api/v1/PettyCashTransaction/{id}/\nOperation ID: PettyCashTransaction_destroy\nدسته‌بندی: PettyCashTransaction","metadata":{"tool_name":"pettycashtransaction_destroy","category":"PettyCashTransaction","method":"DELETE","path":"/api/v1/PettyCashTransaction/{id}/","operation_id":"PettyCashTransaction_destroy","tags":["PettyCashTransaction"],"has_auth":true,"parameters":[{"name":"id","type":"integer","required":true,"description":"یک مقداد عدد یکتا که این تراکنش تنخواه را شناسایی میکند."}],"response_codes":[]}},{"page_content":"Tool: pettycashtransaction_balance_detail_retrieve\nDescription: دریافت وضعیت مالی یک عامل اجرایی خاص\n\nاین endpoint وضعیت مالی کامل یک عامل اجرایی (expense_type) را\nشامل مانده، مجموع دریافت‌ها، هزینه‌ها و مرجوعی‌ها برمی‌گرداند.\n\nParameters:\n    expense_type (str): نوع عامل اجرایی (الزامی)\n\nReturns:\n    Response: شامل:\n        - expense_type: نوع عامل اجرایی\n        - expense_type_label: برچسب نوع عامل\n        - balance: مانده فعلی\n        - total_receipts: مجموع دریافت‌ها\n        - total_expenses: مجموع هزینه‌ها\n        - total_returns: مجموع مرجوعی‌ها\n\nنکات مهم:\n- فقط تراکنش‌های پروژه جاری را شامل می‌شود\n- اگر پروژه جاری وجود نداشته باشد، خطای 400 برمی‌گرداند\n- اگر expense_type ارسال نشود، خطای 400 برمی‌گرداند\n- مانده مثبت = بدهکار (پول در دست دارد)\n- مانده منفی = بستانکار (بدهکار است)\n- تمام مبالغ به تومان هستند\n\nمثال‌های استفاده:\n- pettycashtransaction_balance_detail_retrieve()\n\nنکات مهم:\n- - فقط تراکنش‌های پروژه جاری را شامل می‌شود\n- - اگر پروژه جاری وجود نداشته باشد، خطای 400 برمی‌گرداند\n- - اگر expense_type ارسال نشود، خطای 400 برمی‌گرداند\n- - مانده مثبت = بدهکار (پول در دست دارد)\n- - مانده منفی = بستانکار (بدهکار است)\n- - تمام مبالغ به تومان هستند\n\nAPI Endpoint: GET /api/v1/PettyCashTransaction/balance_detail/\nOperation ID: PettyCashTransaction_balance_detail_retrieve\nدسته‌بندی: PettyCashTransaction","metadata":{"tool_name":"pettycashtransaction_balance_detail_retrieve","category":"PettyCashTransaction","method":"GET","path":"/api/v1/PettyCashTransaction/balance_detail/","operation_id":"PettyCashTransaction_balance_detail_retrieve","tags":["PettyCashTransaction"],"has_auth":true,"parameters":[],"response_codes":["200: PettyCashTransaction"]}},{"page_content":"Tool: pettycashtransaction_balance_trend_retrieve\nDescription: ترند زمانی وضعیت مالی عامل اجرایی\n\nمثال‌های استفاده:\n- pettycashtransaction_balance_trend_retrieve()\n\nنکات مهم:\n- نیاز به احراز هویت دارد\n\nAPI Endpoint: GET /api/v1/PettyCashTransaction/balance_trend/\nOperation ID: PettyCashTransaction_balance_trend_retrieve\nدسته‌بندی: PettyCashTransaction","metadata":{"tool_name":"pettycashtransaction_balance_trend_retrieve","category":"PettyCashTransaction","method":"GET","path":"/api/v1/PettyCashTransaction/balance_trend/","operation_id":"PettyCashTransaction_balance_trend_retrieve","tags":["PettyCashTransaction"],"has_auth":true,"parameters":[],"response_codes":["200: PettyCashTransaction"]}},{"page_content":"Tool: pettycashtransaction_balances_retrieve\nDescription: دریافت وضعیت مالی همه عوامل اجرایی\n\nمثال‌های استفاده:\n- pettycashtransaction_balances_retrieve()\n\nنکات مهم:\n- نیاز به احراز هویت دارد\n\nAPI Endpoint: GET /api/v1/PettyCashTransaction/balances/\nOperation ID: PettyCashTransaction_balances_retrieve\nدسته‌بندی: PettyCashTransaction","metadata":{"tool_name":"pettycashtransaction_balances_retrieve","category":"PettyCashTransaction","method":"GET","path":"/api/v1/PettyCashTransaction/balances/","operation_id":"PettyCashTransaction_balances_retrieve","tags":["PettyCashTransaction"],"has_auth":true,"parameters":[],"response_codes":["200: PettyCashTransaction"]}},{"page_content":"Tool: pettycashtransaction_detailed_report_retrieve\nDescription: گزارش تفصیلی تراکنش‌های تنخواه با فیلتر و جستجو\n\nمثال‌های استفاده:\n- pettycashtransaction_detailed_report_retrieve()\n\nنکات مهم:\n- نیاز به احراز هویت دارد\n\nAPI Endpoint: GET /api/v1/PettyCashTransaction/detailed_report/\nOperation ID: PettyCashTransaction_detailed_report_retrieve\nدسته‌بندی: PettyCashTransaction","metadata":{"tool_name":"pettycashtransaction_detailed_report_retrieve","category":"PettyCashTransaction","method":"GET","path":"/api/v1/PettyCashTransaction/detailed_report/","operation_id":"PettyCashTransaction_detailed_report_retrieve","tags":["PettyCashTransaction"],"has_auth":true,"parameters":[],"response_codes":["200: PettyCashTransaction"]}},{"page_content":"Tool: pettycashtransaction_period_balance_retrieve\nDescription: دریافت وضعیت مالی عامل اجرایی در یک دوره\n\nمثال‌های استفاده:\n- pettycashtransaction_period_balance_retrieve()\n\nنکات مهم:\n- نیاز به احراز هویت دارد\n\nAPI Endpoint: GET /api/v1/PettyCashTransaction/period_balance/\nOperation ID: PettyCashTransaction_period_balance_retrieve\nدسته‌بندی: PettyCashTransaction","metadata":{"tool_name":"pettycashtransaction_period_balance_retrieve","category":"PettyCashTransaction","method":"GET","path":"/api/v1/PettyCashTransaction/period_balance/","operation_id":"PettyCashTransaction_period_balance_retrieve","tags":["PettyCashTransaction"],"has_auth":true,"parameters":[],"response_codes":["200: PettyCashTransaction"]}},{"page_content":"Tool: pettycashtransaction_statistics_retrieve\nDescription: آمار کلی تراکنش‌های تنخواه (Single Source of Truth)\n\nمثال‌های استفاده:\n- pettycashtransaction_statistics_retrieve()\n\nنکات مهم:\n- نیاز به احراز هویت دارد\n\nAPI Endpoint: GET /api/v1/PettyCashTransaction/statistics/\nOperation ID: PettyCashTransaction_statistics_retrieve\nدسته‌بندی: PettyCashTransaction","metadata":{"tool_name":"pettycashtransaction_statistics_retrieve","category":"PettyCashTransaction","method":"GET","path":"/api/v1/PettyCashTransaction/statistics/","operation_id":"PettyCashTransaction_statistics_retrieve","tags":["PettyCashTransaction"],"has_auth":true,"parameters":[],"response_codes":["200: PettyCashTransaction"]}},{"page_content":"Tool: project_list\nDescription: دریافت لیست تمام پروژه‌ها\n\nاین متد لیست تمام پروژه‌های موجود را برمی‌گرداند.\nنتایج به صورت صفحه‌بندی شده و قابل مرتب‌سازی هستند.\n\nQuery Parameters:\n    - page: شماره صفحه (پیش‌فرض: 1)\n    - page_size: تعداد رکورد در هر صفحه (پیش‌فرض: 10)\n    - ordering: فیلد مرتب‌سازی\n\nReturns:\n    Response با ساختار paginated شامل results, count, next, previous\n\nمثال:\n    GET /api/v1/Project/?page=1&page_size=10\n\nنکات:\n    - تمام پروژه‌ها برگردانده می‌شوند\n    - نیاز به احراز هویت دارد\n\nمثال‌های استفاده:\n- GET /api/v1/Project/?page=1&page_size=10\n\nنکات مهم:\n- - تمام پروژه‌ها برگردانده می‌شوند\n- - نیاز به احراز هویت دارد\n\nAPI Endpoint: GET /api/v1/Project/\nOperation ID: Project_list\nدسته‌بندی: Project","metadata":{"tool_name":"project_list","category":"Project","method":"GET","path":"/api/v1/Project/","operation_id":"Project_list","tags":["Project"],"has_auth":true,"parameters":[],"response_codes":["200: array"]}},{"page_content":"Tool: project_create\nDescription: ایجاد پروژه جدید\n\nاین متد پروژه جدید را ثبت می‌کند.\n\nRequest Body:\n    - name (الزامی): نام پروژه\n    - start_date_shamsi (الزامی): تاریخ شروع شمسی\n    - end_date_shamsi (الزامی): تاریخ پایان شمسی\n    - start_date_gregorian (الزامی): تاریخ شروع میلادی\n    - end_date_gregorian (الزامی): تاریخ پایان میلادی\n    - total_infrastructure (اختیاری): زیر بنای کل\n    - correction_factor (اختیاری): ضریب اصلاحی\n    - construction_contractor_percentage (اختیاری): درصد پیمان ساخت\n    - description (اختیاری): توضیحات\n    - color (اختیاری): رنگ پروژه\n    - icon (اختیاری): آیکون پروژه\n\nReturns:\n    Response با اطلاعات پروژه ایجاد شده (status 201)\n\nمثال:\n    POST /api/v1/Project/\n    {\n        \"name\": \"پروژه ساختمانی نمونه\",\n        \"start_date_shamsi\": \"1403-01-01\",\n        \"end_date_shamsi\": \"1405-12-29\",\n        \"start_date_gregorian\": \"2024-03-20\",\n        \"end_date_gregorian\": \"2027-03-19\",\n        \"total_infrastructure\": \"5000.00\",\n        \"correction_factor\": \"1.0000000000\"\n    }\n\nنکات:\n    - جزئیات فیلدها در serializer descriptions موجود است\n    - نیاز به احراز هویت و دسترسی APISecurityPermission دارد\n\nپارامترها:\n- name (str): نام پروژه ساختمانی. (الزامی) [required]\n- start_date_shamsi (str): تاریخ شروع پروژه به شمسی. (الزامی) (فرمت: YYYY-MM-DD) [required]\n- end_date_shamsi (str): تاریخ پایان پروژه به شمسی. (الزامی) (فرمت: YYYY-MM-DD) [required]\n- start_date_gregorian (str): تاریخ شروع پروژه به میلادی. (الزامی) (فرمت: YYYY-MM-DD) [required]\n- end_date_gregorian (str): تاریخ پایان پروژه به میلادی. (الزامی) (فرمت: YYYY-MM-DD) [required]\n- total_infrastructure (str, optional): زیر بنای کل پروژه به متر مربع. (پیش‌فرض: 0.00)\n- correction_factor (str, optional): ضریب اصلاحی برای محاسبات پروژه. (پیش‌فرض: 1.0000000000)\n- construction_contractor_percentage (str, optional): درصد پیمان ساخت از مجموع سایر هزینه‌ها (به صورت اعشاری، مثلاً 0.100 برای 10%). (پیش‌فرض: 0.100)\n- description (str, optional): توضیحات اضافی درباره پروژه. (اختیاری)\n- color (str, optional): رنگ نمایش پروژه (فرمت HEX، مثال: #667eea). (پیش‌فرض: #667eea)\n- icon (str, optional): نام کلاس آیکون Font Awesome (مثال: fa-building). (پیش‌فرض: fa-building)\n- gradient_primary_color (str, optional): رنگ اول گرادیانت پس‌زمینه (فرمت HEX). (پیش‌فرض: #667eea)\n- gradient_secondary_color (str, optional): رنگ دوم گرادیانت پس‌زمینه (فرمت HEX). (پیش‌فرض: #764ba2)\n\nمثال‌های استفاده:\n- POST /api/v1/Project/\n- {\n- \"name\": \"پروژه ساختمانی نمونه\",\n- \"start_date_shamsi\": \"1403-01-01\",\n- \"end_date_shamsi\": \"1405-12-29\",\n\nنکات مهم:\n- - جزئیات فیلدها در serializer descriptions موجود است\n- - نیاز به احراز هویت و دسترسی APISecurityPermission دارد\n\nAPI Endpoint: POST /api/v1/Project/\nOperation ID: Project_create\nدسته‌بندی: Project","metadata":{"tool_name":"project_create","category":"Project","method":"POST","path":"/api/v1/Project/","operation_id":"Project_create","tags":["Project"],"has_auth":true,"parameters":[{"name":"name","type":"string","required":true,"description":"نام پروژه ساختمانی. (الزامی)"},{"name":"start_date_shamsi","type":"string","required":true,"description":"تاریخ شروع پروژه به شمسی. (الزامی)"},{"name":"end_date_shamsi","type":"string","required":true,"description":"تاریخ پایان پروژه به شمسی. (الزامی)"},{"name":"start_date_gregorian","type":"string","required":true,"description":"تاریخ شروع پروژه به میلادی. (الزامی)"},{"name":"end_date_gregorian","type":"string","required":true,"description":"تاریخ پایان پروژه به میلادی. (الزامی)"},{"name":"total_infrastructure","type":"string","required":false,"description":"زیر بنای کل پروژه به متر مربع. (پیش‌فرض: 0.00)"},{"name":"correction_factor","type":"string","required":false,"description":"ضریب اصلاحی برای محاسبات پروژه. (پیش‌فرض: 1.0000000000)"},{"name":"construction_contractor_percentage","type":"string","required":false,"description":"درصد پیمان ساخت از مجموع سایر هزینه‌ها (به صورت اعشاری، مثلاً 0.100 برای 10%). (پیش‌فرض: 0.100)"},{"name":"description","type":"string","required":false,"description":"توضیحات اضافی درباره پروژه. (اختیاری)"},{"name":"color","type":"string","required":false,"description":"رنگ نمایش پروژه (فرمت HEX، مثال: #667eea). (پیش‌فرض: #667eea)"},{"name":"icon","type":"string","required":false,"description":"نام کلاس آیکون Font Awesome (مثال: fa-building). (پیش‌فرض: fa-building)"},{"name":"gradient_primary_color","type":"string","required":false,"description":"رنگ اول گرادیانت پس‌زمینه (فرمت HEX). (پیش‌فرض: #667eea)"},{"name":"gradient_secondary_color","type":"string","required":false,"description":"رنگ دوم گرادیانت پس‌زمینه (فرمت HEX). (پیش‌فرض: #764ba2)"}],"response_codes":["201: Project"]}},{"page_content":"Tool: project_retrieve\nDescription: دریافت جزئیات یک پروژه خاص\n\nاین متد اطلاعات کامل پروژه با شناسه مشخص شده را برمی‌گرداند.\n\nURL Parameters:\n    - pk: شناسه یکتای پروژه\n\nReturns:\n    Response با اطلاعات کامل پروژه\n\nمثال:\n    GET /api/v1/Project/1/\n\nنکات:\n    - نیاز به احراز هویت دارد\n\nپارامترها:\n- id (int): یک مقداد عدد یکتا که این پروژه را شناسایی میکند. [required]\n\nمثال‌های استفاده:\n- GET /api/v1/Project/1/\n\nنکات مهم:\n- - نیاز به احراز هویت دارد\n\nAPI Endpoint: GET /api/v1/Project/{id}/\nOperation ID: Project_retrieve\nدسته‌بندی: Project","metadata":{"tool_name":"project_retrieve","category":"Project","method":"GET","path":"/api/v1/Project/{id}/","operation_id":"Project_retrieve","tags":["Project"],"has_auth":true,"parameters":[{"name":"id","type":"integer","required":true,"description":"یک مقداد عدد یکتا که این پروژه را شناسایی میکند."}],"response_codes":["200: Project"]}},{"page_content":"Tool: project_update\nDescription: به‌روزرسانی کامل پروژه\n\nاین متد امکان تغییر همه فیلدهای یک پروژه را فراهم می‌کند.\nتمام فیلدهای قابل ویرایش باید ارسال شوند.\n\nURL Parameters:\n    - pk: شناسه یکتای پروژه\n\nRequest Body:\n    - تمام فیلدهای قابل ویرایش\n\nReturns:\n    Response با اطلاعات به‌روزرسانی شده پروژه (status 200)\n\nمثال:\n    PUT /api/v1/Project/1/\n    {\n        \"name\": \"پروژه به‌روزرسانی شده\",\n        \"start_date_shamsi\": \"1403-01-01\",\n        \"end_date_shamsi\": \"1405-12-29\"\n    }\n\nنکات:\n    - همه فیلدها باید ارسال شوند\n    - برای به‌روزرسانی جزئی از PATCH استفاده کنید\n    - جزئیات فیلدها در serializer descriptions موجود است\n    - نیاز به احراز هویت دارد\n\nپارامترها:\n- id (int): یک مقداد عدد یکتا که این پروژه را شناسایی میکند. [required]\n- name (str): نام پروژه ساختمانی. (الزامی) [required]\n- start_date_shamsi (str): تاریخ شروع پروژه به شمسی. (الزامی) (فرمت: YYYY-MM-DD) [required]\n- end_date_shamsi (str): تاریخ پایان پروژه به شمسی. (الزامی) (فرمت: YYYY-MM-DD) [required]\n- start_date_gregorian (str): تاریخ شروع پروژه به میلادی. (الزامی) (فرمت: YYYY-MM-DD) [required]\n- end_date_gregorian (str): تاریخ پایان پروژه به میلادی. (الزامی) (فرمت: YYYY-MM-DD) [required]\n- total_infrastructure (str, optional): زیر بنای کل پروژه به متر مربع. (پیش‌فرض: 0.00)\n- correction_factor (str, optional): ضریب اصلاحی برای محاسبات پروژه. (پیش‌فرض: 1.0000000000)\n- construction_contractor_percentage (str, optional): درصد پیمان ساخت از مجموع سایر هزینه‌ها (به صورت اعشاری، مثلاً 0.100 برای 10%). (پیش‌فرض: 0.100)\n- description (str, optional): توضیحات اضافی درباره پروژه. (اختیاری)\n- color (str, optional): رنگ نمایش پروژه (فرمت HEX، مثال: #667eea). (پیش‌فرض: #667eea)\n- icon (str, optional): نام کلاس آیکون Font Awesome (مثال: fa-building). (پیش‌فرض: fa-building)\n- gradient_primary_color (str, optional): رنگ اول گرادیانت پس‌زمینه (فرمت HEX). (پیش‌فرض: #667eea)\n- gradient_secondary_color (str, optional): رنگ دوم گرادیانت پس‌زمینه (فرمت HEX). (پیش‌فرض: #764ba2)\n\nمثال‌های استفاده:\n- PUT /api/v1/Project/1/\n- {\n- \"name\": \"پروژه به‌روزرسانی شده\",\n- \"start_date_shamsi\": \"1403-01-01\",\n- \"end_date_shamsi\": \"1405-12-29\"\n\nنکات مهم:\n- - همه فیلدها باید ارسال شوند\n- - برای به‌روزرسانی جزئی از PATCH استفاده کنید\n- - جزئیات فیلدها در serializer descriptions موجود است\n- - نیاز به احراز هویت دارد\n\nAPI Endpoint: PUT /api/v1/Project/{id}/\nOperation ID: Project_update\nدسته‌بندی: Project","metadata":{"tool_name":"project_update","category":"Project","method":"PUT","path":"/api/v1/Project/{id}/","operation_id":"Project_update","tags":["Project"],"has_auth":true,"parameters":[{"name":"id","type":"integer","required":true,"description":"یک مقداد عدد یکتا که این پروژه را شناسایی میکند."},{"name":"name","type":"string","required":true,"description":"نام پروژه ساختمانی. (الزامی)"},{"name":"start_date_shamsi","type":"string","required":true,"description":"تاریخ شروع پروژه به شمسی. (الزامی)"},{"name":"end_date_shamsi","type":"string","required":true,"description":"تاریخ پایان پروژه به شمسی. (الزامی)"},{"name":"start_date_gregorian","type":"string","required":true,"description":"تاریخ شروع پروژه به میلادی. (الزامی)"},{"name":"end_date_gregorian","type":"string","required":true,"description":"تاریخ پایان پروژه به میلادی. (الزامی)"},{"name":"total_infrastructure","type":"string","required":false,"description":"زیر بنای کل پروژه به متر مربع. (پیش‌فرض: 0.00)"},{"name":"correction_factor","type":"string","required":false,"description":"ضریب اصلاحی برای محاسبات پروژه. (پیش‌فرض: 1.0000000000)"},{"name":"construction_contractor_percentage","type":"string","required":false,"description":"درصد پیمان ساخت از مجموع سایر هزینه‌ها (به صورت اعشاری، مثلاً 0.100 برای 10%). (پیش‌فرض: 0.100)"},{"name":"description","type":"string","required":false,"description":"توضیحات اضافی درباره پروژه. (اختیاری)"},{"name":"color","type":"string","required":false,"description":"رنگ نمایش پروژه (فرمت HEX، مثال: #667eea). (پیش‌فرض: #667eea)"},{"name":"icon","type":"string","required":false,"description":"نام کلاس آیکون Font Awesome (مثال: fa-building). (پیش‌فرض: fa-building)"},{"name":"gradient_primary_color","type":"string","required":false,"description":"رنگ اول گرادیانت پس‌زمینه (فرمت HEX). (پیش‌فرض: #667eea)"},{"name":"gradient_secondary_color","type":"string","required":false,"description":"رنگ دوم گرادیانت پس‌زمینه (فرمت HEX). (پیش‌فرض: #764ba2)"}],"response_codes":["200: Project"]}},{"page_content":"Tool: project_partial_update\nDescription: به‌روزرسانی جزئی پروژه\n\nاین متد امکان تغییر بخشی از فیلدهای پروژه را فراهم می‌کند.\nفقط فیلدهای ارسال شده تغییر می‌کنند.\n\nURL Parameters:\n    - pk: شناسه یکتای پروژه\n\nRequest Body:\n    - فیلدهای انتخابی برای به‌روزرسانی\n\nReturns:\n    Response با اطلاعات به‌روزرسانی شده پروژه (status 200)\n\nمثال:\n    PATCH /api/v1/Project/1/\n    {\n        \"name\": \"نام جدید پروژه\"\n    }\n\nنکات:\n    - فقط فیلدهای ارسال شده تغییر می‌کنند\n    - فیلدهای ارسال نشده حفظ می‌شوند\n    - انعطاف بیشتری نسبت به PUT دارد\n    - جزئیات فیلدها در serializer descriptions موجود است\n    - نیاز به احراز هویت دارد\n\nپارامترها:\n- id (int): یک مقداد عدد یکتا که این پروژه را شناسایی میکند. [required]\n- name (str, optional): نام پروژه ساختمانی. (الزامی)\n- start_date_shamsi (str, optional): تاریخ شروع پروژه به شمسی. (الزامی) (فرمت: YYYY-MM-DD)\n- end_date_shamsi (str, optional): تاریخ پایان پروژه به شمسی. (الزامی) (فرمت: YYYY-MM-DD)\n- start_date_gregorian (str, optional): تاریخ شروع پروژه به میلادی. (الزامی) (فرمت: YYYY-MM-DD)\n- end_date_gregorian (str, optional): تاریخ پایان پروژه به میلادی. (الزامی) (فرمت: YYYY-MM-DD)\n- total_infrastructure (str, optional): زیر بنای کل پروژه به متر مربع. (پیش‌فرض: 0.00)\n- correction_factor (str, optional): ضریب اصلاحی برای محاسبات پروژه. (پیش‌فرض: 1.0000000000)\n- construction_contractor_percentage (str, optional): درصد پیمان ساخت از مجموع سایر هزینه‌ها (به صورت اعشاری، مثلاً 0.100 برای 10%). (پیش‌فرض: 0.100)\n- description (str, optional): توضیحات اضافی درباره پروژه. (اختیاری)\n- color (str, optional): رنگ نمایش پروژه (فرمت HEX، مثال: #667eea). (پیش‌فرض: #667eea)\n- icon (str, optional): نام کلاس آیکون Font Awesome (مثال: fa-building). (پیش‌فرض: fa-building)\n- gradient_primary_color (str, optional): رنگ اول گرادیانت پس‌زمینه (فرمت HEX). (پیش‌فرض: #667eea)\n- gradient_secondary_color (str, optional): رنگ دوم گرادیانت پس‌زمینه (فرمت HEX). (پیش‌فرض: #764ba2)\n\nمثال‌های استفاده:\n- PATCH /api/v1/Project/1/\n- {\n- \"name\": \"نام جدید پروژه\"\n- }\n\nنکات مهم:\n- - فقط فیلدهای ارسال شده تغییر می‌کنند\n- - فیلدهای ارسال نشده حفظ می‌شوند\n- - انعطاف بیشتری نسبت به PUT دارد\n- - جزئیات فیلدها در serializer descriptions موجود است\n- - نیاز به احراز هویت دارد\n\nAPI Endpoint: PATCH /api/v1/Project/{id}/\nOperation ID: Project_partial_update\nدسته‌بندی: Project","metadata":{"tool_name":"project_partial_update","category":"Project","method":"PATCH","path":"/api/v1/Project/{id}/","operation_id":"Project_partial_update","tags":["Project"],"has_auth":true,"parameters":[{"name":"id","type":"integer","required":true,"description":"یک مقداد عدد یکتا که این پروژه را شناسایی میکند."},{"name":"name","type":"string","required":false,"description":"نام پروژه ساختمانی. (الزامی)"},{"name":"start_date_shamsi","type":"string","required":false,"description":"تاریخ شروع پروژه به شمسی. (الزامی)"},{"name":"end_date_shamsi","type":"string","required":false,"description":"تاریخ پایان پروژه به شمسی. (الزامی)"},{"name":"start_date_gregorian","type":"string","required":false,"description":"تاریخ شروع پروژه به میلادی. (الزامی)"},{"name":"end_date_gregorian","type":"string","required":false,"description":"تاریخ پایان پروژه به میلادی. (الزامی)"},{"name":"total_infrastructure","type":"string","required":false,"description":"زیر بنای کل پروژه به متر مربع. (پیش‌فرض: 0.00)"},{"name":"correction_factor","type":"string","required":false,"description":"ضریب اصلاحی برای محاسبات پروژه. (پیش‌فرض: 1.0000000000)"},{"name":"construction_contractor_percentage","type":"string","required":false,"description":"درصد پیمان ساخت از مجموع سایر هزینه‌ها (به صورت اعشاری، مثلاً 0.100 برای 10%). (پیش‌فرض: 0.100)"},{"name":"description","type":"string","required":false,"description":"توضیحات اضافی درباره پروژه. (اختیاری)"},{"name":"color","type":"string","required":false,"description":"رنگ نمایش پروژه (فرمت HEX، مثال: #667eea). (پیش‌فرض: #667eea)"},{"name":"icon","type":"string","required":false,"description":"نام کلاس آیکون Font Awesome (مثال: fa-building). (پیش‌فرض: fa-building)"},{"name":"gradient_primary_color","type":"string","required":false,"description":"رنگ اول گرادیانت پس‌زمینه (فرمت HEX). (پیش‌فرض: #667eea)"},{"name":"gradient_secondary_color","type":"string","required":false,"description":"رنگ دوم گرادیانت پس‌زمینه (فرمت HEX). (پیش‌فرض: #764ba2)"}],"response_codes":["200: Project"]}},{"page_content":"Tool: project_destroy\nDescription: حذف پروژه\n\nاین متد پروژه را به‌طور کامل و برگشت‌ناپذیری حذف می‌کند.\n\nURL Parameters:\n    - pk: شناسه یکتای پروژه\n\nReturns:\n    Response خالی با status 204 No Content در صورت موفقیت\n\nمثال:\n    DELETE /api/v1/Project/1/\n\nنکات:\n    - حذف برگشت‌ناپذیر است\n    - نیاز به احراز هویت و دسترسی APISecurityPermission دارد\n    - در صورت وجود وابستگی (هزینه‌ها، تراکنش‌ها، واحدها)، ممکن است حذف ناموفق باشد\n\nپارامترها:\n- id (int): یک مقداد عدد یکتا که این پروژه را شناسایی میکند. [required]\n\nمثال‌های استفاده:\n- DELETE /api/v1/Project/1/\n\nنکات مهم:\n- - حذف برگشت‌ناپذیر است\n- - نیاز به احراز هویت و دسترسی APISecurityPermission دارد\n- - در صورت وجود وابستگی (هزینه‌ها، تراکنش‌ها، واحدها)، ممکن است حذف ناموفق باشد\n\nAPI Endpoint: DELETE /api/v1/Project/{id}/\nOperation ID: Project_destroy\nدسته‌بندی: Project","metadata":{"tool_name":"project_destroy","category":"Project","method":"DELETE","path":"/api/v1/Project/{id}/","operation_id":"Project_destroy","tags":["Project"],"has_auth":true,"parameters":[{"name":"id","type":"integer","required":true,"description":"یک مقداد عدد یکتا که این پروژه را شناسایی میکند."}],"response_codes":[]}},{"page_content":"Tool: project_active_retrieve\nDescription: دریافت پروژه جاری (از session)\n\nمثال‌های استفاده:\n- project_active_retrieve()\n\nنکات مهم:\n- نیاز به احراز هویت دارد\n\nAPI Endpoint: GET /api/v1/Project/active/\nOperation ID: Project_active_retrieve\nدسته‌بندی: Project","metadata":{"tool_name":"project_active_retrieve","category":"Project","method":"GET","path":"/api/v1/Project/active/","operation_id":"Project_active_retrieve","tags":["Project"],"has_auth":true,"parameters":[],"response_codes":["200: Project"]}},{"page_content":"Tool: project_comprehensive_analysis_retrieve\nDescription: دریافت تحلیل جامع پروژه شامل تمام محاسبات مالی\n\nمثال‌های استفاده:\n- project_comprehensive_analysis_retrieve()\n\nنکات مهم:\n- نیاز به احراز هویت دارد\n\nAPI Endpoint: GET /api/v1/Project/comprehensive_analysis/\nOperation ID: Project_comprehensive_analysis_retrieve\nدسته‌بندی: Project","metadata":{"tool_name":"project_comprehensive_analysis_retrieve","category":"Project","method":"GET","path":"/api/v1/Project/comprehensive_analysis/","operation_id":"Project_comprehensive_analysis_retrieve","tags":["Project"],"has_auth":true,"parameters":[],"response_codes":["200: Project"]}},{"page_content":"Tool: project_cost_metrics_retrieve\nDescription: دریافت متریک‌های هزینه\n\nمثال‌های استفاده:\n- project_cost_metrics_retrieve()\n\nنکات مهم:\n- نیاز به احراز هویت دارد\n\nAPI Endpoint: GET /api/v1/Project/cost_metrics/\nOperation ID: Project_cost_metrics_retrieve\nدسته‌بندی: Project","metadata":{"tool_name":"project_cost_metrics_retrieve","category":"Project","method":"GET","path":"/api/v1/Project/cost_metrics/","operation_id":"Project_cost_metrics_retrieve","tags":["Project"],"has_auth":true,"parameters":[],"response_codes":["200: Project"]}},{"page_content":"Tool: project_current_retrieve\nDescription: دریافت پروژه جاری کاربر از session\n\nمثال‌های استفاده:\n- project_current_retrieve()\n\nنکات مهم:\n- نیاز به احراز هویت دارد\n\nAPI Endpoint: GET /api/v1/Project/current/\nOperation ID: Project_current_retrieve\nدسته‌بندی: Project","metadata":{"tool_name":"project_current_retrieve","category":"Project","method":"GET","path":"/api/v1/Project/current/","operation_id":"Project_current_retrieve","tags":["Project"],"has_auth":true,"parameters":[],"response_codes":["200: Project"]}},{"page_content":"Tool: project_profit_metrics_retrieve\nDescription: دریافت متریک‌های سود (کل، سالانه، ماهانه، روزانه)\n\nاین endpoint متریک‌های مختلف سود شامل سود کل، سالانه، ماهانه و روزانه\nرا برای پروژه محاسبه و برمی‌گرداند.\n\nParameters:\n    project_id (int, optional): شناسه پروژه (از query parameter یا پروژه جاری)\n\nReturns:\n    Response: شامل متریک‌های سود\n\nنکات مهم:\n- اگر پروژه جاری وجود نداشته باشد، خطای 400 برمی‌گرداند\n- محاسبات بر اساس تاریخ شروع و پایان پروژه انجام می‌شود\n- مبالغ به تومان هستند\n\nمثال‌های استفاده:\n- project_profit_metrics_retrieve()\n\nنکات مهم:\n- - اگر پروژه جاری وجود نداشته باشد، خطای 400 برمی‌گرداند\n- - محاسبات بر اساس تاریخ شروع و پایان پروژه انجام می‌شود\n- - مبالغ به تومان هستند\n\nAPI Endpoint: GET /api/v1/Project/profit_metrics/\nOperation ID: Project_profit_metrics_retrieve\nدسته‌بندی: Project","metadata":{"tool_name":"project_profit_metrics_retrieve","category":"Project","method":"GET","path":"/api/v1/Project/profit_metrics/","operation_id":"Project_profit_metrics_retrieve","tags":["Project"],"has_auth":true,"parameters":[],"response_codes":["200: Project"]}},{"page_content":"Tool: project_statistics_detailed_retrieve\nDescription: دریافت آمار تفصیلی پروژه\n\nمثال‌های استفاده:\n- project_statistics_detailed_retrieve()\n\nنکات مهم:\n- نیاز به احراز هویت دارد\n\nAPI Endpoint: GET /api/v1/Project/project_statistics_detailed/\nOperation ID: Project_project_statistics_detailed_retrieve\nدسته‌بندی: Project","metadata":{"tool_name":"project_statistics_detailed_retrieve","category":"Project","method":"GET","path":"/api/v1/Project/project_statistics_detailed/","operation_id":"Project_project_statistics_detailed_retrieve","tags":["Project"],"has_auth":true,"parameters":[],"response_codes":["200: Project"]}},{"page_content":"Tool: project_timeline_retrieve\nDescription: محاسبه روزهای مانده و گذشته پروژه بر اساس تاریخ امروز\n\nمثال‌های استفاده:\n- project_timeline_retrieve()\n\nنکات مهم:\n- نیاز به احراز هویت دارد\n\nAPI Endpoint: GET /api/v1/Project/project_timeline/\nOperation ID: Project_project_timeline_retrieve\nدسته‌بندی: Project","metadata":{"tool_name":"project_timeline_retrieve","category":"Project","method":"GET","path":"/api/v1/Project/project_timeline/","operation_id":"Project_project_timeline_retrieve","tags":["Project"],"has_auth":true,"parameters":[],"response_codes":["200: Project"]}},{"page_content":"Tool: project_set_active_create\nDescription: تنظیم پروژه فعال\n\nپارامترها:\n- name (str): نام پروژه ساختمانی. (الزامی) [required]\n- start_date_shamsi (str): تاریخ شروع پروژه به شمسی. (الزامی) (فرمت: YYYY-MM-DD) [required]\n- end_date_shamsi (str): تاریخ پایان پروژه به شمسی. (الزامی) (فرمت: YYYY-MM-DD) [required]\n- start_date_gregorian (str): تاریخ شروع پروژه به میلادی. (الزامی) (فرمت: YYYY-MM-DD) [required]\n- end_date_gregorian (str): تاریخ پایان پروژه به میلادی. (الزامی) (فرمت: YYYY-MM-DD) [required]\n- total_infrastructure (str, optional): زیر بنای کل پروژه به متر مربع. (پیش‌فرض: 0.00)\n- correction_factor (str, optional): ضریب اصلاحی برای محاسبات پروژه. (پیش‌فرض: 1.0000000000)\n- construction_contractor_percentage (str, optional): درصد پیمان ساخت از مجموع سایر هزینه‌ها (به صورت اعشاری، مثلاً 0.100 برای 10%). (پیش‌فرض: 0.100)\n- description (str, optional): توضیحات اضافی درباره پروژه. (اختیاری)\n- color (str, optional): رنگ نمایش پروژه (فرمت HEX، مثال: #667eea). (پیش‌فرض: #667eea)\n- icon (str, optional): نام کلاس آیکون Font Awesome (مثال: fa-building). (پیش‌فرض: fa-building)\n- gradient_primary_color (str, optional): رنگ اول گرادیانت پس‌زمینه (فرمت HEX). (پیش‌فرض: #667eea)\n- gradient_secondary_color (str, optional): رنگ دوم گرادیانت پس‌زمینه (فرمت HEX). (پیش‌فرض: #764ba2)\n\nمثال‌های استفاده:\n- project_set_active_create(name='value', start_date_shamsi='value', end_date_shamsi='value', start_date_gregorian='value', end_date_gregorian='value')\n\nنکات مهم:\n- نیاز به احراز هویت دارد\n\nAPI Endpoint: POST /api/v1/Project/set_active/\nOperation ID: Project_set_active_create\nدسته‌بندی: Project","metadata":{"tool_name":"project_set_active_create","category":"Project","method":"POST","path":"/api/v1/Project/set_active/","operation_id":"Project_set_active_create","tags":["Project"],"has_auth":true,"parameters":[{"name":"name","type":"string","required":true,"description":"نام پروژه ساختمانی. (الزامی)"},{"name":"start_date_shamsi","type":"string","required":true,"description":"تاریخ شروع پروژه به شمسی. (الزامی)"},{"name":"end_date_shamsi","type":"string","required":true,"description":"تاریخ پایان پروژه به شمسی. (الزامی)"},{"name":"start_date_gregorian","type":"string","required":true,"description":"تاریخ شروع پروژه به میلادی. (الزامی)"},{"name":"end_date_gregorian","type":"string","required":true,"description":"تاریخ پایان پروژه به میلادی. (الزامی)"},{"name":"total_infrastructure","type":"string","required":false,"description":"زیر بنای کل پروژه به متر مربع. (پیش‌فرض: 0.00)"},{"name":"correction_factor","type":"string","required":false,"description":"ضریب اصلاحی برای محاسبات پروژه. (پیش‌فرض: 1.0000000000)"},{"name":"construction_contractor_percentage","type":"string","required":false,"description":"درصد پیمان ساخت از مجموع سایر هزینه‌ها (به صورت اعشاری، مثلاً 0.100 برای 10%). (پیش‌فرض: 0.100)"},{"name":"description","type":"string","required":false,"description":"توضیحات اضافی درباره پروژه. (اختیاری)"},{"name":"color","type":"string","required":false,"description":"رنگ نمایش پروژه (فرمت HEX، مثال: #667eea). (پیش‌فرض: #667eea)"},{"name":"icon","type":"string","required":false,"description":"نام کلاس آیکون Font Awesome (مثال: fa-building). (پیش‌فرض: fa-building)"},{"name":"gradient_primary_color","type":"string","required":false,"description":"رنگ اول گرادیانت پس‌زمینه (فرمت HEX). (پیش‌فرض: #667eea)"},{"name":"gradient_secondary_color","type":"string","required":false,"description":"رنگ دوم گرادیانت پس‌زمینه (فرمت HEX). (پیش‌فرض: #764ba2)"}],"response_codes":["200: Project"]}},{"page_content":"Tool: project_statistics_retrieve\nDescription: دریافت آمار کامل پروژه جاری شامل اطلاعات پروژه و آمار واحدها\n\nمثال‌های استفاده:\n- project_statistics_retrieve()\n\nنکات مهم:\n- نیاز به احراز هویت دارد\n\nAPI Endpoint: GET /api/v1/Project/statistics/\nOperation ID: Project_statistics_retrieve\nدسته‌بندی: Project","metadata":{"tool_name":"project_statistics_retrieve","category":"Project","method":"GET","path":"/api/v1/Project/statistics/","operation_id":"Project_statistics_retrieve","tags":["Project"],"has_auth":true,"parameters":[],"response_codes":["200: Project"]}},{"page_content":"Tool: project_switch_create\nDescription: تغییر پروژه جاری کاربر\n\nپارامترها:\n- name (str): نام پروژه ساختمانی. (الزامی) [required]\n- start_date_shamsi (str): تاریخ شروع پروژه به شمسی. (الزامی) (فرمت: YYYY-MM-DD) [required]\n- end_date_shamsi (str): تاریخ پایان پروژه به شمسی. (الزامی) (فرمت: YYYY-MM-DD) [required]\n- start_date_gregorian (str): تاریخ شروع پروژه به میلادی. (الزامی) (فرمت: YYYY-MM-DD) [required]\n- end_date_gregorian (str): تاریخ پایان پروژه به میلادی. (الزامی) (فرمت: YYYY-MM-DD) [required]\n- total_infrastructure (str, optional): زیر بنای کل پروژه به متر مربع. (پیش‌فرض: 0.00)\n- correction_factor (str, optional): ضریب اصلاحی برای محاسبات پروژه. (پیش‌فرض: 1.0000000000)\n- construction_contractor_percentage (str, optional): درصد پیمان ساخت از مجموع سایر هزینه‌ها (به صورت اعشاری، مثلاً 0.100 برای 10%). (پیش‌فرض: 0.100)\n- description (str, optional): توضیحات اضافی درباره پروژه. (اختیاری)\n- color (str, optional): رنگ نمایش پروژه (فرمت HEX، مثال: #667eea). (پیش‌فرض: #667eea)\n- icon (str, optional): نام کلاس آیکون Font Awesome (مثال: fa-building). (پیش‌فرض: fa-building)\n- gradient_primary_color (str, optional): رنگ اول گرادیانت پس‌زمینه (فرمت HEX). (پیش‌فرض: #667eea)\n- gradient_secondary_color (str, optional): رنگ دوم گرادیانت پس‌زمینه (فرمت HEX). (پیش‌فرض: #764ba2)\n\nمثال‌های استفاده:\n- project_switch_create(name='value', start_date_shamsi='value', end_date_shamsi='value', start_date_gregorian='value', end_date_gregorian='value')\n\nنکات مهم:\n- نیاز به احراز هویت دارد\n\nAPI Endpoint: POST /api/v1/Project/switch/\nOperation ID: Project_switch_create\nدسته‌بندی: Project","metadata":{"tool_name":"project_switch_create","category":"Project","method":"POST","path":"/api/v1/Project/switch/","operation_id":"Project_switch_create","tags":["Project"],"has_auth":true,"parameters":[{"name":"name","type":"string","required":true,"description":"نام پروژه ساختمانی. (الزامی)"},{"name":"start_date_shamsi","type":"string","required":true,"description":"تاریخ شروع پروژه به شمسی. (الزامی)"},{"name":"end_date_shamsi","type":"string","required":true,"description":"تاریخ پایان پروژه به شمسی. (الزامی)"},{"name":"start_date_gregorian","type":"string","required":true,"description":"تاریخ شروع پروژه به میلادی. (الزامی)"},{"name":"end_date_gregorian","type":"string","required":true,"description":"تاریخ پایان پروژه به میلادی. (الزامی)"},{"name":"total_infrastructure","type":"string","required":false,"description":"زیر بنای کل پروژه به متر مربع. (پیش‌فرض: 0.00)"},{"name":"correction_factor","type":"string","required":false,"description":"ضریب اصلاحی برای محاسبات پروژه. (پیش‌فرض: 1.0000000000)"},{"name":"construction_contractor_percentage","type":"string","required":false,"description":"درصد پیمان ساخت از مجموع سایر هزینه‌ها (به صورت اعشاری، مثلاً 0.100 برای 10%). (پیش‌فرض: 0.100)"},{"name":"description","type":"string","required":false,"description":"توضیحات اضافی درباره پروژه. (اختیاری)"},{"name":"color","type":"string","required":false,"description":"رنگ نمایش پروژه (فرمت HEX، مثال: #667eea). (پیش‌فرض: #667eea)"},{"name":"icon","type":"string","required":false,"description":"نام کلاس آیکون Font Awesome (مثال: fa-building). (پیش‌فرض: fa-building)"},{"name":"gradient_primary_color","type":"string","required":false,"description":"رنگ اول گرادیانت پس‌زمینه (فرمت HEX). (پیش‌فرض: #667eea)"},{"name":"gradient_secondary_color","type":"string","required":false,"description":"رنگ دوم گرادیانت پس‌زمینه (فرمت HEX). (پیش‌فرض: #764ba2)"}],"response_codes":["200: Project"]}},{"page_content":"Tool: sale_list\nDescription: دریافت لیست تمام فروش/مرجوعی‌های پروژه جاری\n\nاین متد لیست فروش/مرجوعی‌های مرتبط با پروژه فعال را برمی‌گرداند.\nنتایج به صورت صفحه‌بندی شده و قابل مرتب‌سازی هستند.\n\nQuery Parameters:\n    - page: شماره صفحه (پیش‌فرض: 1)\n    - page_size: تعداد رکورد در هر صفحه (پیش‌فرض: 10)\n    - ordering: فیلد مرتب‌سازی\n\nReturns:\n    Response با ساختار paginated شامل results, count, next, previous\n\nمثال:\n    GET /api/v1/Sale/?page=1&page_size=20\n\nنکات:\n    - فقط فروش/مرجوعی‌های پروژه جاری برگردانده می‌شود\n    - نیاز به احراز هویت دارد\n\nمثال‌های استفاده:\n- GET /api/v1/Sale/?page=1&page_size=20\n\nنکات مهم:\n- - فقط فروش/مرجوعی‌های پروژه جاری برگردانده می‌شود\n- - نیاز به احراز هویت دارد\n\nAPI Endpoint: GET /api/v1/Sale/\nOperation ID: Sale_list\nدسته‌بندی: Sale","metadata":{"tool_name":"sale_list","category":"Sale","method":"GET","path":"/api/v1/Sale/","operation_id":"Sale_list","tags":["Sale"],"has_auth":true,"parameters":[],"response_codes":["200: array"]}},{"page_content":"Tool: sale_create\nDescription: ایجاد فروش/مرجوعی جدید برای پروژه جاری\n\nاین متد فروش/مرجوعی جدید را برای پروژه فعال ثبت می‌کند.\nپروژه به صورت خودکار از session کاربر تعیین می‌شود.\n\nRequest Body:\n    - period (الزامی): شناسه دوره\n    - amount (الزامی): مبلغ فروش/مرجوعی (به صورت string)\n    - description (اختیاری): توضیحات\n\nReturns:\n    Response با اطلاعات فروش/مرجوعی ایجاد شده (status 201)\n\nمثال:\n    POST /api/v1/Sale/\n    {\n        \"period\": 1,\n        \"amount\": \"100000000\",\n        \"description\": \"فروش واحد 101\"\n    }\n\nنکات:\n    - جزئیات فیلدها در serializer descriptions موجود است\n    - پروژه به صورت خودکار از session تنظیم می‌شود\n    - نیاز به احراز هویت و دسترسی APISecurityPermission دارد\n\nپارامترها:\n- project (int, optional): شناسه پروژه. اگر مشخص نشود، از پروژه جاری session استفاده می‌شود.\n- period (int): شناسه دوره‌ای که فروش/مرجوعی برای آن ثبت می‌شود. دوره باید متعلق به پروژه جاری باشد. (الزامی) [required]\n- amount (str): مبلغ فروش/مرجوعی به تومان. برای جلوگیری از مشکلات دقت، به صورت string ارسال شود. (الزامی) [required]\n- description (str, optional): توضیحات تکمیلی درباره فروش/مرجوعی. (اختیاری)\n\nمثال‌های استفاده:\n- POST /api/v1/Sale/\n- {\n- \"period\": 1,\n- \"amount\": \"100000000\",\n- \"description\": \"فروش واحد 101\"\n\nنکات مهم:\n- - جزئیات فیلدها در serializer descriptions موجود است\n- - پروژه به صورت خودکار از session تنظیم می‌شود\n- - نیاز به احراز هویت و دسترسی APISecurityPermission دارد\n\nAPI Endpoint: POST /api/v1/Sale/\nOperation ID: Sale_create\nدسته‌بندی: Sale","metadata":{"tool_name":"sale_create","category":"Sale","method":"POST","path":"/api/v1/Sale/","operation_id":"Sale_create","tags":["Sale"],"has_auth":true,"parameters":[{"name":"project","type":"integer","required":false,"description":"شناسه پروژه. اگر مشخص نشود، از پروژه جاری session استفاده می‌شود."},{"name":"period","type":"integer","required":true,"description":"شناسه دوره‌ای که فروش/مرجوعی برای آن ثبت می‌شود. دوره باید متعلق به پروژه جاری باشد. (الزامی)"},{"name":"amount","type":"string","required":true,"description":"مبلغ فروش/مرجوعی به تومان. برای جلوگیری از مشکلات دقت، به صورت string ارسال شود. (الزامی)"},{"name":"description","type":"string","required":false,"description":"توضیحات تکمیلی درباره فروش/مرجوعی. (اختیاری)"}],"response_codes":["201: Sale"]}},{"page_content":"Tool: sale_retrieve\nDescription: دریافت جزئیات یک فروش/مرجوعی خاص\n\nاین متد اطلاعات کامل فروش/مرجوعی با شناسه مشخص شده را برمی‌گرداند.\n\nURL Parameters:\n    - pk: شناسه یکتای فروش/مرجوعی\n\nReturns:\n    Response با اطلاعات کامل فروش/مرجوعی شامل project_data و period_data\n\nمثال:\n    GET /api/v1/Sale/1/\n\nنکات:\n    - فقط فروش/مرجوعی‌های پروژه جاری قابل دسترسی هستند\n    - در صورت عدم دسترسی، خطای 403 برگردانده می‌شود\n    - نیاز به احراز هویت دارد\n\nپارامترها:\n- id (int): یک مقداد عدد یکتا که این فروش/مرجوعی را شناسایی میکند. [required]\n\nمثال‌های استفاده:\n- GET /api/v1/Sale/1/\n\nنکات مهم:\n- - فقط فروش/مرجوعی‌های پروژه جاری قابل دسترسی هستند\n- - در صورت عدم دسترسی، خطای 403 برگردانده می‌شود\n- - نیاز به احراز هویت دارد\n\nAPI Endpoint: GET /api/v1/Sale/{id}/\nOperation ID: Sale_retrieve\nدسته‌بندی: Sale","metadata":{"tool_name":"sale_retrieve","category":"Sale","method":"GET","path":"/api/v1/Sale/{id}/","operation_id":"Sale_retrieve","tags":["Sale"],"has_auth":true,"parameters":[{"name":"id","type":"integer","required":true,"description":"یک مقداد عدد یکتا که این فروش/مرجوعی را شناسایی میکند."}],"response_codes":["200: Sale"]}},{"page_content":"Tool: sale_update\nDescription: به‌روزرسانی کامل فروش/مرجوعی\n\nاین متد امکان تغییر همه فیلدهای یک فروش/مرجوعی را فراهم می‌کند.\nتمام فیلدهای قابل ویرایش باید ارسال شوند.\n\nURL Parameters:\n    - pk: شناسه یکتای فروش/مرجوعی\n\nRequest Body:\n    - تمام فیلدهای قابل ویرایش (period, amount, description)\n\nReturns:\n    Response با اطلاعات به‌روزرسانی شده فروش/مرجوعی (status 200)\n\nمثال:\n    PUT /api/v1/Sale/1/\n    {\n        \"period\": 1,\n        \"amount\": \"120000000\",\n        \"description\": \"فروش واحد 101 - به‌روزرسانی شده\"\n    }\n\nنکات:\n    - همه فیلدها باید ارسال شوند\n    - برای به‌روزرسانی جزئی از PATCH استفاده کنید\n    - جزئیات فیلدها در serializer descriptions موجود است\n    - نیاز به احراز هویت دارد\n\nپارامترها:\n- id (int): یک مقداد عدد یکتا که این فروش/مرجوعی را شناسایی میکند. [required]\n- project (int, optional): شناسه پروژه. اگر مشخص نشود، از پروژه جاری session استفاده می‌شود.\n- period (int): شناسه دوره‌ای که فروش/مرجوعی برای آن ثبت می‌شود. دوره باید متعلق به پروژه جاری باشد. (الزامی) [required]\n- amount (str): مبلغ فروش/مرجوعی به تومان. برای جلوگیری از مشکلات دقت، به صورت string ارسال شود. (الزامی) [required]\n- description (str, optional): توضیحات تکمیلی درباره فروش/مرجوعی. (اختیاری)\n\nمثال‌های استفاده:\n- PUT /api/v1/Sale/1/\n- {\n- \"period\": 1,\n- \"amount\": \"120000000\",\n- \"description\": \"فروش واحد 101 - به‌روزرسانی شده\"\n\nنکات مهم:\n- - همه فیلدها باید ارسال شوند\n- - برای به‌روزرسانی جزئی از PATCH استفاده کنید\n- - جزئیات فیلدها در serializer descriptions موجود است\n- - نیاز به احراز هویت دارد\n\nAPI Endpoint: PUT /api/v1/Sale/{id}/\nOperation ID: Sale_update\nدسته‌بندی: Sale","metadata":{"tool_name":"sale_update","category":"Sale","method":"PUT","path":"/api/v1/Sale/{id}/","operation_id":"Sale_update","tags":["Sale"],"has_auth":true,"parameters":[{"name":"id","type":"integer","required":true,"description":"یک مقداد عدد یکتا که این فروش/مرجوعی را شناسایی میکند."},{"name":"project","type":"integer","required":false,"description":"شناسه پروژه. اگر مشخص نشود، از پروژه جاری session استفاده می‌شود."},{"name":"period","type":"integer","required":true,"description":"شناسه دوره‌ای که فروش/مرجوعی برای آن ثبت می‌شود. دوره باید متعلق به پروژه جاری باشد. (الزامی)"},{"name":"amount","type":"string","required":true,"description":"مبلغ فروش/مرجوعی به تومان. برای جلوگیری از مشکلات دقت، به صورت string ارسال شود. (الزامی)"},{"name":"description","type":"string","required":false,"description":"توضیحات تکمیلی درباره فروش/مرجوعی. (اختیاری)"}],"response_codes":["200: Sale"]}},{"page_content":"Tool: sale_partial_update\nDescription: به‌روزرسانی جزئی فروش/مرجوعی\n\nاین متد امکان تغییر بخشی از فیلدهای فروش/مرجوعی را فراهم می‌کند.\nفقط فیلدهای ارسال شده تغییر می‌کنند.\n\nURL Parameters:\n    - pk: شناسه یکتای فروش/مرجوعی\n\nRequest Body:\n    - فیلدهای انتخابی برای به‌روزرسانی\n\nReturns:\n    Response با اطلاعات به‌روزرسانی شده فروش/مرجوعی (status 200)\n\nمثال:\n    PATCH /api/v1/Sale/1/\n    {\n        \"amount\": \"120000000\"\n    }\n\nنکات:\n    - فقط فیلدهای ارسال شده تغییر می‌کنند\n    - فیلدهای ارسال نشده حفظ می‌شوند\n    - انعطاف بیشتری نسبت به PUT دارد\n    - جزئیات فیلدها در serializer descriptions موجود است\n    - نیاز به احراز هویت دارد\n\nپارامترها:\n- id (int): یک مقداد عدد یکتا که این فروش/مرجوعی را شناسایی میکند. [required]\n- project (int, optional): شناسه پروژه. اگر مشخص نشود، از پروژه جاری session استفاده می‌شود.\n- period (int, optional): شناسه دوره‌ای که فروش/مرجوعی برای آن ثبت می‌شود. دوره باید متعلق به پروژه جاری باشد. (الزامی)\n- amount (str, optional): مبلغ فروش/مرجوعی به تومان. برای جلوگیری از مشکلات دقت، به صورت string ارسال شود. (الزامی)\n- description (str, optional): توضیحات تکمیلی درباره فروش/مرجوعی. (اختیاری)\n\nمثال‌های استفاده:\n- PATCH /api/v1/Sale/1/\n- {\n- \"amount\": \"120000000\"\n- }\n\nنکات مهم:\n- - فقط فیلدهای ارسال شده تغییر می‌کنند\n- - فیلدهای ارسال نشده حفظ می‌شوند\n- - انعطاف بیشتری نسبت به PUT دارد\n- - جزئیات فیلدها در serializer descriptions موجود است\n- - نیاز به احراز هویت دارد\n\nAPI Endpoint: PATCH /api/v1/Sale/{id}/\nOperation ID: Sale_partial_update\nدسته‌بندی: Sale","metadata":{"tool_name":"sale_partial_update","category":"Sale","method":"PATCH","path":"/api/v1/Sale/{id}/","operation_id":"Sale_partial_update","tags":["Sale"],"has_auth":true,"parameters":[{"name":"id","type":"integer","required":true,"description":"یک مقداد عدد یکتا که این فروش/مرجوعی را شناسایی میکند."},{"name":"project","type":"integer","required":false,"description":"شناسه پروژه. اگر مشخص نشود، از پروژه جاری session استفاده می‌شود."},{"name":"period","type":"integer","required":false,"description":"شناسه دوره‌ای که فروش/مرجوعی برای آن ثبت می‌شود. دوره باید متعلق به پروژه جاری باشد. (الزامی)"},{"name":"amount","type":"string","required":false,"description":"مبلغ فروش/مرجوعی به تومان. برای جلوگیری از مشکلات دقت، به صورت string ارسال شود. (الزامی)"},{"name":"description","type":"string","required":false,"description":"توضیحات تکمیلی درباره فروش/مرجوعی. (اختیاری)"}],"response_codes":["200: Sale"]}},{"page_content":"Tool: sale_destroy\nDescription: حذف فروش/مرجوعی\n\nاین متد فروش/مرجوعی را به‌طور کامل و برگشت‌ناپذیری حذف می‌کند.\n\nURL Parameters:\n    - pk: شناسه یکتای فروش/مرجوعی\n\nReturns:\n    Response خالی با status 204 No Content در صورت موفقیت\n\nمثال:\n    DELETE /api/v1/Sale/1/\n\nنکات:\n    - حذف برگشت‌ناپذیر است\n    - فقط فروش/مرجوعی‌های پروژه جاری قابل حذف هستند\n    - نیاز به احراز هویت و دسترسی APISecurityPermission دارد\n\nپارامترها:\n- id (int): یک مقداد عدد یکتا که این فروش/مرجوعی را شناسایی میکند. [required]\n\nمثال‌های استفاده:\n- DELETE /api/v1/Sale/1/\n\nنکات مهم:\n- - حذف برگشت‌ناپذیر است\n- - فقط فروش/مرجوعی‌های پروژه جاری قابل حذف هستند\n- - نیاز به احراز هویت و دسترسی APISecurityPermission دارد\n\nAPI Endpoint: DELETE /api/v1/Sale/{id}/\nOperation ID: Sale_destroy\nدسته‌بندی: Sale","metadata":{"tool_name":"sale_destroy","category":"Sale","method":"DELETE","path":"/api/v1/Sale/{id}/","operation_id":"Sale_destroy","tags":["Sale"],"has_auth":true,"parameters":[{"name":"id","type":"integer","required":true,"description":"یک مقداد عدد یکتا که این فروش/مرجوعی را شناسایی میکند."}],"response_codes":[]}},{"page_content":"Tool: sale_total_sales_retrieve\nDescription: دریافت مجموع فروش‌ها\n\nمثال‌های استفاده:\n- sale_total_sales_retrieve()\n\nنکات مهم:\n- نیاز به احراز هویت دارد\n\nAPI Endpoint: GET /api/v1/Sale/total_sales/\nOperation ID: Sale_total_sales_retrieve\nدسته‌بندی: Sale","metadata":{"tool_name":"sale_total_sales_retrieve","category":"Sale","method":"GET","path":"/api/v1/Sale/total_sales/","operation_id":"Sale_total_sales_retrieve","tags":["Sale"],"has_auth":true,"parameters":[],"response_codes":["200: Sale"]}},{"page_content":"Tool: transaction_list\nDescription: دریافت لیست تمام تراکنش‌های پروژه جاری\n\nاین متد لیست تراکنش‌های مرتبط با پروژه فعال را برمی‌گرداند.\nنتایج به صورت صفحه‌بندی شده و قابل فیلتر و مرتب‌سازی هستند.\n\nQuery Parameters:\n    - page: شماره صفحه (پیش‌فرض: 1)\n    - page_size: تعداد رکورد در هر صفحه (پیش‌فرض: 10)\n    - ordering: فیلد مرتب‌سازی\n    - investor: فیلتر بر اساس شناسه سرمایه‌گذار\n    - period: فیلتر بر اساس شناسه دوره\n    - transaction_type: فیلتر بر اساس نوع تراکنش\n\nReturns:\n    Response با ساختار paginated شامل results, count, next, previous\n\nمثال:\n    GET /api/v1/Transaction/?investor=1&transaction_type=principal_deposit\n\nنکات:\n    - فقط تراکنش‌های پروژه جاری برگردانده می‌شود\n    - امکان فیلتر بر اساس سرمایه‌گذار، دوره و نوع تراکنش\n    - نیاز به احراز هویت دارد\n\nپارامترها:\n- investor (int, optional)\n- period (int, optional)\n- project (int, optional)\n- transaction_type (str, optional): * `principal_deposit` - آورده\n* `loan_deposit` - آورده وام\n* `principal_withdrawal` - خروج از سرمایه\n* `profit_accrual` - سود\n\nمثال‌های استفاده:\n- GET /api/v1/Transaction/?investor=1&transaction_type=principal_deposit\n\nنکات مهم:\n- - فقط تراکنش‌های پروژه جاری برگردانده می‌شود\n- - امکان فیلتر بر اساس سرمایه‌گذار، دوره و نوع تراکنش\n- - نیاز به احراز هویت دارد\n\nAPI Endpoint: GET /api/v1/Transaction/\nOperation ID: Transaction_list\nدسته‌بندی: Transaction","metadata":{"tool_name":"transaction_list","category":"Transaction","method":"GET","path":"/api/v1/Transaction/","operation_id":"Transaction_list","tags":["Transaction"],"has_auth":true,"parameters":[{"name":"investor","type":"integer","required":false,"description":""},{"name":"period","type":"integer","required":false,"description":""},{"name":"project","type":"integer","required":false,"description":""},{"name":"transaction_type","type":"string","required":false,"description":"* `principal_deposit` - آورده\n* `loan_deposit` - آورده وام\n* `principal_withdrawal` - خروج از سرمایه\n* `profit_accrual` - سود"}],"response_codes":["200: array"]}},{"page_content":"Tool: transaction_create\nDescription: ایجاد تراکنش جدید برای پروژه جاری\n\nاین متد تراکنش جدید را برای پروژه فعال ثبت می‌کند.\nپروژه به صورت خودکار از session کاربر تعیین می‌شود.\n\nRequest Body:\n    - investor/investor_id (الزامی): شناسه سرمایه‌گذار\n    - period/period_id (الزامی): شناسه دوره\n    - date_shamsi_input یا date_shamsi_raw (الزامی): تاریخ شمسی\n    - amount (الزامی): مبلغ تراکنش (به صورت string)\n    - transaction_type (الزامی): نوع تراکنش\n    - description (اختیاری): توضیحات\n\nReturns:\n    Response با اطلاعات تراکنش ایجاد شده (status 201)\n\nمثال:\n    POST /api/v1/Transaction/\n    {\n        \"investor\": 1,\n        \"period\": 1,\n        \"date_shamsi_input\": \"1403-07-15\",\n        \"amount\": \"50000000\",\n        \"transaction_type\": \"principal_deposit\",\n        \"description\": \"آورده اولیه\"\n    }\n\nنکات:\n    - جزئیات فیلدها در serializer descriptions موجود است\n    - پروژه به صورت خودکار از session تنظیم می‌شود\n    - روز مانده و روز از شروع به صورت خودکار محاسبه می‌شوند\n    - نیاز به احراز هویت و دسترسی APISecurityPermission دارد\n\nپارامترها:\n- date_shamsi_input (str, optional): تاریخ شمسی به فرمت YYYY-MM-DD برای دریافت از frontend. (اختیاری)\n- date_shamsi_raw (str, optional): تاریخ شمسی خام برای دریافت مستقیم از frontend. (اختیاری)\n- amount (str): مبلغ تراکنش به تومان. برای جلوگیری از مشکلات دقت، به صورت string ارسال شود. (الزامی) [required]\n- transaction_type (str): نوع تراکنش. مقادیر معتبر: principal_deposit (آورده), loan_deposit (آورده وام), principal_withdrawal (خروج از سرمایه), profit_accrual (سود). (الزامی)\n\n* `principal_deposit` - آورده\n* `loan_deposit` - آورده وام\n* `principal_withdrawal` - خروج از سرمایه\n* `profit_accrual` - سود [required]\n- description (str, optional): توضیحات تکمیلی درباره تراکنش. (اختیاری)\n- investor (int, optional): شناسه سرمایه‌گذار (جایگزین investor_id). (اختیاری)\n- period (int, optional): شناسه دوره (جایگزین period_id). (اختیاری)\n- investor_id (int, optional): شناسه سرمایه‌گذار. می‌تواند از investor یا investor_id استفاده شود. (اختیاری)\n- period_id (int, optional): شناسه دوره. می‌تواند از period یا period_id استفاده شود. (اختیاری)\n\nمثال‌های استفاده:\n- POST /api/v1/Transaction/\n- {\n- \"investor\": 1,\n- \"period\": 1,\n- \"date_shamsi_input\": \"1403-07-15\",\n\nنکات مهم:\n- - جزئیات فیلدها در serializer descriptions موجود است\n- - پروژه به صورت خودکار از session تنظیم می‌شود\n- - روز مانده و روز از شروع به صورت خودکار محاسبه می‌شوند\n- - نیاز به احراز هویت و دسترسی APISecurityPermission دارد\n\nAPI Endpoint: POST /api/v1/Transaction/\nOperation ID: Transaction_create\nدسته‌بندی: Transaction","metadata":{"tool_name":"transaction_create","category":"Transaction","method":"POST","path":"/api/v1/Transaction/","operation_id":"Transaction_create","tags":["Transaction"],"has_auth":true,"parameters":[{"name":"date_shamsi_input","type":"string","required":false,"description":"تاریخ شمسی به فرمت YYYY-MM-DD برای دریافت از frontend. (اختیاری)"},{"name":"date_shamsi_raw","type":"string","required":false,"description":"تاریخ شمسی خام برای دریافت مستقیم از frontend. (اختیاری)"},{"name":"amount","type":"string","required":true,"description":"مبلغ تراکنش به تومان. برای جلوگیری از مشکلات دقت، به صورت string ارسال شود. (الزامی)"},{"name":"transaction_type","type":"string","required":true,"description":"نوع تراکنش. مقادیر معتبر: principal_deposit (آورده), loan_deposit (آورده وام), principal_withdrawal (خروج از سرمایه), profit_accrual (سود). (الزامی)\n\n* `principal_deposit` - آورده\n* `loan_deposit` - آورده وام\n* `principal_withdrawal` - خروج از سرمایه\n* `profit_accrual` - سود"},{"name":"description","type":"string","required":false,"description":"توضیحات تکمیلی درباره تراکنش. (اختیاری)"},{"name":"investor","type":"integer","required":false,"description":"شناسه سرمایه‌گذار (جایگزین investor_id). (اختیاری)"},{"name":"period","type":"integer","required":false,"description":"شناسه دوره (جایگزین period_id). (اختیاری)"},{"name":"investor_id","type":"integer","required":false,"description":"شناسه سرمایه‌گذار. می‌تواند از investor یا investor_id استفاده شود. (اختیاری)"},{"name":"period_id","type":"integer","required":false,"description":"شناسه دوره. می‌تواند از period یا period_id استفاده شود. (اختیاری)"}],"response_codes":["201: Transaction"]}},{"page_content":"Tool: transaction_retrieve\nDescription: دریافت جزئیات یک تراکنش خاص\n\nاین متد اطلاعات کامل تراکنش با شناسه مشخص شده را برمی‌گرداند.\n\nURL Parameters:\n    - pk: شناسه یکتای تراکنش\n\nReturns:\n    Response با اطلاعات کامل تراکنش شامل investor_data, period_data, project_data\n\nمثال:\n    GET /api/v1/Transaction/1/\n\nنکات:\n    - فقط تراکنش‌های پروژه جاری قابل دسترسی هستند\n    - در صورت عدم دسترسی، خطای 403 برگردانده می‌شود\n    - نیاز به احراز هویت دارد\n\nپارامترها:\n- id (int): یک مقداد عدد یکتا که این تراکنش را شناسایی میکند. [required]\n\nمثال‌های استفاده:\n- GET /api/v1/Transaction/1/\n\nنکات مهم:\n- - فقط تراکنش‌های پروژه جاری قابل دسترسی هستند\n- - در صورت عدم دسترسی، خطای 403 برگردانده می‌شود\n- - نیاز به احراز هویت دارد\n\nAPI Endpoint: GET /api/v1/Transaction/{id}/\nOperation ID: Transaction_retrieve\nدسته‌بندی: Transaction","metadata":{"tool_name":"transaction_retrieve","category":"Transaction","method":"GET","path":"/api/v1/Transaction/{id}/","operation_id":"Transaction_retrieve","tags":["Transaction"],"has_auth":true,"parameters":[{"name":"id","type":"integer","required":true,"description":"یک مقداد عدد یکتا که این تراکنش را شناسایی میکند."}],"response_codes":["200: Transaction"]}},{"page_content":"Tool: transaction_update\nDescription: به‌روزرسانی کامل تراکنش\n\nاین متد امکان تغییر همه فیلدهای یک تراکنش را فراهم می‌کند.\nتمام فیلدهای قابل ویرایش باید ارسال شوند.\n\nURL Parameters:\n    - pk: شناسه یکتای تراکنش\n\nRequest Body:\n    - تمام فیلدهای قابل ویرایش\n\nReturns:\n    Response با اطلاعات به‌روزرسانی شده تراکنش (status 200)\n\nمثال:\n    PUT /api/v1/Transaction/1/\n    {\n        \"investor\": 1,\n        \"period\": 1,\n        \"date_shamsi_input\": \"1403-07-15\",\n        \"amount\": \"60000000\",\n        \"transaction_type\": \"principal_deposit\"\n    }\n\nنکات:\n    - همه فیلدها باید ارسال شوند\n    - برای به‌روزرسانی جزئی از PATCH استفاده کنید\n    - جزئیات فیلدها در serializer descriptions موجود است\n    - نیاز به احراز هویت دارد\n\nپارامترها:\n- id (int): یک مقداد عدد یکتا که این تراکنش را شناسایی میکند. [required]\n- date_shamsi_input (str, optional): تاریخ شمسی به فرمت YYYY-MM-DD برای دریافت از frontend. (اختیاری)\n- date_shamsi_raw (str, optional): تاریخ شمسی خام برای دریافت مستقیم از frontend. (اختیاری)\n- amount (str): مبلغ تراکنش به تومان. برای جلوگیری از مشکلات دقت، به صورت string ارسال شود. (الزامی) [required]\n- transaction_type (str): نوع تراکنش. مقادیر معتبر: principal_deposit (آورده), loan_deposit (آورده وام), principal_withdrawal (خروج از سرمایه), profit_accrual (سود). (الزامی)\n\n* `principal_deposit` - آورده\n* `loan_deposit` - آورده وام\n* `principal_withdrawal` - خروج از سرمایه\n* `profit_accrual` - سود [required]\n- description (str, optional): توضیحات تکمیلی درباره تراکنش. (اختیاری)\n- investor (int, optional): شناسه سرمایه‌گذار (جایگزین investor_id). (اختیاری)\n- period (int, optional): شناسه دوره (جایگزین period_id). (اختیاری)\n- investor_id (int, optional): شناسه سرمایه‌گذار. می‌تواند از investor یا investor_id استفاده شود. (اختیاری)\n- period_id (int, optional): شناسه دوره. می‌تواند از period یا period_id استفاده شود. (اختیاری)\n\nمثال‌های استفاده:\n- PUT /api/v1/Transaction/1/\n- {\n- \"investor\": 1,\n- \"period\": 1,\n- \"date_shamsi_input\": \"1403-07-15\",\n\nنکات مهم:\n- - همه فیلدها باید ارسال شوند\n- - برای به‌روزرسانی جزئی از PATCH استفاده کنید\n- - جزئیات فیلدها در serializer descriptions موجود است\n- - نیاز به احراز هویت دارد\n\nAPI Endpoint: PUT /api/v1/Transaction/{id}/\nOperation ID: Transaction_update\nدسته‌بندی: Transaction","metadata":{"tool_name":"transaction_update","category":"Transaction","method":"PUT","path":"/api/v1/Transaction/{id}/","operation_id":"Transaction_update","tags":["Transaction"],"has_auth":true,"parameters":[{"name":"id","type":"integer","required":true,"description":"یک مقداد عدد یکتا که این تراکنش را شناسایی میکند."},{"name":"date_shamsi_input","type":"string","required":false,"description":"تاریخ شمسی به فرمت YYYY-MM-DD برای دریافت از frontend. (اختیاری)"},{"name":"date_shamsi_raw","type":"string","required":false,"description":"تاریخ شمسی خام برای دریافت مستقیم از frontend. (اختیاری)"},{"name":"amount","type":"string","required":true,"description":"مبلغ تراکنش به تومان. برای جلوگیری از مشکلات دقت، به صورت string ارسال شود. (الزامی)"},{"name":"transaction_type","type":"string","required":true,"description":"نوع تراکنش. مقادیر معتبر: principal_deposit (آورده), loan_deposit (آورده وام), principal_withdrawal (خروج از سرمایه), profit_accrual (سود). (الزامی)\n\n* `principal_deposit` - آورده\n* `loan_deposit` - آورده وام\n* `principal_withdrawal` - خروج از سرمایه\n* `profit_accrual` - سود"},{"name":"description","type":"string","required":false,"description":"توضیحات تکمیلی درباره تراکنش. (اختیاری)"},{"name":"investor","type":"integer","required":false,"description":"شناسه سرمایه‌گذار (جایگزین investor_id). (اختیاری)"},{"name":"period","type":"integer","required":false,"description":"شناسه دوره (جایگزین period_id). (اختیاری)"},{"name":"investor_id","type":"integer","required":false,"description":"شناسه سرمایه‌گذار. می‌تواند از investor یا investor_id استفاده شود. (اختیاری)"},{"name":"period_id","type":"integer","required":false,"description":"شناسه دوره. می‌تواند از period یا period_id استفاده شود. (اختیاری)"}],"response_codes":["200: Transaction"]}},{"page_content":"Tool: transaction_partial_update\nDescription: به‌روزرسانی جزئی تراکنش\n\nاین متد امکان تغییر بخشی از فیلدهای تراکنش را فراهم می‌کند.\nفقط فیلدهای ارسال شده تغییر می‌کنند.\n\nURL Parameters:\n    - pk: شناسه یکتای تراکنش\n\nRequest Body:\n    - فیلدهای انتخابی برای به‌روزرسانی\n\nReturns:\n    Response با اطلاعات به‌روزرسانی شده تراکنش (status 200)\n\nمثال:\n    PATCH /api/v1/Transaction/1/\n    {\n        \"amount\": \"60000000\"\n    }\n\nنکات:\n    - فقط فیلدهای ارسال شده تغییر می‌کنند\n    - فیلدهای ارسال نشده حفظ می‌شوند\n    - انعطاف بیشتری نسبت به PUT دارد\n    - جزئیات فیلدها در serializer descriptions موجود است\n    - نیاز به احراز هویت دارد\n\nپارامترها:\n- id (int): یک مقداد عدد یکتا که این تراکنش را شناسایی میکند. [required]\n- date_shamsi_input (str, optional): تاریخ شمسی به فرمت YYYY-MM-DD برای دریافت از frontend. (اختیاری)\n- date_shamsi_raw (str, optional): تاریخ شمسی خام برای دریافت مستقیم از frontend. (اختیاری)\n- amount (str, optional): مبلغ تراکنش به تومان. برای جلوگیری از مشکلات دقت، به صورت string ارسال شود. (الزامی)\n- transaction_type (str, optional): نوع تراکنش. مقادیر معتبر: principal_deposit (آورده), loan_deposit (آورده وام), principal_withdrawal (خروج از سرمایه), profit_accrual (سود). (الزامی)\n\n* `principal_deposit` - آورده\n* `loan_deposit` - آورده وام\n* `principal_withdrawal` - خروج از سرمایه\n* `profit_accrual` - سود\n- description (str, optional): توضیحات تکمیلی درباره تراکنش. (اختیاری)\n- investor (int, optional): شناسه سرمایه‌گذار (جایگزین investor_id). (اختیاری)\n- period (int, optional): شناسه دوره (جایگزین period_id). (اختیاری)\n- investor_id (int, optional): شناسه سرمایه‌گذار. می‌تواند از investor یا investor_id استفاده شود. (اختیاری)\n- period_id (int, optional): شناسه دوره. می‌تواند از period یا period_id استفاده شود. (اختیاری)\n\nمثال‌های استفاده:\n- PATCH /api/v1/Transaction/1/\n- {\n- \"amount\": \"60000000\"\n- }\n\nنکات مهم:\n- - فقط فیلدهای ارسال شده تغییر می‌کنند\n- - فیلدهای ارسال نشده حفظ می‌شوند\n- - انعطاف بیشتری نسبت به PUT دارد\n- - جزئیات فیلدها در serializer descriptions موجود است\n- - نیاز به احراز هویت دارد\n\nAPI Endpoint: PATCH /api/v1/Transaction/{id}/\nOperation ID: Transaction_partial_update\nدسته‌بندی: Transaction","metadata":{"tool_name":"transaction_partial_update","category":"Transaction","method":"PATCH","path":"/api/v1/Transaction/{id}/","operation_id":"Transaction_partial_update","tags":["Transaction"],"has_auth":true,"parameters":[{"name":"id","type":"integer","required":true,"description":"یک مقداد عدد یکتا که این تراکنش را شناسایی میکند."},{"name":"date_shamsi_input","type":"string","required":false,"description":"تاریخ شمسی به فرمت YYYY-MM-DD برای دریافت از frontend. (اختیاری)"},{"name":"date_shamsi_raw","type":"string","required":false,"description":"تاریخ شمسی خام برای دریافت مستقیم از frontend. (اختیاری)"},{"name":"amount","type":"string","required":false,"description":"مبلغ تراکنش به تومان. برای جلوگیری از مشکلات دقت، به صورت string ارسال شود. (الزامی)"},{"name":"transaction_type","type":"string","required":false,"description":"نوع تراکنش. مقادیر معتبر: principal_deposit (آورده), loan_deposit (آورده وام), principal_withdrawal (خروج از سرمایه), profit_accrual (سود). (الزامی)\n\n* `principal_deposit` - آورده\n* `loan_deposit` - آورده وام\n* `principal_withdrawal` - خروج از سرمایه\n* `profit_accrual` - سود"},{"name":"description","type":"string","required":false,"description":"توضیحات تکمیلی درباره تراکنش. (اختیاری)"},{"name":"investor","type":"integer","required":false,"description":"شناسه سرمایه‌گذار (جایگزین investor_id). (اختیاری)"},{"name":"period","type":"integer","required":false,"description":"شناسه دوره (جایگزین period_id). (اختیاری)"},{"name":"investor_id","type":"integer","required":false,"description":"شناسه سرمایه‌گذار. می‌تواند از investor یا investor_id استفاده شود. (اختیاری)"},{"name":"period_id","type":"integer","required":false,"description":"شناسه دوره. می‌تواند از period یا period_id استفاده شود. (اختیاری)"}],"response_codes":["200: Transaction"]}},{"page_content":"Tool: transaction_destroy\nDescription: حذف تراکنش\n\nاین متد تراکنش را به‌طور کامل و برگشت‌ناپذیری حذف می‌کند.\n\nURL Parameters:\n    - pk: شناسه یکتای تراکنش\n\nReturns:\n    Response خالی با status 204 No Content در صورت موفقیت\n\nمثال:\n    DELETE /api/v1/Transaction/1/\n\nنکات:\n    - حذف برگشت‌ناپذیر است\n    - فقط تراکنش‌های پروژه جاری قابل حذف هستند\n    - نیاز به احراز هویت و دسترسی APISecurityPermission دارد\n\nپارامترها:\n- id (int): یک مقداد عدد یکتا که این تراکنش را شناسایی میکند. [required]\n\nمثال‌های استفاده:\n- DELETE /api/v1/Transaction/1/\n\nنکات مهم:\n- - حذف برگشت‌ناپذیر است\n- - فقط تراکنش‌های پروژه جاری قابل حذف هستند\n- - نیاز به احراز هویت و دسترسی APISecurityPermission دارد\n\nAPI Endpoint: DELETE /api/v1/Transaction/{id}/\nOperation ID: Transaction_destroy\nدسته‌بندی: Transaction","metadata":{"tool_name":"transaction_destroy","category":"Transaction","method":"DELETE","path":"/api/v1/Transaction/{id}/","operation_id":"Transaction_destroy","tags":["Transaction"],"has_auth":true,"parameters":[{"name":"id","type":"integer","required":true,"description":"یک مقداد عدد یکتا که این تراکنش را شناسایی میکند."}],"response_codes":[]}},{"page_content":"Tool: transaction_combined_retrieve\nDescription: دریافت تراکنش‌های اصلی به همراه تراکنش‌های سود مرتبط در یک رکورد\n\nفقط تراکنش‌های اصلی (غیر سود) را برمی‌گرداند\n\nمثال‌های استفاده:\n- transaction_combined_retrieve()\n\nنکات مهم:\n- نیاز به احراز هویت دارد\n\nAPI Endpoint: GET /api/v1/Transaction/combined/\nOperation ID: Transaction_combined_retrieve\nدسته‌بندی: Transaction","metadata":{"tool_name":"transaction_combined_retrieve","category":"Transaction","method":"GET","path":"/api/v1/Transaction/combined/","operation_id":"Transaction_combined_retrieve","tags":["Transaction"],"has_auth":true,"parameters":[],"response_codes":["200: Transaction"]}},{"page_content":"Tool: transaction_detailed_statistics_retrieve\nDescription: دریافت آمار تفصیلی تراکنش‌ها با فیلترهای پیشرفته\n\nمثال‌های استفاده:\n- transaction_detailed_statistics_retrieve()\n\nنکات مهم:\n- نیاز به احراز هویت دارد\n\nAPI Endpoint: GET /api/v1/Transaction/detailed_statistics/\nOperation ID: Transaction_detailed_statistics_retrieve\nدسته‌بندی: Transaction","metadata":{"tool_name":"transaction_detailed_statistics_retrieve","category":"Transaction","method":"GET","path":"/api/v1/Transaction/detailed_statistics/","operation_id":"Transaction_detailed_statistics_retrieve","tags":["Transaction"],"has_auth":true,"parameters":[],"response_codes":["200: Transaction"]}},{"page_content":"Tool: transaction_recalculate_construction_contractor_create\nDescription: محاسبه مجدد همه هزینه‌های پیمان ساختمان\n\nپارامترها:\n- date_shamsi_input (str, optional): تاریخ شمسی به فرمت YYYY-MM-DD برای دریافت از frontend. (اختیاری)\n- date_shamsi_raw (str, optional): تاریخ شمسی خام برای دریافت مستقیم از frontend. (اختیاری)\n- amount (str): مبلغ تراکنش به تومان. برای جلوگیری از مشکلات دقت، به صورت string ارسال شود. (الزامی) [required]\n- transaction_type (str): نوع تراکنش. مقادیر معتبر: principal_deposit (آورده), loan_deposit (آورده وام), principal_withdrawal (خروج از سرمایه), profit_accrual (سود). (الزامی)\n\n* `principal_deposit` - آورده\n* `loan_deposit` - آورده وام\n* `principal_withdrawal` - خروج از سرمایه\n* `profit_accrual` - سود [required]\n- description (str, optional): توضیحات تکمیلی درباره تراکنش. (اختیاری)\n- investor (int, optional): شناسه سرمایه‌گذار (جایگزین investor_id). (اختیاری)\n- period (int, optional): شناسه دوره (جایگزین period_id). (اختیاری)\n- investor_id (int, optional): شناسه سرمایه‌گذار. می‌تواند از investor یا investor_id استفاده شود. (اختیاری)\n- period_id (int, optional): شناسه دوره. می‌تواند از period یا period_id استفاده شود. (اختیاری)\n\nمثال‌های استفاده:\n- transaction_recalculate_construction_contractor_create(date_shamsi_input='value', date_shamsi_raw='value', amount='value', transaction_type='value', description='value')\n\nنکات مهم:\n- نیاز به احراز هویت دارد\n\nAPI Endpoint: POST /api/v1/Transaction/recalculate_construction_contractor/\nOperation ID: Transaction_recalculate_construction_contractor_create\nدسته‌بندی: Transaction","metadata":{"tool_name":"transaction_recalculate_construction_contractor_create","category":"Transaction","method":"POST","path":"/api/v1/Transaction/recalculate_construction_contractor/","operation_id":"Transaction_recalculate_construction_contractor_create","tags":["Transaction"],"has_auth":true,"parameters":[{"name":"date_shamsi_input","type":"string","required":false,"description":"تاریخ شمسی به فرمت YYYY-MM-DD برای دریافت از frontend. (اختیاری)"},{"name":"date_shamsi_raw","type":"string","required":false,"description":"تاریخ شمسی خام برای دریافت مستقیم از frontend. (اختیاری)"},{"name":"amount","type":"string","required":true,"description":"مبلغ تراکنش به تومان. برای جلوگیری از مشکلات دقت، به صورت string ارسال شود. (الزامی)"},{"name":"transaction_type","type":"string","required":true,"description":"نوع تراکنش. مقادیر معتبر: principal_deposit (آورده), loan_deposit (آورده وام), principal_withdrawal (خروج از سرمایه), profit_accrual (سود). (الزامی)\n\n* `principal_deposit` - آورده\n* `loan_deposit` - آورده وام\n* `principal_withdrawal` - خروج از سرمایه\n* `profit_accrual` - سود"},{"name":"description","type":"string","required":false,"description":"توضیحات تکمیلی درباره تراکنش. (اختیاری)"},{"name":"investor","type":"integer","required":false,"description":"شناسه سرمایه‌گذار (جایگزین investor_id). (اختیاری)"},{"name":"period","type":"integer","required":false,"description":"شناسه دوره (جایگزین period_id). (اختیاری)"},{"name":"investor_id","type":"integer","required":false,"description":"شناسه سرمایه‌گذار. می‌تواند از investor یا investor_id استفاده شود. (اختیاری)"},{"name":"period_id","type":"integer","required":false,"description":"شناسه دوره. می‌تواند از period یا period_id استفاده شود. (اختیاری)"}],"response_codes":["200: Transaction"]}},{"page_content":"Tool: transaction_recalculate_profits_create\nDescription: محاسبه مجدد سودها با نرخ سود فعال فعلی برای پروژه فعال\n\nپارامترها:\n- date_shamsi_input (str, optional): تاریخ شمسی به فرمت YYYY-MM-DD برای دریافت از frontend. (اختیاری)\n- date_shamsi_raw (str, optional): تاریخ شمسی خام برای دریافت مستقیم از frontend. (اختیاری)\n- amount (str): مبلغ تراکنش به تومان. برای جلوگیری از مشکلات دقت، به صورت string ارسال شود. (الزامی) [required]\n- transaction_type (str): نوع تراکنش. مقادیر معتبر: principal_deposit (آورده), loan_deposit (آورده وام), principal_withdrawal (خروج از سرمایه), profit_accrual (سود). (الزامی)\n\n* `principal_deposit` - آورده\n* `loan_deposit` - آورده وام\n* `principal_withdrawal` - خروج از سرمایه\n* `profit_accrual` - سود [required]\n- description (str, optional): توضیحات تکمیلی درباره تراکنش. (اختیاری)\n- investor (int, optional): شناسه سرمایه‌گذار (جایگزین investor_id). (اختیاری)\n- period (int, optional): شناسه دوره (جایگزین period_id). (اختیاری)\n- investor_id (int, optional): شناسه سرمایه‌گذار. می‌تواند از investor یا investor_id استفاده شود. (اختیاری)\n- period_id (int, optional): شناسه دوره. می‌تواند از period یا period_id استفاده شود. (اختیاری)\n\nمثال‌های استفاده:\n- transaction_recalculate_profits_create(date_shamsi_input='value', date_shamsi_raw='value', amount='value', transaction_type='value', description='value')\n\nنکات مهم:\n- نیاز به احراز هویت دارد\n\nAPI Endpoint: POST /api/v1/Transaction/recalculate_profits/\nOperation ID: Transaction_recalculate_profits_create\nدسته‌بندی: Transaction","metadata":{"tool_name":"transaction_recalculate_profits_create","category":"Transaction","method":"POST","path":"/api/v1/Transaction/recalculate_profits/","operation_id":"Transaction_recalculate_profits_create","tags":["Transaction"],"has_auth":true,"parameters":[{"name":"date_shamsi_input","type":"string","required":false,"description":"تاریخ شمسی به فرمت YYYY-MM-DD برای دریافت از frontend. (اختیاری)"},{"name":"date_shamsi_raw","type":"string","required":false,"description":"تاریخ شمسی خام برای دریافت مستقیم از frontend. (اختیاری)"},{"name":"amount","type":"string","required":true,"description":"مبلغ تراکنش به تومان. برای جلوگیری از مشکلات دقت، به صورت string ارسال شود. (الزامی)"},{"name":"transaction_type","type":"string","required":true,"description":"نوع تراکنش. مقادیر معتبر: principal_deposit (آورده), loan_deposit (آورده وام), principal_withdrawal (خروج از سرمایه), profit_accrual (سود). (الزامی)\n\n* `principal_deposit` - آورده\n* `loan_deposit` - آورده وام\n* `principal_withdrawal` - خروج از سرمایه\n* `profit_accrual` - سود"},{"name":"description","type":"string","required":false,"description":"توضیحات تکمیلی درباره تراکنش. (اختیاری)"},{"name":"investor","type":"integer","required":false,"description":"شناسه سرمایه‌گذار (جایگزین investor_id). (اختیاری)"},{"name":"period","type":"integer","required":false,"description":"شناسه دوره (جایگزین period_id). (اختیاری)"},{"name":"investor_id","type":"integer","required":false,"description":"شناسه سرمایه‌گذار. می‌تواند از investor یا investor_id استفاده شود. (اختیاری)"},{"name":"period_id","type":"integer","required":false,"description":"شناسه دوره. می‌تواند از period یا period_id استفاده شود. (اختیاری)"}],"response_codes":["200: Transaction"]}},{"page_content":"Tool: transaction_statistics_retrieve\nDescription: دریافت آمار کلی تراکنش‌های پروژه\n\nاین endpoint آمار جامع و کلی تمام تراکنش‌های پروژه جاری را برمی‌گرداند.\n\nخروجی شامل:\n- تعداد کل تراکنش‌ها\n- مجموع آورده‌ها (deposits)\n- مجموع برداشت‌ها (withdrawals)\n- مجموع سود (profits)\n- سرمایه خالص (net principal)\n- مجموع کل (grand total)\n- تعداد سرمایه‌گذاران منحصر به فرد\n\nسناریوهای استفاده:\n- نمایش خلاصه مالی پروژه\n- نمایش داشبورد تراکنش‌ها\n- تحلیل جریان نقدی پروژه\n- محاسبه شاخص‌های مالی کلیدی\n- تهیه گزارش‌های مدیریتی\n\nمثال استفاده:\nGET /api/v1/Transaction/statistics/\n\nمثال خروجی:\n{\n    \"total_transactions\": 150,\n    \"total_deposits\": 500000000,\n    \"total_withdrawals\": -20000000,\n    \"total_profits\": 75000000,\n    \"net_principal\": 480000000,\n    \"grand_total\": 555000000,\n    \"unique_investors\": 5\n}\n\nنکات مهم:\n- فقط تراکنش‌های پروژه جاری را شامل می‌شود\n- اگر پروژه جاری وجود نداشته باشد، خطای 400 برمی‌گرداند\n- مجموع برداشت‌ها به صورت منفی محاسبه می‌شود\n- تمام مبالغ به تومان هستند\n\nسناریوهای استفاده:\n- - نمایش خلاصه مالی پروژه\n- - نمایش داشبورد تراکنش‌ها\n- - تحلیل جریان نقدی پروژه\n- - محاسبه شاخص‌های مالی کلیدی\n- - تهیه گزارش‌های مدیریتی\n\nمثال‌های استفاده:\n- GET /api/v1/Transaction/statistics/\n- {\n- \"total_transactions\": 150,\n- \"total_deposits\": 500000000,\n- \"total_withdrawals\": -20000000,\n\nنکات مهم:\n- - فقط تراکنش‌های پروژه جاری را شامل می‌شود\n- - اگر پروژه جاری وجود نداشته باشد، خطای 400 برمی‌گرداند\n- - مجموع برداشت‌ها به صورت منفی محاسبه می‌شود\n- - تمام مبالغ به تومان هستند\n\nAPI Endpoint: GET /api/v1/Transaction/statistics/\nOperation ID: Transaction_statistics_retrieve\nدسته‌بندی: Transaction","metadata":{"tool_name":"transaction_statistics_retrieve","category":"Transaction","method":"GET","path":"/api/v1/Transaction/statistics/","operation_id":"Transaction_statistics_retrieve","tags":["Transaction"],"has_auth":true,"parameters":[],"response_codes":["200: Transaction"]}},{"page_content":"Tool: unit_list\nDescription: دریافت لیست تمام واحدهای پروژه جاری\n\nاین متد لیست واحدهای مرتبط با پروژه فعال را برمی‌گرداند.\nنتایج به صورت صفحه‌بندی شده و قابل مرتب‌سازی هستند.\n\nQuery Parameters:\n    - page: شماره صفحه (پیش‌فرض: 1)\n    - page_size: تعداد رکورد در هر صفحه (پیش‌فرض: 10)\n    - ordering: فیلد مرتب‌سازی\n\nReturns:\n    Response با ساختار paginated شامل results, count, next, previous\n\nمثال:\n    GET /api/v1/Unit/?page=1&page_size=20\n\nنکات:\n    - فقط واحدهای پروژه جاری برگردانده می‌شود\n    - نیاز به احراز هویت دارد\n\nمثال‌های استفاده:\n- GET /api/v1/Unit/?page=1&page_size=20\n\nنکات مهم:\n- - فقط واحدهای پروژه جاری برگردانده می‌شود\n- - نیاز به احراز هویت دارد\n\nAPI Endpoint: GET /api/v1/Unit/\nOperation ID: Unit_list\nدسته‌بندی: Unit","metadata":{"tool_name":"unit_list","category":"Unit","method":"GET","path":"/api/v1/Unit/","operation_id":"Unit_list","tags":["Unit"],"has_auth":true,"parameters":[],"response_codes":["200: array"]}},{"page_content":"Tool: unit_create\nDescription: ایجاد واحد جدید برای پروژه جاری\n\nاین متد واحد جدید را برای پروژه فعال ثبت می‌کند.\nپروژه به صورت خودکار از session کاربر تعیین می‌شود.\n\nRequest Body:\n    - name (الزامی): نام واحد\n    - area (الزامی): متراژ واحد (به صورت string)\n    - price_per_meter (الزامی): قیمت هر متر (به صورت string)\n    - total_price (الزامی): قیمت نهایی (به صورت string)\n\nReturns:\n    Response با اطلاعات واحد ایجاد شده (status 201)\n\nمثال:\n    POST /api/v1/Unit/\n    {\n        \"name\": \"واحد 101\",\n        \"area\": \"120.5\",\n        \"price_per_meter\": \"5000000\",\n        \"total_price\": \"602500000\"\n    }\n\nنکات:\n    - جزئیات فیلدها در serializer descriptions موجود است\n    - پروژه به صورت خودکار از session تنظیم می‌شود\n    - قیمت نهایی باید برابر area × price_per_meter باشد\n    - نیاز به احراز هویت و دسترسی APISecurityPermission دارد\n\nپارامترها:\n- name (str): نام واحد (مثال: \"واحد 101\" یا \"آپارتمان 2A\"). (الزامی) [required]\n- area (str): متراژ واحد به متر مربع. برای جلوگیری از مشکلات دقت، به صورت string ارسال شود. (الزامی) [required]\n- price_per_meter (str): قیمت هر متر مربع به تومان. برای جلوگیری از مشکلات دقت، به صورت string ارسال شود. (الزامی) [required]\n- total_price (str): قیمت نهایی واحد به تومان (محاسبه شده: area × price_per_meter). برای جلوگیری از مشکلات دقت، به صورت string ارسال شود. (الزامی) [required]\n- project (int, optional): شناسه پروژه. اگر مشخص نشود، از پروژه جاری session استفاده می‌شود.\n\nمثال‌های استفاده:\n- POST /api/v1/Unit/\n- {\n- \"name\": \"واحد 101\",\n- \"area\": \"120.5\",\n- \"price_per_meter\": \"5000000\",\n\nنکات مهم:\n- - جزئیات فیلدها در serializer descriptions موجود است\n- - پروژه به صورت خودکار از session تنظیم می‌شود\n- - قیمت نهایی باید برابر area × price_per_meter باشد\n- - نیاز به احراز هویت و دسترسی APISecurityPermission دارد\n\nAPI Endpoint: POST /api/v1/Unit/\nOperation ID: Unit_create\nدسته‌بندی: Unit","metadata":{"tool_name":"unit_create","category":"Unit","method":"POST","path":"/api/v1/Unit/","operation_id":"Unit_create","tags":["Unit"],"has_auth":true,"parameters":[{"name":"name","type":"string","required":true,"description":"نام واحد (مثال: \"واحد 101\" یا \"آپارتمان 2A\"). (الزامی)"},{"name":"area","type":"string","required":true,"description":"متراژ واحد به متر مربع. برای جلوگیری از مشکلات دقت، به صورت string ارسال شود. (الزامی)"},{"name":"price_per_meter","type":"string","required":true,"description":"قیمت هر متر مربع به تومان. برای جلوگیری از مشکلات دقت، به صورت string ارسال شود. (الزامی)"},{"name":"total_price","type":"string","required":true,"description":"قیمت نهایی واحد به تومان (محاسبه شده: area × price_per_meter). برای جلوگیری از مشکلات دقت، به صورت string ارسال شود. (الزامی)"},{"name":"project","type":"integer","required":false,"description":"شناسه پروژه. اگر مشخص نشود، از پروژه جاری session استفاده می‌شود."}],"response_codes":["201: Unit"]}},{"page_content":"Tool: unit_retrieve\nDescription: دریافت جزئیات یک واحد خاص\n\nاین متد اطلاعات کامل واحد با شناسه مشخص شده را برمی‌گرداند.\n\nURL Parameters:\n    - pk: شناسه یکتای واحد\n\nReturns:\n    Response با اطلاعات کامل واحد\n\nمثال:\n    GET /api/v1/Unit/1/\n\nنکات:\n    - فقط واحدهای پروژه جاری قابل دسترسی هستند\n    - در صورت عدم دسترسی، خطای 403 برگردانده می‌شود\n    - نیاز به احراز هویت دارد\n\nپارامترها:\n- id (int): یک مقداد عدد یکتا که این واحد را شناسایی میکند. [required]\n\nمثال‌های استفاده:\n- GET /api/v1/Unit/1/\n\nنکات مهم:\n- - فقط واحدهای پروژه جاری قابل دسترسی هستند\n- - در صورت عدم دسترسی، خطای 403 برگردانده می‌شود\n- - نیاز به احراز هویت دارد\n\nAPI Endpoint: GET /api/v1/Unit/{id}/\nOperation ID: Unit_retrieve\nدسته‌بندی: Unit","metadata":{"tool_name":"unit_retrieve","category":"Unit","method":"GET","path":"/api/v1/Unit/{id}/","operation_id":"Unit_retrieve","tags":["Unit"],"has_auth":true,"parameters":[{"name":"id","type":"integer","required":true,"description":"یک مقداد عدد یکتا که این واحد را شناسایی میکند."}],"response_codes":["200: Unit"]}},{"page_content":"Tool: unit_update\nDescription: به‌روزرسانی کامل واحد\n\nاین متد امکان تغییر همه فیلدهای یک واحد را فراهم می‌کند.\nتمام فیلدهای قابل ویرایش باید ارسال شوند.\n\nURL Parameters:\n    - pk: شناسه یکتای واحد\n\nRequest Body:\n    - تمام فیلدهای قابل ویرایش\n\nReturns:\n    Response با اطلاعات به‌روزرسانی شده واحد (status 200)\n\nمثال:\n    PUT /api/v1/Unit/1/\n    {\n        \"name\": \"واحد 101\",\n        \"area\": \"125.0\",\n        \"price_per_meter\": \"5500000\",\n        \"total_price\": \"687500000\"\n    }\n\nنکات:\n    - همه فیلدها باید ارسال شوند\n    - برای به‌روزرسانی جزئی از PATCH استفاده کنید\n    - جزئیات فیلدها در serializer descriptions موجود است\n    - نیاز به احراز هویت دارد\n\nپارامترها:\n- id (int): یک مقداد عدد یکتا که این واحد را شناسایی میکند. [required]\n- name (str): نام واحد (مثال: \"واحد 101\" یا \"آپارتمان 2A\"). (الزامی) [required]\n- area (str): متراژ واحد به متر مربع. برای جلوگیری از مشکلات دقت، به صورت string ارسال شود. (الزامی) [required]\n- price_per_meter (str): قیمت هر متر مربع به تومان. برای جلوگیری از مشکلات دقت، به صورت string ارسال شود. (الزامی) [required]\n- total_price (str): قیمت نهایی واحد به تومان (محاسبه شده: area × price_per_meter). برای جلوگیری از مشکلات دقت، به صورت string ارسال شود. (الزامی) [required]\n- project (int, optional): شناسه پروژه. اگر مشخص نشود، از پروژه جاری session استفاده می‌شود.\n\nمثال‌های استفاده:\n- PUT /api/v1/Unit/1/\n- {\n- \"name\": \"واحد 101\",\n- \"area\": \"125.0\",\n- \"price_per_meter\": \"5500000\",\n\nنکات مهم:\n- - همه فیلدها باید ارسال شوند\n- - برای به‌روزرسانی جزئی از PATCH استفاده کنید\n- - جزئیات فیلدها در serializer descriptions موجود است\n- - نیاز به احراز هویت دارد\n\nAPI Endpoint: PUT /api/v1/Unit/{id}/\nOperation ID: Unit_update\nدسته‌بندی: Unit","metadata":{"tool_name":"unit_update","category":"Unit","method":"PUT","path":"/api/v1/Unit/{id}/","operation_id":"Unit_update","tags":["Unit"],"has_auth":true,"parameters":[{"name":"id","type":"integer","required":true,"description":"یک مقداد عدد یکتا که این واحد را شناسایی میکند."},{"name":"name","type":"string","required":true,"description":"نام واحد (مثال: \"واحد 101\" یا \"آپارتمان 2A\"). (الزامی)"},{"name":"area","type":"string","required":true,"description":"متراژ واحد به متر مربع. برای جلوگیری از مشکلات دقت، به صورت string ارسال شود. (الزامی)"},{"name":"price_per_meter","type":"string","required":true,"description":"قیمت هر متر مربع به تومان. برای جلوگیری از مشکلات دقت، به صورت string ارسال شود. (الزامی)"},{"name":"total_price","type":"string","required":true,"description":"قیمت نهایی واحد به تومان (محاسبه شده: area × price_per_meter). برای جلوگیری از مشکلات دقت، به صورت string ارسال شود. (الزامی)"},{"name":"project","type":"integer","required":false,"description":"شناسه پروژه. اگر مشخص نشود، از پروژه جاری session استفاده می‌شود."}],"response_codes":["200: Unit"]}},{"page_content":"Tool: unit_partial_update\nDescription: به‌روزرسانی جزئی واحد\n\nاین متد امکان تغییر بخشی از فیلدهای واحد را فراهم می‌کند.\nفقط فیلدهای ارسال شده تغییر می‌کنند.\n\nURL Parameters:\n    - pk: شناسه یکتای واحد\n\nRequest Body:\n    - فیلدهای انتخابی برای به‌روزرسانی\n\nReturns:\n    Response با اطلاعات به‌روزرسانی شده واحد (status 200)\n\nمثال:\n    PATCH /api/v1/Unit/1/\n    {\n        \"price_per_meter\": \"5500000\"\n    }\n\nنکات:\n    - فقط فیلدهای ارسال شده تغییر می‌کنند\n    - فیلدهای ارسال نشده حفظ می‌شوند\n    - انعطاف بیشتری نسبت به PUT دارد\n    - جزئیات فیلدها در serializer descriptions موجود است\n    - نیاز به احراز هویت دارد\n\nپارامترها:\n- id (int): یک مقداد عدد یکتا که این واحد را شناسایی میکند. [required]\n- name (str, optional): نام واحد (مثال: \"واحد 101\" یا \"آپارتمان 2A\"). (الزامی)\n- area (str, optional): متراژ واحد به متر مربع. برای جلوگیری از مشکلات دقت، به صورت string ارسال شود. (الزامی)\n- price_per_meter (str, optional): قیمت هر متر مربع به تومان. برای جلوگیری از مشکلات دقت، به صورت string ارسال شود. (الزامی)\n- total_price (str, optional): قیمت نهایی واحد به تومان (محاسبه شده: area × price_per_meter). برای جلوگیری از مشکلات دقت، به صورت string ارسال شود. (الزامی)\n- project (int, optional): شناسه پروژه. اگر مشخص نشود، از پروژه جاری session استفاده می‌شود.\n\nمثال‌های استفاده:\n- PATCH /api/v1/Unit/1/\n- {\n- \"price_per_meter\": \"5500000\"\n- }\n\nنکات مهم:\n- - فقط فیلدهای ارسال شده تغییر می‌کنند\n- - فیلدهای ارسال نشده حفظ می‌شوند\n- - انعطاف بیشتری نسبت به PUT دارد\n- - جزئیات فیلدها در serializer descriptions موجود است\n- - نیاز به احراز هویت دارد\n\nAPI Endpoint: PATCH /api/v1/Unit/{id}/\nOperation ID: Unit_partial_update\nدسته‌بندی: Unit","metadata":{"tool_name":"unit_partial_update","category":"Unit","method":"PATCH","path":"/api/v1/Unit/{id}/","operation_id":"Unit_partial_update","tags":["Unit"],"has_auth":true,"parameters":[{"name":"id","type":"integer","required":true,"description":"یک مقداد عدد یکتا که این واحد را شناسایی میکند."},{"name":"name","type":"string","required":false,"description":"نام واحد (مثال: \"واحد 101\" یا \"آپارتمان 2A\"). (الزامی)"},{"name":"area","type":"string","required":false,"description":"متراژ واحد به متر مربع. برای جلوگیری از مشکلات دقت، به صورت string ارسال شود. (الزامی)"},{"name":"price_per_meter","type":"string","required":false,"description":"قیمت هر متر مربع به تومان. برای جلوگیری از مشکلات دقت، به صورت string ارسال شود. (الزامی)"},{"name":"total_price","type":"string","required":false,"description":"قیمت نهایی واحد به تومان (محاسبه شده: area × price_per_meter). برای جلوگیری از مشکلات دقت، به صورت string ارسال شود. (الزامی)"},{"name":"project","type":"integer","required":false,"description":"شناسه پروژه. اگر مشخص نشود، از پروژه جاری session استفاده می‌شود."}],"response_codes":["200: Unit"]}},{"page_content":"Tool: unit_destroy\nDescription: حذف واحد\n\nاین متد واحد را به‌طور کامل و برگشت‌ناپذیری حذف می‌کند.\n\nURL Parameters:\n    - pk: شناسه یکتای واحد\n\nReturns:\n    Response خالی با status 204 No Content در صورت موفقیت\n\nمثال:\n    DELETE /api/v1/Unit/1/\n\nنکات:\n    - حذف برگشت‌ناپذیر است\n    - فقط واحدهای پروژه جاری قابل حذف هستند\n    - نیاز به احراز هویت و دسترسی APISecurityPermission دارد\n    - در صورت وجود وابستگی (سرمایه‌گذاران)، ممکن است حذف ناموفق باشد\n\nپارامترها:\n- id (int): یک مقداد عدد یکتا که این واحد را شناسایی میکند. [required]\n\nمثال‌های استفاده:\n- DELETE /api/v1/Unit/1/\n\nنکات مهم:\n- - حذف برگشت‌ناپذیر است\n- - فقط واحدهای پروژه جاری قابل حذف هستند\n- - نیاز به احراز هویت و دسترسی APISecurityPermission دارد\n- - در صورت وجود وابستگی (سرمایه‌گذاران)، ممکن است حذف ناموفق باشد\n\nAPI Endpoint: DELETE /api/v1/Unit/{id}/\nOperation ID: Unit_destroy\nدسته‌بندی: Unit","metadata":{"tool_name":"unit_destroy","category":"Unit","method":"DELETE","path":"/api/v1/Unit/{id}/","operation_id":"Unit_destroy","tags":["Unit"],"has_auth":true,"parameters":[{"name":"id","type":"integer","required":true,"description":"یک مقداد عدد یکتا که این واحد را شناسایی میکند."}],"response_codes":[]}},{"page_content":"Tool: unit_statistics_retrieve\nDescription: دریافت آمار کلی واحدها\n\nمثال‌های استفاده:\n- unit_statistics_retrieve()\n\nنکات مهم:\n- نیاز به احراز هویت دارد\n\nAPI Endpoint: GET /api/v1/Unit/statistics/\nOperation ID: Unit_statistics_retrieve\nدسته‌بندی: Unit","metadata":{"tool_name":"unit_statistics_retrieve","category":"Unit","method":"GET","path":"/api/v1/Unit/statistics/","operation_id":"Unit_statistics_retrieve","tags":["Unit"],"has_auth":true,"parameters":[],"response_codes":["200: Unit"]}},{"page_content":"Tool: unitspecificexpense_list\nDescription: دریافت لیست تمام هزینه‌های اختصاصی واحدهای پروژه جاری\n\nاین متد لیست هزینه‌های اختصاصی مرتبط با پروژه فعال را برمی‌گرداند.\nنتایج به صورت صفحه‌بندی شده و قابل فیلتر و مرتب‌سازی هستند.\n\nQuery Parameters:\n    - page: شماره صفحه (پیش‌فرض: 1)\n    - page_size: تعداد رکورد در هر صفحه (پیش‌فرض: 10)\n    - ordering: فیلد مرتب‌سازی\n    - unit: فیلتر بر اساس شناسه واحد\n    - project: فیلتر بر اساس شناسه پروژه\n\nReturns:\n    Response با ساختار paginated شامل results, count, next, previous\n\nمثال:\n    GET /api/v1/UnitSpecificExpense/?unit=1&page=1\n\nنکات:\n    - فقط هزینه‌های اختصاصی پروژه جاری برگردانده می‌شود\n    - امکان فیلتر بر اساس واحد\n    - نیاز به احراز هویت دارد\n\nپارامترها:\n- project (int, optional)\n- unit (int, optional)\n\nمثال‌های استفاده:\n- GET /api/v1/UnitSpecificExpense/?unit=1&page=1\n\nنکات مهم:\n- - فقط هزینه‌های اختصاصی پروژه جاری برگردانده می‌شود\n- - امکان فیلتر بر اساس واحد\n- - نیاز به احراز هویت دارد\n\nAPI Endpoint: GET /api/v1/UnitSpecificExpense/\nOperation ID: UnitSpecificExpense_list\nدسته‌بندی: UnitSpecificExpense","metadata":{"tool_name":"unitspecificexpense_list","category":"UnitSpecificExpense","method":"GET","path":"/api/v1/UnitSpecificExpense/","operation_id":"UnitSpecificExpense_list","tags":["UnitSpecificExpense"],"has_auth":true,"parameters":[{"name":"project","type":"integer","required":false,"description":""},{"name":"unit","type":"integer","required":false,"description":""}],"response_codes":["200: array"]}},{"page_content":"Tool: unitspecificexpense_create\nDescription: ایجاد هزینه اختصاصی جدید برای واحد\n\nاین متد هزینه اختصاصی جدید را برای یک واحد ثبت می‌کند.\nپروژه به صورت خودکار از session کاربر تعیین می‌شود.\n\nRequest Body:\n    - unit/unit_id (الزامی): شناسه واحد\n    - title (الزامی): عنوان هزینه\n    - date_shamsi_input (الزامی): تاریخ شمسی (YYYY-MM-DD)\n    - amount (الزامی): مبلغ هزینه (به صورت string)\n    - description (اختیاری): توضیحات\n\nReturns:\n    Response با اطلاعات هزینه اختصاصی ایجاد شده (status 201)\n\nمثال:\n    POST /api/v1/UnitSpecificExpense/\n    {\n        \"unit\": 1,\n        \"title\": \"نصب کولر گازی\",\n        \"date_shamsi_input\": \"1403-07-15\",\n        \"amount\": \"5000000\",\n        \"description\": \"نصب کولر گازی در واحد 101\"\n    }\n\nنکات:\n    - جزئیات فیلدها در serializer descriptions موجود است\n    - پروژه به صورت خودکار از session تنظیم می‌شود\n    - تاریخ میلادی به صورت خودکار محاسبه می‌شود\n    - نیاز به احراز هویت و دسترسی APISecurityPermission دارد\n\nپارامترها:\n- project (int, optional): شناسه پروژه (جایگزین project_id). اگر مشخص نشود، از پروژه جاری session استفاده می‌شود. (اختیاری)\n- project_id (int, optional): شناسه پروژه. اگر مشخص نشود، از پروژه جاری session استفاده می‌شود. (اختیاری)\n- unit (int, optional): شناسه واحد (جایگزین unit_id). (اختیاری)\n- unit_id (int, optional): شناسه واحد. می‌تواند از unit یا unit_id استفاده شود. (اختیاری)\n- title (str): عنوان هزینه اختصاصی واحد (مثال: \"نصب کولر گازی\"). (الزامی) [required]\n- date_shamsi_input (str, optional): تاریخ شمسی به فرمت YYYY-MM-DD برای دریافت از frontend. (اختیاری)\n- amount (str): مبلغ هزینه به تومان. برای جلوگیری از مشکلات دقت، به صورت string ارسال شود. (الزامی) [required]\n- description (str, optional): توضیحات تکمیلی درباره هزینه. (اختیاری)\n\nمثال‌های استفاده:\n- POST /api/v1/UnitSpecificExpense/\n- {\n- \"unit\": 1,\n- \"title\": \"نصب کولر گازی\",\n- \"date_shamsi_input\": \"1403-07-15\",\n\nنکات مهم:\n- - جزئیات فیلدها در serializer descriptions موجود است\n- - پروژه به صورت خودکار از session تنظیم می‌شود\n- - تاریخ میلادی به صورت خودکار محاسبه می‌شود\n- - نیاز به احراز هویت و دسترسی APISecurityPermission دارد\n\nAPI Endpoint: POST /api/v1/UnitSpecificExpense/\nOperation ID: UnitSpecificExpense_create\nدسته‌بندی: UnitSpecificExpense","metadata":{"tool_name":"unitspecificexpense_create","category":"UnitSpecificExpense","method":"POST","path":"/api/v1/UnitSpecificExpense/","operation_id":"UnitSpecificExpense_create","tags":["UnitSpecificExpense"],"has_auth":true,"parameters":[{"name":"project","type":"integer","required":false,"description":"شناسه پروژه (جایگزین project_id). اگر مشخص نشود، از پروژه جاری session استفاده می‌شود. (اختیاری)"},{"name":"project_id","type":"integer","required":false,"description":"شناسه پروژه. اگر مشخص نشود، از پروژه جاری session استفاده می‌شود. (اختیاری)"},{"name":"unit","type":"integer","required":false,"description":"شناسه واحد (جایگزین unit_id). (اختیاری)"},{"name":"unit_id","type":"integer","required":false,"description":"شناسه واحد. می‌تواند از unit یا unit_id استفاده شود. (اختیاری)"},{"name":"title","type":"string","required":true,"description":"عنوان هزینه اختصاصی واحد (مثال: \"نصب کولر گازی\"). (الزامی)"},{"name":"date_shamsi_input","type":"string","required":false,"description":"تاریخ شمسی به فرمت YYYY-MM-DD برای دریافت از frontend. (اختیاری)"},{"name":"amount","type":"string","required":true,"description":"مبلغ هزینه به تومان. برای جلوگیری از مشکلات دقت، به صورت string ارسال شود. (الزامی)"},{"name":"description","type":"string","required":false,"description":"توضیحات تکمیلی درباره هزینه. (اختیاری)"}],"response_codes":["201: UnitSpecificExpense"]}},{"page_content":"Tool: unitspecificexpense_retrieve\nDescription: دریافت جزئیات یک هزینه اختصاصی خاص\n\nاین متد اطلاعات کامل هزینه اختصاصی با شناسه مشخص شده را برمی‌گرداند.\n\nURL Parameters:\n    - pk: شناسه یکتای هزینه اختصاصی\n\nReturns:\n    Response با اطلاعات کامل هزینه اختصاصی شامل unit_data و project_data\n\nمثال:\n    GET /api/v1/UnitSpecificExpense/1/\n\nنکات:\n    - فقط هزینه‌های اختصاصی پروژه جاری قابل دسترسی هستند\n    - در صورت عدم دسترسی، خطای 403 برگردانده می‌شود\n    - نیاز به احراز هویت دارد\n\nپارامترها:\n- id (int): یک مقداد عدد یکتا که این هزینه اختصاصی واحد را شناسایی میکند. [required]\n\nمثال‌های استفاده:\n- GET /api/v1/UnitSpecificExpense/1/\n\nنکات مهم:\n- - فقط هزینه‌های اختصاصی پروژه جاری قابل دسترسی هستند\n- - در صورت عدم دسترسی، خطای 403 برگردانده می‌شود\n- - نیاز به احراز هویت دارد\n\nAPI Endpoint: GET /api/v1/UnitSpecificExpense/{id}/\nOperation ID: UnitSpecificExpense_retrieve\nدسته‌بندی: UnitSpecificExpense","metadata":{"tool_name":"unitspecificexpense_retrieve","category":"UnitSpecificExpense","method":"GET","path":"/api/v1/UnitSpecificExpense/{id}/","operation_id":"UnitSpecificExpense_retrieve","tags":["UnitSpecificExpense"],"has_auth":true,"parameters":[{"name":"id","type":"integer","required":true,"description":"یک مقداد عدد یکتا که این هزینه اختصاصی واحد را شناسایی میکند."}],"response_codes":["200: UnitSpecificExpense"]}},{"page_content":"Tool: unitspecificexpense_update\nDescription: به‌روزرسانی کامل هزینه اختصاصی\n\nاین متد امکان تغییر همه فیلدهای یک هزینه اختصاصی را فراهم می‌کند.\nتمام فیلدهای قابل ویرایش باید ارسال شوند.\n\nURL Parameters:\n    - pk: شناسه یکتای هزینه اختصاصی\n\nRequest Body:\n    - تمام فیلدهای قابل ویرایش\n\nReturns:\n    Response با اطلاعات به‌روزرسانی شده هزینه اختصاصی (status 200)\n\nمثال:\n    PUT /api/v1/UnitSpecificExpense/1/\n    {\n        \"unit\": 1,\n        \"title\": \"نصب کولر گازی - به‌روزرسانی شده\",\n        \"date_shamsi_input\": \"1403-07-15\",\n        \"amount\": \"6000000\"\n    }\n\nنکات:\n    - همه فیلدها باید ارسال شوند\n    - برای به‌روزرسانی جزئی از PATCH استفاده کنید\n    - جزئیات فیلدها در serializer descriptions موجود است\n    - نیاز به احراز هویت دارد\n\nپارامترها:\n- id (int): یک مقداد عدد یکتا که این هزینه اختصاصی واحد را شناسایی میکند. [required]\n- project (int, optional): شناسه پروژه (جایگزین project_id). اگر مشخص نشود، از پروژه جاری session استفاده می‌شود. (اختیاری)\n- project_id (int, optional): شناسه پروژه. اگر مشخص نشود، از پروژه جاری session استفاده می‌شود. (اختیاری)\n- unit (int, optional): شناسه واحد (جایگزین unit_id). (اختیاری)\n- unit_id (int, optional): شناسه واحد. می‌تواند از unit یا unit_id استفاده شود. (اختیاری)\n- title (str): عنوان هزینه اختصاصی واحد (مثال: \"نصب کولر گازی\"). (الزامی) [required]\n- date_shamsi_input (str, optional): تاریخ شمسی به فرمت YYYY-MM-DD برای دریافت از frontend. (اختیاری)\n- amount (str): مبلغ هزینه به تومان. برای جلوگیری از مشکلات دقت، به صورت string ارسال شود. (الزامی) [required]\n- description (str, optional): توضیحات تکمیلی درباره هزینه. (اختیاری)\n\nمثال‌های استفاده:\n- PUT /api/v1/UnitSpecificExpense/1/\n- {\n- \"unit\": 1,\n- \"title\": \"نصب کولر گازی - به‌روزرسانی شده\",\n- \"date_shamsi_input\": \"1403-07-15\",\n\nنکات مهم:\n- - همه فیلدها باید ارسال شوند\n- - برای به‌روزرسانی جزئی از PATCH استفاده کنید\n- - جزئیات فیلدها در serializer descriptions موجود است\n- - نیاز به احراز هویت دارد\n\nAPI Endpoint: PUT /api/v1/UnitSpecificExpense/{id}/\nOperation ID: UnitSpecificExpense_update\nدسته‌بندی: UnitSpecificExpense","metadata":{"tool_name":"unitspecificexpense_update","category":"UnitSpecificExpense","method":"PUT","path":"/api/v1/UnitSpecificExpense/{id}/","operation_id":"UnitSpecificExpense_update","tags":["UnitSpecificExpense"],"has_auth":true,"parameters":[{"name":"id","type":"integer","required":true,"description":"یک مقداد عدد یکتا که این هزینه اختصاصی واحد را شناسایی میکند."},{"name":"project","type":"integer","required":false,"description":"شناسه پروژه (جایگزین project_id). اگر مشخص نشود، از پروژه جاری session استفاده می‌شود. (اختیاری)"},{"name":"project_id","type":"integer","required":false,"description":"شناسه پروژه. اگر مشخص نشود، از پروژه جاری session استفاده می‌شود. (اختیاری)"},{"name":"unit","type":"integer","required":false,"description":"شناسه واحد (جایگزین unit_id). (اختیاری)"},{"name":"unit_id","type":"integer","required":false,"description":"شناسه واحد. می‌تواند از unit یا unit_id استفاده شود. (اختیاری)"},{"name":"title","type":"string","required":true,"description":"عنوان هزینه اختصاصی واحد (مثال: \"نصب کولر گازی\"). (الزامی)"},{"name":"date_shamsi_input","type":"string","required":false,"description":"تاریخ شمسی به فرمت YYYY-MM-DD برای دریافت از frontend. (اختیاری)"},{"name":"amount","type":"string","required":true,"description":"مبلغ هزینه به تومان. برای جلوگیری از مشکلات دقت، به صورت string ارسال شود. (الزامی)"},{"name":"description","type":"string","required":false,"description":"توضیحات تکمیلی درباره هزینه. (اختیاری)"}],"response_codes":["200: UnitSpecificExpense"]}},{"page_content":"Tool: unitspecificexpense_partial_update\nDescription: به‌روزرسانی جزئی هزینه اختصاصی\n\nاین متد امکان تغییر بخشی از فیلدهای هزینه اختصاصی را فراهم می‌کند.\nفقط فیلدهای ارسال شده تغییر می‌کنند.\n\nURL Parameters:\n    - pk: شناسه یکتای هزینه اختصاصی\n\nRequest Body:\n    - فیلدهای انتخابی برای به‌روزرسانی\n\nReturns:\n    Response با اطلاعات به‌روزرسانی شده هزینه اختصاصی (status 200)\n\nمثال:\n    PATCH /api/v1/UnitSpecificExpense/1/\n    {\n        \"amount\": \"6000000\"\n    }\n\nنکات:\n    - فقط فیلدهای ارسال شده تغییر می‌کنند\n    - فیلدهای ارسال نشده حفظ می‌شوند\n    - انعطاف بیشتری نسبت به PUT دارد\n    - جزئیات فیلدها در serializer descriptions موجود است\n    - نیاز به احراز هویت دارد\n\nپارامترها:\n- id (int): یک مقداد عدد یکتا که این هزینه اختصاصی واحد را شناسایی میکند. [required]\n- project (int, optional): شناسه پروژه (جایگزین project_id). اگر مشخص نشود، از پروژه جاری session استفاده می‌شود. (اختیاری)\n- project_id (int, optional): شناسه پروژه. اگر مشخص نشود، از پروژه جاری session استفاده می‌شود. (اختیاری)\n- unit (int, optional): شناسه واحد (جایگزین unit_id). (اختیاری)\n- unit_id (int, optional): شناسه واحد. می‌تواند از unit یا unit_id استفاده شود. (اختیاری)\n- title (str, optional): عنوان هزینه اختصاصی واحد (مثال: \"نصب کولر گازی\"). (الزامی)\n- date_shamsi_input (str, optional): تاریخ شمسی به فرمت YYYY-MM-DD برای دریافت از frontend. (اختیاری)\n- amount (str, optional): مبلغ هزینه به تومان. برای جلوگیری از مشکلات دقت، به صورت string ارسال شود. (الزامی)\n- description (str, optional): توضیحات تکمیلی درباره هزینه. (اختیاری)\n\nمثال‌های استفاده:\n- PATCH /api/v1/UnitSpecificExpense/1/\n- {\n- \"amount\": \"6000000\"\n- }\n\nنکات مهم:\n- - فقط فیلدهای ارسال شده تغییر می‌کنند\n- - فیلدهای ارسال نشده حفظ می‌شوند\n- - انعطاف بیشتری نسبت به PUT دارد\n- - جزئیات فیلدها در serializer descriptions موجود است\n- - نیاز به احراز هویت دارد\n\nAPI Endpoint: PATCH /api/v1/UnitSpecificExpense/{id}/\nOperation ID: UnitSpecificExpense_partial_update\nدسته‌بندی: UnitSpecificExpense","metadata":{"tool_name":"unitspecificexpense_partial_update","category":"UnitSpecificExpense","method":"PATCH","path":"/api/v1/UnitSpecificExpense/{id}/","operation_id":"UnitSpecificExpense_partial_update","tags":["UnitSpecificExpense"],"has_auth":true,"parameters":[{"name":"id","type":"integer","required":true,"description":"یک مقداد عدد یکتا که این هزینه اختصاصی واحد را شناسایی میکند."},{"name":"project","type":"integer","required":false,"description":"شناسه پروژه (جایگزین project_id). اگر مشخص نشود، از پروژه جاری session استفاده می‌شود. (اختیاری)"},{"name":"project_id","type":"integer","required":false,"description":"شناسه پروژه. اگر مشخص نشود، از پروژه جاری session استفاده می‌شود. (اختیاری)"},{"name":"unit","type":"integer","required":false,"description":"شناسه واحد (جایگزین unit_id). (اختیاری)"},{"name":"unit_id","type":"integer","required":false,"description":"شناسه واحد. می‌تواند از unit یا unit_id استفاده شود. (اختیاری)"},{"name":"title","type":"string","required":false,"description":"عنوان هزینه اختصاصی واحد (مثال: \"نصب کولر گازی\"). (الزامی)"},{"name":"date_shamsi_input","type":"string","required":false,"description":"تاریخ شمسی به فرمت YYYY-MM-DD برای دریافت از frontend. (اختیاری)"},{"name":"amount","type":"string","required":false,"description":"مبلغ هزینه به تومان. برای جلوگیری از مشکلات دقت، به صورت string ارسال شود. (الزامی)"},{"name":"description","type":"string","required":false,"description":"توضیحات تکمیلی درباره هزینه. (اختیاری)"}],"response_codes":["200: UnitSpecificExpense"]}},{"page_content":"Tool: unitspecificexpense_destroy\nDescription: حذف هزینه اختصاصی\n\nاین متد هزینه اختصاصی را به‌طور کامل و برگشت‌ناپذیری حذف می‌کند.\n\nURL Parameters:\n    - pk: شناسه یکتای هزینه اختصاصی\n\nReturns:\n    Response خالی با status 204 No Content در صورت موفقیت\n\nمثال:\n    DELETE /api/v1/UnitSpecificExpense/1/\n\nنکات:\n    - حذف برگشت‌ناپذیر است\n    - فقط هزینه‌های اختصاصی پروژه جاری قابل حذف هستند\n    - نیاز به احراز هویت و دسترسی APISecurityPermission دارد\n\nپارامترها:\n- id (int): یک مقداد عدد یکتا که این هزینه اختصاصی واحد را شناسایی میکند. [required]\n\nمثال‌های استفاده:\n- DELETE /api/v1/UnitSpecificExpense/1/\n\nنکات مهم:\n- - حذف برگشت‌ناپذیر است\n- - فقط هزینه‌های اختصاصی پروژه جاری قابل حذف هستند\n- - نیاز به احراز هویت و دسترسی APISecurityPermission دارد\n\nAPI Endpoint: DELETE /api/v1/UnitSpecificExpense/{id}/\nOperation ID: UnitSpecificExpense_destroy\nدسته‌بندی: UnitSpecificExpense","metadata":{"tool_name":"unitspecificexpense_destroy","category":"UnitSpecificExpense","method":"DELETE","path":"/api/v1/UnitSpecificExpense/{id}/","operation_id":"UnitSpecificExpense_destroy","tags":["UnitSpecificExpense"],"has_auth":true,"parameters":[{"name":"id","type":"integer","required":true,"description":"یک مقداد عدد یکتا که این هزینه اختصاصی واحد را شناسایی میکند."}],"response_codes":[]}},{"page_content":"Tool: auth_change_password_create\nDescription: تغییر رمز عبور کاربر\n\nمثال‌های استفاده:\n- auth_change_password_create()\n\nنکات مهم:\n- نیاز به احراز هویت دارد\n\nAPI Endpoint: POST /api/v1/auth/change-password/\nOperation ID: auth_change_password_create\nدسته‌بندی: Authentication","metadata":{"tool_name":"auth_change_password_create","category":"Authentication","method":"POST","path":"/api/v1/auth/change-password/","operation_id":"auth_change_password_create","tags":["Authentication"],"has_auth":true,"parameters":[],"response_codes":["200: object","400: object","401: object","500: object"]}},{"page_content":"Tool: auth_csrf_retrieve\nDescription: دریافت CSRF Token برای استفاده در درخواست‌های بعدی\n\nمثال‌های استفاده:\n- auth_csrf_retrieve()\n\nنکات مهم:\n- نیاز به احراز هویت دارد\n\nAPI Endpoint: GET /api/v1/auth/csrf/\nOperation ID: auth_csrf_retrieve\nدسته‌بندی: Authentication","metadata":{"tool_name":"auth_csrf_retrieve","category":"Authentication","method":"GET","path":"/api/v1/auth/csrf/","operation_id":"auth_csrf_retrieve","tags":["Authentication"],"has_auth":true,"parameters":[],"response_codes":["200: object","500: object"]}},{"page_content":"Tool: auth_login_create\nDescription: ورود کاربر به سیستم و دریافت token\n\nمثال‌های استفاده:\n- auth_login_create()\n\nنکات مهم:\n- نیاز به احراز هویت دارد\n\nAPI Endpoint: POST /api/v1/auth/login/\nOperation ID: auth_login_create\nدسته‌بندی: Authentication","metadata":{"tool_name":"auth_login_create","category":"Authentication","method":"POST","path":"/api/v1/auth/login/","operation_id":"auth_login_create","tags":["Authentication"],"has_auth":true,"parameters":[],"response_codes":["200: object","400: object","401: object","500: object"]}},{"page_content":"Tool: auth_logout_create\nDescription: خروج کاربر از سیستم و حذف token\n\nمثال‌های استفاده:\n- auth_logout_create()\n\nنکات مهم:\n- نیاز به احراز هویت دارد\n\nAPI Endpoint: POST /api/v1/auth/logout/\nOperation ID: auth_logout_create\nدسته‌بندی: Authentication","metadata":{"tool_name":"auth_logout_create","category":"Authentication","method":"POST","path":"/api/v1/auth/logout/","operation_id":"auth_logout_create","tags":["Authentication"],"has_auth":true,"parameters":[],"response_codes":["200: object","500: object"]}},{"page_content":"Tool: auth_register_create\nDescription: ثبت‌نام کاربر جدید (فقط برای ادمین‌ها)\n\nمثال‌های استفاده:\n- auth_register_create()\n\nنکات مهم:\n- نیاز به احراز هویت دارد\n\nAPI Endpoint: POST /api/v1/auth/register/\nOperation ID: auth_register_create\nدسته‌بندی: Authentication","metadata":{"tool_name":"auth_register_create","category":"Authentication","method":"POST","path":"/api/v1/auth/register/","operation_id":"auth_register_create","tags":["Authentication"],"has_auth":true,"parameters":[],"response_codes":["201: object","400: object","403: object","500: object"]}},{"page_content":"Tool: auth_user_retrieve\nDescription: دریافت اطلاعات کاربر احراز هویت شده\n\nمثال‌های استفاده:\n- auth_user_retrieve()\n\nنکات مهم:\n- نیاز به احراز هویت دارد\n\nAPI Endpoint: GET /api/v1/auth/user/\nOperation ID: auth_user_retrieve\nدسته‌بندی: Authentication","metadata":{"tool_name":"auth_user_retrieve","category":"Authentication","method":"GET","path":"/api/v1/auth/user/","operation_id":"auth_user_retrieve","tags":["Authentication"],"has_auth":true,"parameters":[],"response_codes":["200: object","401: object","500: object"]}},{"page_content":"Tool: comprehensive_analysis_retrieve\nDescription: دریافت تحلیل جامع پروژه شامل تمام محاسبات مالی\n\nپارامترها:\n- project_id (int, optional): شناسه پروژه (اختیاری - اگر مشخص نشود از پروژه جاری استفاده می‌شود)\n\nمثال‌های استفاده:\n- comprehensive_analysis_retrieve(project_id=1)\n\nنکات مهم:\n- نیاز به احراز هویت دارد\n\nAPI Endpoint: GET /api/v1/comprehensive/comprehensive_analysis/\nOperation ID: comprehensive_comprehensive_analysis_retrieve\nدسته‌بندی: Analysis","metadata":{"tool_name":"comprehensive_analysis_retrieve","category":"Analysis","method":"GET","path":"/api/v1/comprehensive/comprehensive_analysis/","operation_id":"comprehensive_comprehensive_analysis_retrieve","tags":["Analysis"],"has_auth":true,"parameters":[{"name":"project_id","type":"integer","required":false,"description":"شناسه پروژه (اختیاری - اگر مشخص نشود از پروژه جاری استفاده می‌شود)"}],"response_codes":["200: object","400: object","500: object"]}},{"page_content":"Tool: status_retrieve\nDescription: بررسی وضعیت API و اطلاعات کاربر\n\nمثال‌های استفاده:\n- status_retrieve()\n\nنکات مهم:\n- نیاز به احراز هویت دارد\n\nAPI Endpoint: GET /api/v1/status/\nOperation ID: status_retrieve\nدسته‌بندی: Authentication","metadata":{"tool_name":"status_retrieve","category":"Authentication","method":"GET","path":"/api/v1/status/","operation_id":"status_retrieve","tags":["Authentication"],"has_auth":true,"parameters":[],"response_codes":["200: object","500: object"]}}]